Workbook

Sheet Board Dashboard
A1: Board Dashboard - AI Security and Governance Posture
A2: Board-level summary of AI governance, risk, compliance, service delivery and strategic posture. Owner: AI Security Manager. Reporting period: Q1 2026 (as at 02/05/2026).
A3: Navigation: Board Pack Notes | Operational Dashboard | Executive Report | TOM Index | ID Glossary
A5: 1. Headline Posture
A6: ISO 42001 Control Implementation | D6: Maturity vs Target | G6: Total Residual Exposure (GBP M) | J6: High/Critical Residual Risks
A7: =IFERROR('Compliance Mapping'!U16,"N/A") -> 0.75 | D7: =IFERROR(SUM('Maturity Assessment'!D4:D12)/SUM('Maturity Assessment'!F4:F12),"N/A") -> 0.76470588 | G7: =IFERROR(SUM('Risk Quantification'!L5:L17),"N/A") -> 53.7 | J7: =COUNTIF('Risk Quantification'!K5:K17,">="&15) -> 0
A8: Controls implemented / total (16 controls in scope) | D8: Composite of 9 domains vs target | G8: Sum of quantified residual exposure (13 risks) | J8: Risks with residual score >=15 (max 25)
A10: KRI Breaches (Red + Amber) | D10: Open High-Severity Incidents | G10: Overdue Roadmap Items | J10: Tier-1 Vendor DD Currency
A11: =COUNTIF('KRI Tracking'!J5:J13,"Red")+COUNTIF('KRI Tracking'!J5:J13,"Amber") -> 2 | D11: =COUNTIFS('Incident Analysis'!D5:D12,"Sev 1",'Incident Analysis'!M5:M12,"<>Closed")+COUNTIFS('Incident Analysis'!D5:D12,"Sev 2",'Incident Analysis'!M5:M12,"<>Closed") -> 0 | G11: =COUNTIF('Implementation Roadmap'!H5:H16,"Delayed") -> 0 | J11: =IFERROR(COUNTIFS('Third-Party Risk Services'!G5:G20,"Complete",'Third-Party Risk Services'!N5:N20,"High*")/COUNTIF('Third-Party Risk Services'!N5:N20,"High*"),"N/A") -> 1
A12: KRIs above amber or red threshold | D12: Sev 1/2 incidents open or under review (90d) | G12: Roadmap items with Delayed status | J12: High-criticality vendors with DD complete
A14: 2. Top 5 Material Risks (by Quantified Residual Exposure)
A15: Risk ID | C15: Risk Title | G15: Residual Score | H15: Exposure (GBP M) | I15: Treatment | J15: Treatment Action | K15: Owner
A16: ='Risk Quantification'!A15 -> RSK-011 | C16: ='Risk Quantification'!B15 -> Regulatory breach (Consumer Duty / fairness / FCA) | G16: ='Risk Quantification'!K15 -> 10 | H16: ='Risk Quantification'!L15 -> 7.5 | I16: ='Risk Quantification'!M15 -> Mitigate | J16: ='Risk Quantification'!N15 -> ACT-012 | K16: =IFERROR(INDEX('Implementation Roadmap'!E$5:E$16,MATCH('Risk Quantification'!N15,'Implementation Roadmap'!A$5:A$16,0)),"See Action") -> See Action
A17: ='Risk Quantification'!A5 -> RSK-001 | C17: ='Risk Quantification'!B5 -> Model performance drift causing pricing/UW losses | G17: ='Risk Quantification'!K5 -> 8 | H17: ='Risk Quantification'!L5 -> 6.5 | I17: ='Risk Quantification'!M5 -> Mitigate | J17: ='Risk Quantification'!N5 -> ACT-001 | K17: =IFERROR(INDEX('Implementation Roadmap'!E$5:E$16,MATCH('Risk Quantification'!N5,'Implementation Roadmap'!A$5:A$16,0)),"See Action") -> See Action
A18: ='Risk Quantification'!A14 -> RSK-010 | C18: ='Risk Quantification'!B14 -> Cloud misconfiguration exposing AI workloads | G18: ='Risk Quantification'!K14 -> 10 | H18: ='Risk Quantification'!L14 -> 6 | I18: ='Risk Quantification'!M14 -> Mitigate | J18: ='Risk Quantification'!N14 -> ACT-011 | K18: =IFERROR(INDEX('Implementation Roadmap'!E$5:E$16,MATCH('Risk Quantification'!N14,'Implementation Roadmap'!A$5:A$16,0)),"See Action") -> See Action
A19: ='Risk Quantification'!A8 -> RSK-004 | C19: ='Risk Quantification'!B8 -> Pricing/fairness bias against protected groups | G19: ='Risk Quantification'!K8 -> 8 | H19: ='Risk Quantification'!L8 -> 5.5 | I19: ='Risk Quantification'!M8 -> Mitigate | J19: ='Risk Quantification'!N8 -> ACT-006 | K19: =IFERROR(INDEX('Implementation Roadmap'!E$5:E$16,MATCH('Risk Quantification'!N8,'Implementation Roadmap'!A$5:A$16,0)),"See Action") -> See Action
A20: ='Risk Quantification'!A9 -> RSK-005 | C20: ='Risk Quantification'!B9 -> LLM hallucination delivered to customer | G20: ='Risk Quantification'!K9 -> 8 | H20: ='Risk Quantification'!L9 -> 4.8 | I20: ='Risk Quantification'!M9 -> Mitigate | J20: ='Risk Quantification'!N9 -> ACT-007 | K20: =IFERROR(INDEX('Implementation Roadmap'!E$5:E$16,MATCH('Risk Quantification'!N9,'Implementation Roadmap'!A$5:A$16,0)),"See Action") -> See Action
A22: 3. Maturity by Domain (Current vs Target)
A23: Domain ID | C23: Domain | G23: Current | H23: Level | I23: Target | J23: Gap | K23: Owner
A24: ='Maturity Assessment'!A4 -> Domain ID | C24: ='Maturity Assessment'!B4 -> Domain | G24: ='Maturity Assessment'!D4 -> Current Maturity (1-5) | H24: ='Maturity Assessment'!E4 -> Current Level | I24: ='Maturity Assessment'!F4 -> Target Maturity (1-5) | J24: ='Maturity Assessment'!H4 -> Gap | K24: ='Maturity Assessment'!K4 -> Owner
A25: ='Maturity Assessment'!A5 -> MAT-01 | C25: ='Maturity Assessment'!B5 -> Governance | G25: ='Maturity Assessment'!D5 -> 4 | H25: ='Maturity Assessment'!E5 -> Managed | I25: ='Maturity Assessment'!F5 -> 5 | J25: ='Maturity Assessment'!H5 -> 1 | K25: ='Maturity Assessment'!K5 -> Andrew Pollard
A26: ='Maturity Assessment'!A6 -> MAT-02 | C26: ='Maturity Assessment'!B6 -> Risk Management | G26: ='Maturity Assessment'!D6 -> 3 | H26: ='Maturity Assessment'!E6 -> Defined | I26: ='Maturity Assessment'!F6 -> 4 | J26: ='Maturity Assessment'!H6 -> 1 | K26: ='Maturity Assessment'!K6 -> Geoffrey Sanders
A27: ='Maturity Assessment'!A7 -> MAT-03 | C27: ='Maturity Assessment'!B7 -> Security Controls | G27: ='Maturity Assessment'!D7 -> 4 | H27: ='Maturity Assessment'!E7 -> Managed | I27: ='Maturity Assessment'!F7 -> 5 | J27: ='Maturity Assessment'!H7 -> 1 | K27: ='Maturity Assessment'!K7 -> Karen Holloway
A28: ='Maturity Assessment'!A8 -> MAT-04 | C28: ='Maturity Assessment'!B8 -> Privacy and Data Handling | G28: ='Maturity Assessment'!D8 -> 3 | H28: ='Maturity Assessment'!E8 -> Defined | I28: ='Maturity Assessment'!F8 -> 4 | J28: ='Maturity Assessment'!H8 -> 1 | K28: ='Maturity Assessment'!K8 -> Rebecca Lloyd
A29: ='Maturity Assessment'!A9 -> MAT-05 | C29: ='Maturity Assessment'!B9 -> Monitoring and Assurance | G29: ='Maturity Assessment'!D9 -> 3 | H29: ='Maturity Assessment'!E9 -> Defined | I29: ='Maturity Assessment'!F9 -> 4 | J29: ='Maturity Assessment'!H9 -> 1 | K29: ='Maturity Assessment'!K9 -> Mohammed Iqbal
A30: ='Maturity Assessment'!A10 -> MAT-06 | C30: ='Maturity Assessment'!B10 -> Third-Party Oversight | G30: ='Maturity Assessment'!D10 -> 3 | H30: ='Maturity Assessment'!E10 -> Defined | I30: ='Maturity Assessment'!F10 -> 4 | J30: ='Maturity Assessment'!H10 -> 1 | K30: ='Maturity Assessment'!K10 -> Sarah Mitchell
A31: ='Maturity Assessment'!A11 -> MAT-07 | C31: ='Maturity Assessment'!B11 -> Lifecycle Management | G31: ='Maturity Assessment'!D11 -> 3 | H31: ='Maturity Assessment'!E11 -> Defined | I31: ='Maturity Assessment'!F11 -> 4 | J31: ='Maturity Assessment'!H11 -> 1 | K31: ='Maturity Assessment'!K11 -> Daniel O'Reilly
A32: ='Maturity Assessment'!A12 -> MAT-08 | C32: ='Maturity Assessment'!B12 -> Resilience and Continuity | G32: ='Maturity Assessment'!D12 -> 3 | H32: ='Maturity Assessment'!E12 -> Defined | I32: ='Maturity Assessment'!F12 -> 4 | J32: ='Maturity Assessment'!H12 -> 1 | K32: ='Maturity Assessment'!K12 -> Yvonne Mathieson
A33: Average / Total | G33: =AVERAGE(G24:G32) -> 3.25 | I33: =AVERAGE(I24:I32) -> 4.25 | J33: =SUM(J24:J32) -> 8
A35: 4. Key Risk Indicators (KRI) Summary
A36: KRI ID | C36: KRI Name | F36: Current | G36: Amber | H36: Red | I36: Trend | J36: Status | K36: Owner
A37: ='KRI Tracking'!A5 -> KRI-001 | C37: ='KRI Tracking'!B5 -> Models with material drift in last 30 days | F37: ='KRI Tracking'!G5 -> 1 | G37: ='KRI Tracking'!E5 -> 2 | H37: ='KRI Tracking'!F5 -> 4 | I37: ='KRI Tracking'!I5 -> Improving | J37: ='KRI Tracking'!J5 -> Green | K37: ='KRI Tracking'!K5 -> Mohammed Iqbal
A38: ='KRI Tracking'!A6 -> KRI-002 | C38: ='KRI Tracking'!B6 -> Tier-1 models without current monitoring coverage | F38: ='KRI Tracking'!G6 -> 0 | G38: ='KRI Tracking'!E6 -> 1 | H38: ='KRI Tracking'!F6 -> 2 | I38: ='KRI Tracking'!I6 -> Stable | J38: ='KRI Tracking'!J6 -> Green | K38: ='KRI Tracking'!K6 -> Mohammed Iqbal
A39: ='KRI Tracking'!A7 -> KRI-003 | C39: ='KRI Tracking'!B7 -> Pricing fairness review breaches outstanding | F39: ='KRI Tracking'!G7 -> 0 | G39: ='KRI Tracking'!E7 -> 1 | H39: ='KRI Tracking'!F7 -> 3 | I39: ='KRI Tracking'!I7 -> Stable | J39: ='KRI Tracking'!J7 -> Green | K39: ='KRI Tracking'!K7 -> Helen Carter
A40: ='KRI Tracking'!A8 -> KRI-004 | C40: ='KRI Tracking'!B8 -> Customer-facing AI complaints linked to AI behaviour (rolling 90d) | F40: ='KRI Tracking'!G8 -> 3 | G40: ='KRI Tracking'!E8 -> 5 | H40: ='KRI Tracking'!F8 -> 10 | I40: ='KRI Tracking'!I8 -> Improving | J40: ='KRI Tracking'!J8 -> Green | K40: ='KRI Tracking'!K8 -> Olivia Bennett
A41: ='KRI Tracking'!A9 -> KRI-005 | C41: ='KRI Tracking'!B9 -> Vulnerable customer cases handled outside specialist team | F41: ='KRI Tracking'!G9 -> 1 | G41: ='KRI Tracking'!E9 -> 2 | H41: ='KRI Tracking'!F9 -> 5 | I41: ='KRI Tracking'!I9 -> Stable | J41: ='KRI Tracking'!J9 -> Green | K41: ='KRI Tracking'!K9 -> Olivia Bennett
A42: ='KRI Tracking'!A10 -> KRI-006 | C42: ='KRI Tracking'!B10 -> Sanctions/fraud false-negative incidents (rolling 90d) | F42: ='KRI Tracking'!G10 -> 0 | G42: ='KRI Tracking'!E10 -> 1 | H42: ='KRI Tracking'!F10 -> 2 | I42: ='KRI Tracking'!I10 -> Improving | J42: ='KRI Tracking'!J10 -> Green | K42: ='KRI Tracking'!K10 -> Helen Carter
A43: ='KRI Tracking'!A11 -> KRI-007 | C43: ='KRI Tracking'!B11 -> DLP exceptions raised on GenAI tools (per month) | F43: ='KRI Tracking'!G11 -> 14 | G43: ='KRI Tracking'!E11 -> 10 | H43: ='KRI Tracking'!F11 -> 20 | I43: ='KRI Tracking'!I11 -> Deteriorating | J43: ='KRI Tracking'!J11 -> Amber | K43: ='KRI Tracking'!K11 -> Karen Holloway
A44: ='KRI Tracking'!A12 -> KRI-008 | C44: ='KRI Tracking'!B12 -> Document AI extraction reject rate | F44: ='KRI Tracking'!G12 -> 3 | G44: ='KRI Tracking'!E12 -> 4 | H44: ='KRI Tracking'!F12 -> 8 | I44: ='KRI Tracking'!I12 -> Stable | J44: ='KRI Tracking'!J12 -> Green | K44: ='KRI Tracking'!K12 -> Mohammed Iqbal
A45: ='KRI Tracking'!A13 -> KRI-009 | C45: ='KRI Tracking'!B13 -> Cloud configuration drift on AI workloads | F45: ='KRI Tracking'!G13 -> 2 | G45: ='KRI Tracking'!E13 -> 2 | H45: ='KRI Tracking'!F13 -> 5 | I45: ='KRI Tracking'!I13 -> Stable | J45: ='KRI Tracking'!J13 -> Amber | K45: ='KRI Tracking'!K13 -> Karen Holloway
A47: 5. Incident Summary (Rolling 90 Days)
A48: Total Incidents | D48: Sev 1/2 Incidents | G48: Currently Open | J48: Vendor-Driven
A49: ='Incident Analysis'!Q5 -> 8 | D49: ='Incident Analysis'!Q6+'Incident Analysis'!Q7 -> 4 | G49: ='Incident Analysis'!Q10 -> 0 | J49: ='Incident Analysis'!Q11 -> 1
A50: All incidents in 90-day window | D50: High-severity incidents | G50: Open or under review | J50: Incidents caused by vendor
A52: 6. Third-Party AI Risk Hotspots (Amber/Red Vendors)
A53: Vendor ID | C53: Supplier | F53: Action Required | I53: Residual | K53: Owner
A54: ='Third-Party Risk Services'!A5 -> VEN-001 | C54: ='Third-Party Risk Services'!B5 -> Microsoft (Azure OpenAI / M365 Copilot) | F54: ='Third-Party Risk Services'!M5 -> Quarterly subprocessor review; refresh DPIA after RDM-002 | I54: ='Third-Party Risk Services'!K5 -> Amber | K54: ='Third-Party Risk Services'!O5 -> Sarah Mitchell
A55: ='Third-Party Risk Services'!A7 -> VEN-003 | C55: ='Third-Party Risk Services'!B7 -> ABBYY | F55: ='Third-Party Risk Services'!M7 -> Complete privacy review by 30/06/2026 (ACT-002) | I55: ='Third-Party Risk Services'!K7 -> Amber | K55: ='Third-Party Risk Services'!O7 -> Sarah Mitchell
A56: ='Third-Party Risk Services'!A11 -> VEN-007 | C56: ='Third-Party Risk Services'!B11 -> Tractable | F56: ='Third-Party Risk Services'!M11 -> Complete security review (ACT-005) | I56: ='Third-Party Risk Services'!K11 -> Amber | K56: ='Third-Party Risk Services'!O11 -> Sarah Mitchell
A57: ='Third-Party Risk Services'!A16 -> VEN-012 | C57: ='Third-Party Risk Services'!B16 -> Hugging Face Enterprise | F57: ='Third-Party Risk Services'!M16 -> Complete DD by 30/06/2026 (ACT-009) | I57: ='Third-Party Risk Services'!K16 -> Amber | K57: ='Third-Party Risk Services'!O16 -> Mohammed Iqbal
A58: ='Third-Party Risk Services'!A17 -> VEN-013 | C58: ='Third-Party Risk Services'!B17 -> Persistent Systems | F58: ='Third-Party Risk Services'!M17 -> Update contract clauses for AI; finalise renewal (ACT-008) | I58: ='Third-Party Risk Services'!K17 -> Amber | K58: ='Third-Party Risk Services'!O17 -> Sarah Mitchell
A59: ='Third-Party Risk Services'!A19 -> VEN-015 | C59: ='Third-Party Risk Services'!B19 -> Splunk | F59: ='Third-Party Risk Services'!M19 -> Complete migration by Q4 2026 (RDM-010) | I59: ='Third-Party Risk Services'!K19 -> Amber | K59: ='Third-Party Risk Services'!O19 -> Karen Holloway
A61: 7. Key Decisions Required This Quarter
A62: Decision ID | C62: Decision | G62: Forum | I62: Owner | K62: Decision By
A63: DEC-Q1-01 | C63: Approve closure plan for 4 major-NC-risk areas (CA-009, CA-010, CA-011, CA-014) | G63: AI Governance Forum | I63: Sarah Mitchell | K63: 30/06/2026
A64: DEC-Q1-02 | C64: Approve Tier-1 vendor exit plans (VEN-001 Microsoft, VEN-006 Sentinel) | G64: Third-Party Oversight Forum | I64: Sarah Mitchell | K64: 30/09/2026
A65: DEC-Q1-03 | C65: Approve net hire of 5 FTE to close resource gap | G65: ExCo | I65: Sarah Mitchell | K65: 30/06/2026
A66: DEC-Q1-04 | C66: Reset risk appetite for residual AI risk pending refreshed quantification (RDM-012) | G66: Risk Committee Board | I66: Geoffrey Sanders | K66: 30/09/2026
A67: DEC-Q1-05 | C67: Approve ISO 42001 readiness review pack and certification path | G67: ExCo / Risk Committee | I67: Sarah Mitchell | K67: 31/01/2027
A68: DEC-Q1-06 | C68: Approve Salesforce Einstein-feature posture | G68: AI Governance Forum | I68: Olivia Bennett | K68: 30/06/2026
A70: 8. Implementation Roadmap Summary
A71: Roadmap ID | C71: Workstream / Milestone | F71: Phase | G71: Status | H71: % Complete | I71: End Date | J71: Owner | K71: Commentary
A72: ='Implementation Roadmap'!A5 -> RDM-001 | C72: ='Implementation Roadmap'!B5&" - "&'Implementation Roadmap'!C5 -> Customer-Facing AI Uplift - Customer-facing AI guardrail uplift (output filter, hallucination QA, complaint linkage) | F72: ='Implementation Roadmap'!J5 -> Phase 2 - Embed | G72: ='Implementation Roadmap'!H5 -> In Progress | H72: ='Implementation Roadmap'!I5 -> 0.55 | I72: ='Implementation Roadmap'!G5 -> 30/09/2026 | J72: ='Implementation Roadmap'!E5 -> Olivia Bennett | K72: ='Implementation Roadmap'!L5 -> Salesforce Einstein-feature decision pending
A73: ='Implementation Roadmap'!A6 -> RDM-002 | C73: ='Implementation Roadmap'!B6&" - "&'Implementation Roadmap'!C6 -> GenAI Productivity - GenAI productivity tooling sensitivity-label remediation programme | F73: ='Implementation Roadmap'!J6 -> Phase 2 - Embed | G73: ='Implementation Roadmap'!H6 -> In Progress | H73: ='Implementation Roadmap'!I6 -> 0.4 | I73: ='Implementation Roadmap'!G6 -> 31/12/2026 | J73: ='Implementation Roadmap'!E6 -> Karen Holloway | K73: ='Implementation Roadmap'!L6 -> Closes legacy SharePoint label gap
A74: ='Implementation Roadmap'!A7 -> RDM-003 | C74: ='Implementation Roadmap'!B7&" - "&'Implementation Roadmap'!C7 -> Pricing/UW Assurance - Pricing fairness review programme uplift; bias testing harness | F74: ='Implementation Roadmap'!J7 -> Phase 2 - Embed | G74: ='Implementation Roadmap'!H7 -> On Track | H74: ='Implementation Roadmap'!I7 -> 0.3 | I74: ='Implementation Roadmap'!G7 -> 30/06/2027 | J74: ='Implementation Roadmap'!E7 -> Helen Carter | K74: ='Implementation Roadmap'!L7 -> Embedded in pricing committee
A75: ='Implementation Roadmap'!A8 -> RDM-004 | C75: ='Implementation Roadmap'!B8&" - "&'Implementation Roadmap'!C8 -> Claims AI Resilience - Tier 2 DR plan refresh and tabletop exercise programme | F75: ='Implementation Roadmap'!J8 -> Phase 2 - Embed | G75: ='Implementation Roadmap'!H8 -> On Track | H75: ='Implementation Roadmap'!I8 -> 0.25 | I75: ='Implementation Roadmap'!G8 -> 31/12/2026 | J75: ='Implementation Roadmap'!E8 -> James Whitfield | K75: ='Implementation Roadmap'!L8 -> Aligned with PRA operational resilience
A76: ='Implementation Roadmap'!A9 -> RDM-005 | C76: ='Implementation Roadmap'!B9&" - "&'Implementation Roadmap'!C9 -> Third-Party Oversight - Vendor exit planning for Tier-1 AI providers (incl. VEN-001 and VEN-006) | F76: ='Implementation Roadmap'!J9 -> Phase 2 - Embed | G76: ='Implementation Roadmap'!H9 -> On Track | H76: ='Implementation Roadmap'!I9 -> 0.2 | I76: ='Implementation Roadmap'!G9 -> 30/06/2027 | J76: ='Implementation Roadmap'!E9 -> Sarah Mitchell | K76: ='Implementation Roadmap'!L9 -> Two plans drafted; remainder due
A77: ='Implementation Roadmap'!A10 -> RDM-006 | C77: ='Implementation Roadmap'!B10&" - "&'Implementation Roadmap'!C10 -> Document AI Hardening - Vendor change-window controls and QA harness expansion | F77: ='Implementation Roadmap'!J10 -> Phase 2 - Embed | G77: ='Implementation Roadmap'!H10 -> On Track | H77: ='Implementation Roadmap'!I10 -> 0.15 | I77: ='Implementation Roadmap'!G10 -> 30/11/2026 | J77: ='Implementation Roadmap'!E10 -> Mohammed Iqbal | K77: ='Implementation Roadmap'!L10 -> Triggered by INC-008
A78: ='Implementation Roadmap'!A11 -> RDM-007 | C78: ='Implementation Roadmap'!B11&" - "&'Implementation Roadmap'!C11 -> ISO 42001 Readiness - ISO/IEC 42001 internal readiness assessment and remediation | F78: ='Implementation Roadmap'!J11 -> Phase 1 - Foundation | G78: ='Implementation Roadmap'!H11 -> On Track | H78: ='Implementation Roadmap'!I11 -> 0.5 | I78: ='Implementation Roadmap'!G11 -> 31/12/2026 | J78: ='Implementation Roadmap'!E11 -> Sarah Mitchell | K78: ='Implementation Roadmap'!L11 -> Aimed at certification readiness Q1 2027
A79: ='Implementation Roadmap'!A12 -> RDM-008 | C79: ='Implementation Roadmap'!B12&" - "&'Implementation Roadmap'!C12 -> Lifecycle Management - AI lifecycle management framework v2 (intake-to-retirement playbooks) | F79: ='Implementation Roadmap'!J12 -> Phase 1 - Foundation | G79: ='Implementation Roadmap'!H12 -> In Progress | H79: ='Implementation Roadmap'!I12 -> 0.45 | I79: ='Implementation Roadmap'!G12 -> 31/10/2026 | J79: ='Implementation Roadmap'!E12 -> Daniel O'Reilly | K79: ='Implementation Roadmap'!L12 -> Embeds quarterly review cadence
A80: ='Implementation Roadmap'!A13 -> RDM-009 | C80: ='Implementation Roadmap'!B13&" - "&'Implementation Roadmap'!C13 -> AI Knowledge Management - Compliance and HR knowledge corpus controls plus bias review framework | F80: ='Implementation Roadmap'!J13 -> Phase 2 - Embed | G80: ='Implementation Roadmap'!H13 -> On Track | H80: ='Implementation Roadmap'!I13 -> 0.35 | I80: ='Implementation Roadmap'!G13 -> 30/09/2026 | J80: ='Implementation Roadmap'!E13 -> Rebecca Lloyd | K80: ='Implementation Roadmap'!L13 -> Supports AUC-008 and AUC-016
A81: ='Implementation Roadmap'!A14 -> RDM-010 | C81: ='Implementation Roadmap'!B14&" - "&'Implementation Roadmap'!C14 -> SOC and SIEM Modernisation - Splunk to Sentinel migration; Copilot for Security expansion to Azure subs | F81: ='Implementation Roadmap'!J14 -> Phase 2 - Embed | G81: ='Implementation Roadmap'!H14 -> On Track | H81: ='Implementation Roadmap'!I14 -> 0.6 | I81: ='Implementation Roadmap'!G14 -> 31/12/2026 | J81: ='Implementation Roadmap'!E14 -> Karen Holloway | K81: ='Implementation Roadmap'!L14 -> Critical to retire dual-running cost
A82: ='Implementation Roadmap'!A15 -> RDM-011 | C82: ='Implementation Roadmap'!B15&" - "&'Implementation Roadmap'!C15 -> Operating Model - AI Security operating model uplift (FTE plan plus sourcing model refresh) | F82: ='Implementation Roadmap'!J15 -> Phase 3 - Optimise | G82: ='Implementation Roadmap'!H15 -> Not Started | H82: ='Implementation Roadmap'!I15 -> 0 | I82: ='Implementation Roadmap'!G15 -> 31/03/2027 | J82: ='Implementation Roadmap'!E15 -> Sarah Mitchell | K82: ='Implementation Roadmap'!L15 -> Ties to vacancies in Resource Plan
A83: ='Implementation Roadmap'!A16 -> RDM-012 | C83: ='Implementation Roadmap'!B16&" - "&'Implementation Roadmap'!C16 -> Resilience Modelling - Quantitative scenario modelling refresh for AI risks | F83: ='Implementation Roadmap'!J16 -> Phase 3 - Optimise | G83: ='Implementation Roadmap'!H16 -> Not Started | H83: ='Implementation Roadmap'!I16 -> 0 | I83: ='Implementation Roadmap'!G16 -> 30/06/2027 | J83: ='Implementation Roadmap'!E16 -> Mohammed Iqbal | K83: ='Implementation Roadmap'!L16 -> Improves quantification depth
A85: 9. Budget and People Summary (FY 2026/27)
A86: Total Budget (GBP k) | D86: Run Cost (GBP k) | G86: Change Cost (GBP k) | J86: Contingency (GBP k)
A87: ='Financial Analysis'!L8 -> 6159.3 | D87: ='Financial Analysis'!L5 -> 4786 | G87: ='Financial Analysis'!L6 -> 1080 | J87: ='Financial Analysis'!L7 -> 293.3
A88: Run + Change + Contingency | D88: =TEXT('Financial Analysis'!L9,"0.0%")&" of total" -> 77.7% of total | G88: =TEXT('Financial Analysis'!L10,"0.0%")&" of total" -> 17.5% of total | J88: 5% of Run + Change
A90: Current FTE | D90: Target FTE | G90: FTE Gap | J90: Internal / External
A91: ='Resource Planning'!N6 -> 16 | D91: ='Resource Planning'!N7 -> 21 | G91: ='Resource Planning'!N8 -> 5 | J91: ='Resource Planning'!N9&" / "&'Resource Planning'!N10 -> 8 / 4
A92: Headcount in post | D92: Approved workforce plan | G92: Vacancies to fill | J92: Internal FTE / External roles
A94: 10. Strategic Posture and Major Changes Since Last Review
A95: The AI estate continues to expand within Risk Appetite. Internal models (underwriting, claims triage, fraud, pricing) remain robust with strong assurance and monitoring coverage at 92% for Tier-1 models. Customer-facing AI (voice agent assist, vulnerable customer detection, smart search) has matured with output guardrails, sample QA, complaint linkage, and refreshed hallucination filter post INC-008. Generative AI productivity tooling is embedded with Microsoft Purview controls; legacy SharePoint label inheritance is the residual gap (CA-004). The Splunk to Sentinel migration (RDM-010) is 60% complete and on track to retire dual-running cost in Q4 2026.
A98: Major Changes Since Last Review:
A99: INC-008 (Hallucination) | D99: Hallucinated reference in policy-wording smart search. Filter regression after vendor model update. Filter re-tuned; vendor change-window controls strengthened. No customer impact.
A100: KRI-007 (DLP Exceptions) | D100: GenAI DLP exceptions at 14/month vs amber threshold of 10. Targeted training to top-3 BUs underway; Purview labels reviewed.
A101: KRI-009 (Training) | D101: Training completion at 86% vs 95% target. Mandatory AI awareness module deployed; deadline extended to catch stragglers.
A102: ISO 42001 Readiness | D102: Overall readiness at 76.3%. Four areas with major NC risk identified (CA-009, CA-010, CA-011, CA-014). Closure plan requires board approval.
A103: Vendor Posture | D103: Six vendors at Amber residual. VEN-007 (Tractable) security review in progress; VEN-012 (Hugging Face) initial DD underway; VEN-015 (Splunk) migration to Sentinel on track.
A104: Resource Gap | D104: 5 FTE gap (16 current vs 21 target). Two vacancies in active recruitment (AI Risk Analyst, AI Security Engineer). Net hire approval sought at ExCo.
A105: Roadmap Progress | D105: Average completion at 37.5%. Two Phase 3 items not yet started (Operating Model, Resilience Modelling). All Phase 1/2 items in progress or on track.
A107: 11. Audit Committee Focus Items
A108: ISO 42001 Certification Path | D108: Internal readiness review (AUDIT-006) scheduled September 2026. Four major-NC-risk areas require closure before external assessment. Board approval of closure plan sought (DEC-Q1-01). Certification not guaranteed -- depends on assessor judgement.
A109: Evidence Library Currency | D109: Evidence register maintained with next-review dates. Stale evidence items flagged monthly. Current currency rate feeds into headline posture tile above.
A110: Corrective Action Discipline | D110: All open corrective actions tracked with target close dates. Overdue items escalated through AI Governance Forum. Management Review (MR-2026-Q2) scheduled for effectiveness review of all closed PIRs.
A111: Third-Party Assurance Gaps | D111: Six vendors at Amber residual. Two material Tier-1 vendors (VEN-001 Microsoft, VEN-006 Sentinel) require documented exit plans (DEC-Q1-02). Hugging Face (VEN-012) DD in progress.
A112: Control Coverage Depth | D112: 16 controls in scope; 12 fully implemented, 4 partial. Tier-1 use case control coverage tracked: 4/11 with production monitoring (CTL-005), 7/11 with HITL gate (CTL-008), 4/11 with independent bias test (CTL-014).
A114: 12. KPI Performance Summary
A115: KPIs On Track | D115: KPIs At Risk | G115: KPIs Off Track | J115: Total KPIs
A116: ='KPI Tracking'!N6 -> 8 | D116: ='KPI Tracking'!N7 -> 2 | G116: ='KPI Tracking'!N8 -> 1 | J116: ='KPI Tracking'!N5 -> 11
...

Sheet Board Pack Notes
A1: Board Pack Notes - Q1 2026
A2: Concise companion to the Board Dashboard. Threshold definitions, board metric interpretation notes, decisions required this quarter and narrative on major changes since last review. Owner AI Security Manager.
A3: Board Dashboard | B3: Operational Dashboard | C3: Executive Report | D3: ID Glossary | E3: ISO 42001 Matrix | F3: Evidence Register | G3: Mgmt Review | H3: TOM and Strategy
B5: 1. Board Metric Interpretation Notes
B6: Metric | C6: What it Tells the Board | D6: How it is Calculated | E6: Why it Matters | F6: Source Sheet | G6: Cadence | H6: Owner
B7: ISO 42001 Audit Readiness | C7: Average readiness across 38 ISO 42001 clauses and Annex A controls | D7: Average of readiness score 0-3 divided by 3 across 38 items | E7: Indicates how prepared the AIMS would be for an external 42001 assessment | F7: ISO 42001 Audit Readiness Matrix | G7: Quarterly | H7: Sarah Mitchell
B8: Maturity vs Target | C8: Composite maturity score expressed as percent of target | D8: Sum of current scores divided by sum of target scores across 9 domains | E8: Tracks progress toward target maturity 4.22 of 5 | F8: Maturity Assessment | G8: Half-yearly | H8: AI Security Manager
B9: Total Residual Exposure | C9: Sum of quantified residual exposure across all AI risks | D9: SUM of column L on Risk Quantification | E9: Headline financial exposure metric for risk appetite | F9: Risk Quantification | G9: Quarterly | H9: Geoffrey Sanders
B10: High Critical Residual Risks | C10: Number of risks with residual score 15 or higher | D10: COUNTIF residual score greater than or equal to 15 (out of max 25) | E10: Identifies risks above board appetite for residual harm | F10: Risk Quantification | G10: Monthly | H10: Geoffrey Sanders
B11: Major NC Risks Open | C11: Number of audit readiness items where absence is a potential major nonconformity | D11: COUNTIF on Potential NC column starts with Major | E11: Indicates audit-blocking gaps that need closure before assessment | F11: ISO 42001 Audit Readiness Matrix | G11: Quarterly | H11: Sarah Mitchell
B12: KRI Breaches Red and Amber | C12: Forward-looking risk indicators above amber threshold | D12: COUNTIF KRI status equals Red or Amber | E12: Early warning signal for emerging risk concentrations | F12: KRI Tracking | G12: Monthly | H12: AI Security Manager
B13: Open and High Severity Incidents | C13: Sev 1/2 incidents in rolling 90 days plus open or under-review incidents | D13: COUNTIF on severity Sev 1 plus Sev 2 plus Open | E13: Operational AI risk crystallisation indicator | F13: Incident Analysis | G13: Continuous | H13: AI Security Manager
B14: Overdue Corrective Actions | C14: Open corrective actions past target close date | D14: SUMPRODUCT on status not Closed and target date in past | E14: Indicates remediation discipline and audit-readiness risk | F14: Management Review and Internal Audit Tracker | G14: Monthly | H14: AI Security Manager
B15: Tier-1 Control Coverage | C15: Number of Tier-1 use cases with each material control linked | D15: SUMPRODUCT counting Tier-1 use cases linked to specific control IDs | E15: Indicates control depth on critical AI use cases | F15: AI Use Case Register | G15: Quarterly | H15: Mohammed Iqbal
B16: Evidence Currency Pct | C16: Percent of evidence items with current next-review date | D16: COUNTIF evidence currency Current divided by total | E16: Indicator of audit-readiness of evidence library | F16: Evidence Register | G16: Monthly | H16: Sarah Mitchell
B18: 2. Threshold and RAG Rule Definitions
B19: Indicator | C19: Green | D19: Amber | E19: Red | F19: Notes | G19: Source | H19: Owner
B20: ISO 42001 Audit Readiness pct | C20: 85 percent or higher | D20: 70 to 85 percent | E20: Below 70 percent | F20: Composite of 38 items each 0-3 score | G20: ISO 42001 Audit Readiness Matrix | H20: Sarah Mitchell
B21: Maturity vs Target pct | C21: 85 percent or higher | D21: 70 to 85 percent | E21: Below 70 percent | F21: Sum of current divided by sum of target across 9 domains | G21: Maturity Assessment | H21: AI Security Manager
B22: Major NC Risks Open | C22: Zero | D22: 1 to 5 | E22: More than 5 | F22: Items where absence is a major NC risk | G22: ISO 42001 Audit Readiness Matrix | H22: Sarah Mitchell
B23: High Critical Residual Risks | C23: Zero | D23: 1 | E23: More than 1 | F23: Residual score greater than or equal to 15 | G23: Risk Quantification | H23: Geoffrey Sanders
B24: KRI Breaches Red and Amber | C24: Zero | D24: 1 to 2 | E24: More than 2 | F24: KRI breach status either Red or Amber | G24: KRI Tracking | H24: AI Security Manager
B25: Open Incidents | C25: Zero | D25: 1 to 2 | E25: More than 2 | F25: Open or Under Review status | G25: Incident Analysis | H25: AI Security Manager
B26: Overdue Corrective Actions | C26: Zero | D26: 1 to 2 | E26: More than 2 | F26: Open or In Progress with target date in past | G26: Management Review and Internal Audit Tracker | H26: AI Security Manager
B27: Maturity Score 1-5 | C27: 4 or 5 (Managed or Optimised) | D27: 3 (Defined) | E27: 1 or 2 (Initial or Developing) | F27: Per-domain maturity rating | G27: Maturity Assessment | H27: AI Security Manager
B28: Vendor Residual | C28: Green - all assurance current | D28: Amber - one or more assurance items pending | E28: Red - material assurance gap | F28: Per-vendor residual posture | G28: Third-Party Risk Services | H28: Sarah Mitchell
B29: Days to Target on Corrective Actions | C29: Greater than 30 days | D29: 0 to 30 days | E29: Negative (overdue) | F29: Days to target close date | G29: Management Review and Internal Audit Tracker | H29: AI Security Manager
B31: 3. Decisions Required This Quarter
B32: Decision ID | C32: Decision | D32: Recommendation | E32: Forum | F32: Owner | G32: Decision By | H32: Linked Item
B33: DEC-Q1-01 | C33: Approve closure plan for 4 major-NC-risk areas (CA-009, CA-010, CA-011, CA-014) | D33: Approve and resource the closure plan ahead of internal readiness review | E33: AI Governance Forum | F33: Sarah Mitchell | G33: 30/06/2026 | H33: Mgmt Review tracker Section 3
B34: DEC-Q1-02 | C34: Approve Tier-1 vendor exit plans (VEN-001 Microsoft, VEN-006 Sentinel) | D34: Approve documented substitutability assessments and exit plans | E34: Third-Party Oversight Forum | F34: Sarah Mitchell | G34: 30/09/2026 | H34: Third-Party Risk Services
B35: DEC-Q1-03 | C35: Approve net hire of 5 FTE to close resource gap | D35: Approve hiring in line with FY26/27 plan | E35: ExCo | F35: Sarah Mitchell | G35: 30/06/2026 | H35: Resource Planning
B36: DEC-Q1-04 | C36: Reset risk appetite for residual AI risk pending refreshed quantification (RDM-012) | D36: Reaffirm appetite; commit to scenario-range refresh | E36: Risk Committee Board | F36: Geoffrey Sanders | G36: 30/09/2026 | H36: Risk Quantification
B37: DEC-Q1-05 | C37: Approve ISO 42001 readiness review pack and certification path | D37: Approve subject to AUDIT-006 outcome | E37: ExCo / Risk Committee | F37: Sarah Mitchell | G37: 31/01/2027 | H37: ISO 42001 Audit Readiness Matrix
B38: DEC-Q1-06 | C38: Approve Salesforce Einstein-feature posture | D38: Maintain restricted posture pending vendor AI feature review | E38: AI Governance Forum | F38: Olivia Bennett | G38: 30/06/2026 | H38: AI Use Case Register AUC-004
B40: 4. Narrative on Major Changes Since Last Review (Q4 2025 to Q1 2026)
B41: Theme | C41: What Changed | D41: So What for the Board | E41: Linked IDs | F41: Owner
B42: ISO 42001 Readiness | C42: Internal readiness programme RDM-007 lifted to 50 percent complete; AIMS scope statement and AI policy approved; first internal audit AUDIT-001 closed | D42: Credible glide-path to internal readiness review Q4 2026 and certification readiness assessment Q1 2027 | E42: RDM-007; AUDIT-001; EVD-023; EVD-024 | F42: Sarah Mitchell
B43: Customer-Facing AI | C43: Hallucination filter retuned post INC-008; PIR-008 closed; sample QA increased; vendor change-window controls being aligned with QA windows | D43: Operational risk on customer-facing GenAI demonstrably reduced; CTL-007 and CTL-010 strengthened | E43: INC-008; CA-008; CTL-007; CTL-010 | F43: Olivia Bennett
B44: Third-Party Posture | C44: Tier-1 vendor due diligence currency at 94 percent against 100 target; two Tier-1 exit plans documented with remainder in flight; ABBYY privacy review in progress | D44: Concentration risk on Microsoft platform remains the largest substitutability concern; CA-011 closure expected Sep 2026 | E44: VEN-001; VEN-006; CA-008; CA-011 | F44: Sarah Mitchell
B45: Cyber and Cloud | C45: Splunk to Sentinel migration RDM-010 lifted to 60 percent complete; PAM bundles re-baselined post INC-007; Copilot for Security expanded across Azure subscriptions | D45: Detection capability on AI workloads improving; dual-running cost retires Q4 2026 | E45: RDM-010; INC-007; CA-007; CTL-013 | F45: Karen Holloway
B46: Risk Quantification | C46: Total residual exposure 53.7m unchanged this quarter; RDM-012 scenario-range modelling refresh scheduled for H2 | D46: Risk appetite reset will be informed by RDM-012 outputs; expect refreshed quantification at Q3 review | E46: RDM-012; RSK-001 to RSK-013 | F46: Geoffrey Sanders
B47: Workforce and Competence | C47: AI awareness training completion 86 percent against 95 target; targeted campaign CA-014 in progress; 5 FTE vacancies in flight | D47: Closes Clauses 7.2-7.3 ISO 42001 gap and addresses CTL-016 partial implementation | E47: CA-014; CTL-016; RES-002 to RES-008 | F47: Daniel O'Reilly
A49: Footer note: This Board Pack Notes sheet is the companion to the Board Dashboard. RAG thresholds defined in Section 2 are applied via conditional formatting on the Board Dashboard. Refer to ID Glossary for full ID definitions and Evidence Register for audit evidence detail.

Sheet Board KPI-KRI Tracker
A1: Board KPI-KRI Tracker - Leading Indicators for AI Security and Governance
A2: Forward-looking (leading) indicators that predict emerging risk before it materialises. These complement lagging indicators (incidents, losses) by providing early warning for board-level oversight. Owner: AI Security Manager. As at 02/05/2026.
A3: Navigation: Board Dashboard | KRI Tracking | KPI Tracking | Risk Quantification | Maturity Assessment | Board Pack Notes
A5: LEADING vs LAGGING: Leading indicators measure conditions that precede risk events (e.g., control coverage gaps, training shortfalls, overdue reviews, configuration drift). They enable proactive intervention BEFORE harm occurs. Lagging indicators (e.g., incident count, customer complaints, financial losses) confirm risk has already crystallised. This tracker focuses on LEADING indicators to give the Board predictive visibility into the AI risk posture.
A8: Section 1: Leading Key Risk Indicators (KRIs) - Early Warning Signals
A9: ID | B9: Leading Indicator | C9: Linked Risk | D9: Current | E9: Amber | F9: Red | G9: Target | H9: Status | I9: Trend | J9: Predictive Signal | K9: Lead Time | L9: Owner | M9: Escalation | N9: Board Action if Breached
A10: ='KRI Tracking'!A5 -> KRI-001 | B10: ='KRI Tracking'!B5 -> Models with material drift in last 30 days | C10: ='KRI Tracking'!C5 -> RSK-001 | D10: ='KRI Tracking'!G5 -> 1 | E10: ='KRI Tracking'!E5 -> 2 | F10: ='KRI Tracking'!F5 -> 4 | G10: ='KRI Tracking'!H5 -> 0 | H10: ='KRI Tracking'!J5 -> Green | I10: ='KRI Tracking'!I5 -> Improving | J10: Drift precedes model failure; early signal of pricing/claims errors before customer impact | K10: 2-4 weeks before incident | L10: ='KRI Tracking'!K5 -> Mohammed Iqbal | M10: ='KRI Tracking'!N5 -> BAU | N10: Escalate to Model Risk Committee; invoke champion-challenger fallback
A11: ='KRI Tracking'!A6 -> KRI-002 | B11: ='KRI Tracking'!B6 -> Tier-1 models without current monitoring coverage | C11: ='KRI Tracking'!C6 -> RSK-002 | D11: ='KRI Tracking'!G6 -> 0 | E11: ='KRI Tracking'!E6 -> 1 | F11: ='KRI Tracking'!F6 -> 2 | G11: ='KRI Tracking'!H6 -> 0 | H11: ='KRI Tracking'!J6 -> Green | I11: ='KRI Tracking'!I6 -> Stable | J11: Unmonitored models cannot detect degradation; gap precedes undetected failure | K11: 4-8 weeks before undetected drift | L11: ='KRI Tracking'!K6 -> Mohammed Iqbal | M11: ='KRI Tracking'!N6 -> BAU | N11: Mandate monitoring reinstatement within 5 working days
A12: ='KRI Tracking'!A7 -> KRI-003 | B12: ='KRI Tracking'!B7 -> Pricing fairness review breaches outstanding | C12: ='KRI Tracking'!C7 -> RSK-001 | D12: ='KRI Tracking'!G7 -> 0 | E12: ='KRI Tracking'!E7 -> 1 | F12: ='KRI Tracking'!F7 -> 3 | G12: ='KRI Tracking'!H7 -> 0 | H12: ='KRI Tracking'!J7 -> Green | I12: ='KRI Tracking'!I7 -> Stable | J12: Outstanding fairness breaches signal future regulatory/Consumer Duty exposure | K12: 3-6 months before regulatory action | L12: ='KRI Tracking'!K7 -> Helen Carter | M12: ='KRI Tracking'!N7 -> BAU | N12: Suspend affected models; inform compliance and FCA engagement team
A13: ='KRI Tracking'!A8 -> KRI-004 | B13: ='KRI Tracking'!B8 -> Customer-facing AI complaints linked to AI behaviour (rolling 90d) | C13: ='KRI Tracking'!C8 -> RSK-005 | D13: ='KRI Tracking'!G8 -> 3 | E13: ='KRI Tracking'!E8 -> 5 | F13: ='KRI Tracking'!F8 -> 10 | G13: ='KRI Tracking'!H8 -> <=2 | H13: ='KRI Tracking'!J8 -> Green | I13: ='KRI Tracking'!I8 -> Improving | J13: Rising complaints trend predicts regulatory scrutiny and reputational damage | K13: 1-3 months before regulatory enquiry | L13: ='KRI Tracking'!K8 -> Olivia Bennett | M13: ='KRI Tracking'!N8 -> BAU | N13: Trigger Consumer Duty review; brief Risk Committee
A14: ='KRI Tracking'!A9 -> KRI-005 | B14: ='KRI Tracking'!B9 -> Vulnerable customer cases handled outside specialist team | C14: ='KRI Tracking'!C9 -> RSK-012 | D14: ='KRI Tracking'!G9 -> 1 | E14: ='KRI Tracking'!E9 -> 2 | F14: ='KRI Tracking'!F9 -> 5 | G14: ='KRI Tracking'!H9 -> 0 | H14: ='KRI Tracking'!J9 -> Green | I14: ='KRI Tracking'!I9 -> Stable | J14: Routing failures signal control weakness; predicts harm to vulnerable customers | K14: Immediate - each case is a near-miss | L14: ='KRI Tracking'!K9 -> Olivia Bennett | M14: ='KRI Tracking'!N9 -> BAU | N14: Invoke immediate remediation; report to Consumer Duty forum
A15: ='KRI Tracking'!A10 -> KRI-006 | B15: ='KRI Tracking'!B10 -> Sanctions/fraud false-negative incidents (rolling 90d) | C15: ='KRI Tracking'!C10 -> RSK-003 | D15: ='KRI Tracking'!G10 -> 0 | E15: ='KRI Tracking'!E10 -> 1 | F15: ='KRI Tracking'!F10 -> 2 | G15: ='KRI Tracking'!H10 -> 0 | H15: ='KRI Tracking'!J10 -> Green | I15: ='KRI Tracking'!I10 -> Improving | J15: Any false-negative signals model degradation; predicts undetected financial crime | K15: 1-2 weeks before leakage crystallises | L15: ='KRI Tracking'!K10 -> Helen Carter | M15: ='KRI Tracking'!N10 -> BAU | N15: Invoke SIU review; brief Fraud Committee and consider model suspension
A16: ='KRI Tracking'!A11 -> KRI-007 | B16: ='KRI Tracking'!B11 -> DLP exceptions raised on GenAI tools (per month) | C16: ='KRI Tracking'!C11 -> RSK-008 | D16: ='KRI Tracking'!G11 -> 14 | E16: ='KRI Tracking'!E11 -> 10 | F16: ='KRI Tracking'!F11 -> 20 | G16: ='KRI Tracking'!H11 -> <=8 | H16: ='KRI Tracking'!J11 -> Amber | I16: ='KRI Tracking'!I11 -> Deteriorating | J16: Rising DLP exceptions predict eventual data leakage before exfiltration occurs | K16: 2-6 weeks before potential breach | L16: ='KRI Tracking'!K11 -> Karen Holloway | M16: ='KRI Tracking'!N11 -> Monitor at next AIGF | N16: Restrict GenAI access for repeat offenders; brief CISO
A17: ='KRI Tracking'!A12 -> KRI-008 | B17: ='KRI Tracking'!B12 -> Document AI extraction reject rate | C17: ='KRI Tracking'!C12 -> RSK-006 | D17: ='KRI Tracking'!G12 -> 3 | E17: ='KRI Tracking'!E12 -> 4 | F17: ='KRI Tracking'!F12 -> 8 | G17: ='KRI Tracking'!H12 -> <=3 | H17: ='KRI Tracking'!J12 -> Green | I17: ='KRI Tracking'!I12 -> Stable | J17: Rising reject rates predict downstream claim errors before customer impact | K17: 1-2 weeks before payment errors | L17: ='KRI Tracking'!K12 -> Mohammed Iqbal | M17: ='KRI Tracking'!N12 -> BAU | N17: Invoke vendor escalation; increase manual QA sampling
A18: ='KRI Tracking'!A13 -> KRI-009 | B18: ='KRI Tracking'!B13 -> Cloud configuration drift on AI workloads | C18: ='KRI Tracking'!C13 -> RSK-010 | D18: ='KRI Tracking'!G13 -> 2 | E18: ='KRI Tracking'!E13 -> 2 | F18: ='KRI Tracking'!F13 -> 5 | G18: ='KRI Tracking'!H13 -> 0 | H18: ='KRI Tracking'!J13 -> Amber | I18: ='KRI Tracking'!I13 -> Stable | J18: Configuration drift signals exposure window; predicts cloud compromise before attack | K18: Days to weeks before exploitation | L18: ='KRI Tracking'!K13 -> Karen Holloway | M18: ='KRI Tracking'!N13 -> Monitor at next AIGF | N18: Emergency patching window; brief Technology Risk Committee
A20: Section 2: Leading Key Performance Indicators (KPIs) - Predictive Effectiveness Measures
A21: ID | B21: Leading Indicator | C21: Linked Service | D21: Target | E21: Actual | F21: Gap | G21: Status | H21: Trend | I21: Predictive Signal | J21: Lead Time | K21: Why Leading | L21: Owner | M21: Cadence | N21: Board Action if Off Track
A22: ='KPI Tracking'!A5 -> KPI-001 | B22: ='KPI Tracking'!B5 -> AI use case intake decisions on time (within 10 working days) | C22: ='KPI Tracking'!C5 -> SVC-001 | D22: ='KPI Tracking'!D5 -> 0.95 | E22: ='KPI Tracking'!E5 -> 0.97 | F22: =IFERROR(D22-E22,"") -> -0.02 | G22: ='KPI Tracking'!G5 -> On Track | H22: ='KPI Tracking'!F5 -> Improving | I22: Process speed predicts bottlenecks; delays signal governance overload before use cases stall | J22: 2-4 weeks before pipeline blockage | K22: Measures control process efficiency BEFORE it delays business value | L22: ='KPI Tracking'!H5 -> Daniel O'Reilly | M22: ='KPI Tracking'!I5 -> Monthly | N22: Review intake capacity; approve additional resource
A23: ='KPI Tracking'!A6 -> KPI-002 | B23: ='KPI Tracking'!B6 -> Material models with current independent assurance | C23: ='KPI Tracking'!C6 -> SVC-002 | D23: ='KPI Tracking'!D6 -> 0.98 | E23: ='KPI Tracking'!E6 -> 0.96 | F23: =IFERROR(D23-E23,"") -> 0.02 | G23: ='KPI Tracking'!G6 -> At Risk | H23: ='KPI Tracking'!F6 -> Stable | I23: Assurance gaps predict undetected model failure; declining coverage precedes incidents | J23: 4-8 weeks before undetected drift leads to loss | K23: Measures control coverage BEFORE failure occurs; gap = blind spot | L23: ='KPI Tracking'!H6 -> Mohammed Iqbal | M23: ='KPI Tracking'!I6 -> Monthly | N23: Mandate immediate re-validation; restrict model use until assured
A24: ='KPI Tracking'!A7 -> KPI-003 | B24: ='KPI Tracking'!B7 -> Claims AI uptime (monthly) | C24: ='KPI Tracking'!C7 -> SVC-003,SVC-010 | D24: ='KPI Tracking'!D7 -> 0.995 | E24: ='KPI Tracking'!E7 -> 0.997 | F24: =IFERROR(D24-E24,"") -> -0.002 | G24: ='KPI Tracking'!G7 -> On Track | H24: ='KPI Tracking'!F7 -> Stable | I24: Uptime trend predicts service reliability; degradation signals infrastructure stress before outage | J24: 1-2 weeks before prolonged outage | K24: Early degradation patterns (short dips) precede major failures | L24: ='KPI Tracking'!H7 -> Mohammed Iqbal | M24: ='KPI Tracking'!I7 -> Weekly | N24: Invoke resilience review; approve redundancy investment
A25: ='KPI Tracking'!A8 -> KPI-004 | B25: ='KPI Tracking'!B8 -> Fraud and sanctions FPR within agreed band | C25: ='KPI Tracking'!C8 -> SVC-004,SVC-012 | D25: ='KPI Tracking'!D8 -> 0.9 | E25: ='KPI Tracking'!E8 -> 0.92 | F25: =IFERROR(D25-E25,"") -> -0.02 | G25: ='KPI Tracking'!G8 -> On Track | H25: ='KPI Tracking'!F8 -> Improving | I25: Narrowing FPR band signals model calibration drift before fraud leakage occurs | J25: 2-4 weeks before false-negatives increase | K25: Threshold drift is visible before fraud leakage crystallises | L25: ='KPI Tracking'!H8 -> Helen Carter | M25: ='KPI Tracking'!I8 -> Monthly | N25: Invoke model recalibration; brief Fraud Committee
A26: ='KPI Tracking'!A9 -> KPI-005 | B26: ='KPI Tracking'!B9 -> Customer-facing AI sample QA pass rate | C26: ='KPI Tracking'!C9 -> SVC-005,SVC-009 | D26: ='KPI Tracking'!D9 -> 0.95 | E26: ='KPI Tracking'!E9 -> 0.93 | F26: =IFERROR(D26-E26,"") -> 0.02 | G26: ='KPI Tracking'!G9 -> At Risk | H26: ='KPI Tracking'!F9 -> Stable | I26: Declining QA pass rate predicts customer harm before complaints materialise | J26: 4-8 weeks before complaints spike | K26: Quality failures occur before customers notice and complain | L26: ='KPI Tracking'!H9 -> Olivia Bennett | M26: ='KPI Tracking'!I9 -> Monthly | N26: Restrict affected AI feature; invoke output filter review
A27: ='KPI Tracking'!A10 -> KPI-006 | B27: ='KPI Tracking'!B10 -> SOC mean-time-to-triage on AI-related alerts | C27: ='KPI Tracking'!C10 -> SVC-014 | D27: ='KPI Tracking'!D10 -> 15 | E27: ='KPI Tracking'!E10 -> 12 | F27: =IFERROR(D27-E27,"") -> 3 | G27: ='KPI Tracking'!G10 -> On Track | H27: ='KPI Tracking'!F10 -> Improving | I27: Rising triage time predicts SOC overload before alerts are missed | J27: 1-3 weeks before missed critical alert | K27: Response time degradation precedes missed detections | L27: ='KPI Tracking'!H10 -> Karen Holloway | M27: ='KPI Tracking'!I10 -> Weekly | N27: Approve SOC staffing increase; review alert prioritisation rules
A28: ='KPI Tracking'!A11 -> KPI-007 | B28: ='KPI Tracking'!B11 -> Tier-1 vendor due diligence currency | C28: ='KPI Tracking'!C11 -> SVC-015 | D28: ='KPI Tracking'!D11 -> 1 | E28: ='KPI Tracking'!E11 -> 0.94 | F28: =IFERROR(D28-E28,"") -> 0.06 | G28: ='KPI Tracking'!G11 -> Off Track | H28: ='KPI Tracking'!F11 -> Stable | I28: DD expiry signals assurance gap before vendor risk materialises | J28: 2-3 months before unassured vendor risk event | K28: Expired DD means blind spots on vendor changes that could harm us | L28: ='KPI Tracking'!H11 -> Sarah Mitchell | M28: ='KPI Tracking'!I11 -> Monthly | N28: Suspend new workloads to vendor; escalate renewal
A29: ='KPI Tracking'!A12 -> KPI-008 | B29: ='KPI Tracking'!B12 -> Document AI extraction QA reject rate | C29: ='KPI Tracking'!C12 -> SVC-006,SVC-011 | D29: ='KPI Tracking'!D12 -> 0.04 | E29: ='KPI Tracking'!E12 -> 0.03 | F29: =IFERROR(D29-E29,"") -> 0.01 | G29: ='KPI Tracking'!G12 -> On Track | H29: ='KPI Tracking'!F12 -> Stable | I29: Rising reject rate signals extraction model degradation before claim errors | J29: 1-2 weeks before incorrect payments | K29: Extraction failures precede downstream financial errors | L29: ='KPI Tracking'!H12 -> Mohammed Iqbal | M29: ='KPI Tracking'!I12 -> Monthly | N29: Invoke vendor review; increase manual sampling rate
A30: ='KPI Tracking'!A13 -> KPI-009 | B30: ='KPI Tracking'!B13 -> Claims triage SLA attainment | C30: ='KPI Tracking'!C13 -> SVC-003 | D30: ='KPI Tracking'!D13 -> 0.98 | E30: ='KPI Tracking'!E13 -> 0.985 | F30: =IFERROR(D30-E30,"") -> -0.005 | G30: ='KPI Tracking'!G13 -> On Track | H30: ='KPI Tracking'!F13 -> Improving | I30: SLA degradation predicts claims handling failures before customer detriment | J30: 1-2 weeks before customer harm | K30: Triage delays cause downstream SLA cascades | L30: ='KPI Tracking'!H13 -> James Whitfield | M30: ='KPI Tracking'!I13 -> Weekly | N30: Review capacity plan; invoke claims ops escalation
A31: ='KPI Tracking'!A14 -> KPI-010 | B31: ='KPI Tracking'!B14 -> Customer complaints linked to AI behaviour (per 1000 customers) | C31: ='KPI Tracking'!C14 -> SVC-005,SVC-009 | D31: ='KPI Tracking'!D14 -> 0.5 | E31: ='KPI Tracking'!E14 -> 0.4 | F31: =IFERROR(D31-E31,"") -> 0.1 | G31: ='KPI Tracking'!G14 -> On Track | H31: ='KPI Tracking'!F14 -> Improving | I31: Complaint trend predicts regulatory attention before FCA engagement | J31: 2-6 months before regulatory enquiry | K31: Rising trend visible months before regulator acts | L31: ='KPI Tracking'!H14 -> Olivia Bennett | M31: ='KPI Tracking'!I14 -> Monthly | N31: Brief Consumer Duty forum; prepare FCA response pack
A32: ='KPI Tracking'!A15 -> KPI-011 | B32: ='KPI Tracking'!B15 -> Internal GenAI tooling adoption (% of eligible users active monthly) | C32: ='KPI Tracking'!C15 -> SVC-007,SVC-008,SVC-009 | D32: ='KPI Tracking'!D15 -> 0.7 | E32: ='KPI Tracking'!E15 -> 0.73 | F32: =IFERROR(D32-E32,"") -> -0.03 | G32: ='KPI Tracking'!G15 -> On Track | H32: ='KPI Tracking'!F15 -> Stable | I32: Adoption plateau signals shadow AI risk; low adoption predicts ungoverned tool use | J32: 1-3 months before shadow AI incidents | K32: Low adoption drives users to ungoverned alternatives | L32: ='KPI Tracking'!H15 -> Karen Holloway | M32: ='KPI Tracking'!I15 -> Monthly | N32: Review UX barriers; extend training; communicate policy
A34: Section 3: Leading Indicator Summary - Board Attention Required
A35: KRI Breaches (Amber + Red) | C35: KRIs Deteriorating | E35: KPIs At Risk or Off Track | G35: Total Leading Indicators | I35: Overall Predictive Posture
A36: =COUNTIF(H10:H18,"Amber")+COUNTIF(H10:H18,"Red") -> 2 | C36: =COUNTIF(I10:I18,"Deteriorating") -> 1 | E36: =COUNTIF(G22:G32,"At Risk")+COUNTIF(G22:G32,"Off Track") -> 3 | G36: =COUNTA(A10:A18)+COUNTA(A22:A32) -> 20 | I36: =IF(COUNTIF(H10:H18,"Red")>0,"RED - Immediate Action Required",IF(A36+E36>4,"AMBER - Heightened Monitoring",IF(A36+E36>2,"AMBER - Monitor Closely","GREEN - Within Appetite"))) -> AMBER - Heightened Monitoring
A37: Early warning breaches | C37: Worsening trend direction | E37: Effectiveness gaps | G37: KRIs (9) + KPIs (11) | I37: Composite board-level assessment
A39: Section 4: Board Attention Items - Leading Indicators Signalling Emerging Risk
A40: Priority | B40: Indicator | C40: Current State | D40: Predictive Concern | H40: Board Action | L40: Timeline | M40: Owner | N40: Risk
A41: 1 | B41: DLP exceptions (KRI-007) | C41: 14/mth vs Amber 10; Deteriorating | D41: Predicts data leakage within 2-6 weeks. 3 BUs driving 80%. Pre-breach pattern. | H41: Restrict repeat-offender BU access; mandate training by 30/06/2026 | L41: Immediate | M41: K Holloway | N41: RSK-008
A42: 2 | B42: Cloud config drift (KRI-009) | C42: 2 findings vs Amber 2; Stable | D42: Exposed API endpoints. Exploitation lead time is days once threat actor discovers. | H42: Mandate 48-hour emergency remediation; approve out-of-cycle patch | L42: 48 hours | M42: K Holloway | N42: RSK-010
A43: 3 | B43: Vendor DD currency (KPI-007) | C43: 94% vs 100%; Off Track | D43: Tier-1 vendor in renewal with expired DD. Unassured platform changes introduce blind risk. | H43: Expedite renewal; restrict new workloads until DD refreshed | L43: 30 days | M43: S Mitchell | N43: RSK-008
A44: 4 | B44: QA pass rate (KPI-005) | C44: 93% vs 95%; At Risk | D44: Declining QA predicts complaints spike in 4-8 weeks. Filter retune needed post INC-008. | H44: Approve filter retune; increase QA sample to 10% | L44: 4 weeks | M44: O Bennett | N44: RSK-005
A45: 5 | B45: Training completion gap | C45: 86% vs 95% target | D45: Low completion correlates with DLP exceptions. Untrained staff 3x more likely to trigger. | H45: Mandate completion; withhold GenAI access for non-completers | L45: 30/06/2026 | M45: D O'Reilly | N45: RSK-008
A47: Section 5: RAG Threshold Definitions and Escalation Framework
A48: Indicator Type | B48: Green | C48: Amber | D48: Red | E48: Escalation Route | I48: Board Reporting Trigger | L48: Review Cadence
A49: KRI Breaches | B49: Zero breaches | C49: 1-2 breaches | D49: >2 breaches or any Red | E49: Owner action; AIGF review at next meeting | I49: Any Red KRI triggers immediate board notification | L49: Monthly via AIGF; Quarterly to Board
A50: KRI Trend | B50: Improving or Stable | C50: Stable at Amber boundary | D50: Deteriorating | E50: AIGF escalation; Risk Committee if sustained | I50: Two consecutive Deteriorating months triggers board paper | L50: Monthly trend analysis
A51: KPI Status | B51: On Track | C51: At Risk (within tolerance) | D51: Off Track (below tolerance) | E51: Service owner remediation plan within 10 days | I51: Any Off Track for 2+ months triggers board attention | L51: Monthly; Quarterly board summary
A52: Residual Risk Score | B52: <10 (Low-Medium) | C52: 10-14 (High) | D52: >=15 (Critical) | E52: Risk Committee; ExCo if score 20+ | I52: Any risk scoring >=15 residual reported to board immediately | L52: Monthly re-scoring
A53: Vendor Residual | B53: Green - all assurance current | C53: Amber - assurance item pending | D53: Red - material assurance gap | E53: Third-Party Oversight Forum; Risk Committee | I53: Any Tier-1 vendor at Red reported to board | L53: Monthly; Quarterly board pack
A54: Maturity Gap | B54: Gap = 0 (at target) | C54: Gap = 1 (one level below) | D54: Gap >= 2 (two+ levels below) | E54: Domain owner action plan; AIGF oversight | I54: Any domain at gap >=2 triggers board discussion | L54: Half-yearly assessment
A56: End of Board KPI-KRI Tracker | All indicators are LEADING (predictive) | Source: KRI Tracking, KPI Tracking, Risk Quantification | Owner: AI Security Manager | Classification: Board Confidential
A57: RAG Key: GREEN = Within appetite | AMBER = Monitor / approaching threshold | RED = Breach / requires immediate action | LEADING = Predicts future risk before crystallisation | LAGGING = Confirms risk already materialised

Sheet Management Review and Internal 
A1: Management Review and Internal Audit Tracker - AIMS Effectiveness Evidence
A2: Tracks AIMS internal audits (Clause 9.2), management reviews (Clause 9.3), corrective actions and effectiveness reviews (Clause 10.1, 10.2) and continual improvement. Owner: AI Security Manager and Internal Audit. Cadence: Quarterly review.
A3: Back to Dashboard | Open ID Glossary | Board Dashboard | Executive Report | Compliance Mapping
A5: Section 1: Internal Audit Programme (ISO 42001 Clause 9.2)
A6: Audit ID | B6: Audit Title / Scope | C6: Clause | D6: Lead Auditor | E6: Status | F6: Date | G6: Findings | H6: Major NCs | I6: Minor NCs | J6: Observations | K6: Key Finding Summary | L6: Linked CA
A7: AUDIT-001 | B7: AIMS Governance and Policy Framework | C7: 4.1-5.3, 6.1 | D7: Liam Carmichael (CAE) | E7: Closed | F7: 15/01/2026 | G7: 4 | H7: 1 | I7: 2 | J7: 1 | K7: AIMS scope and policy approved; management review input checklist incomplete (Major NC); two minor gaps in documented roles. | L7: CA-009
A8: AUDIT-002 | B8: Customer-Facing AI Assurance | C8: 6.1.4, 8.1, 9.1 | D8: Liam Carmichael (CAE) | E8: Closed | F8: 28/02/2026 | G8: 3 | H8: 1 | I8: 1 | J8: 1 | K8: Impact assessments require refresh for customer-facing use cases after vendor sub-processor changes (Major NC). QA sampling adequate. | L8: CA-010
A9: AUDIT-003 | B9: Third-Party AI Oversight | C9: 8.1, A.7.5 | D9: Liam Carmichael (CAE) | E9: Closed | F9: 20/03/2026 | G9: 3 | H9: 1 | I9: 1 | J9: 1 | K9: Tier-1 vendor exit plans incomplete for VEN-001 and VEN-006 (Major NC). DD currency at 94% vs 100% target. | L9: CA-011
A10: AUDIT-004 | B10: Cloud and IAM Security Controls | C10: 8.1, A.6.2.4 | D10: External (KPMG) | E10: Closed | F10: 46299 | G10: 2 | H10: 0 | I10: 1 | J10: 1 | K10: Cloud CSPM controls effective; one minor finding on PAM bundle configuration (remediated). IAM controls satisfactory. | L10: CA-007
A11: AUDIT-005 | B11: AI Model Lifecycle and MRM | C11: 9.1, 9.2, A.6.2.6 | D11: Liam Carmichael (CAE) | E11: In Progress | F11: 30/06/2026 | K11: Scope: independent challenge of material models, validation backlog, model retirement process.
A12: AUDIT-006 | B12: ISO 42001 Internal Readiness Review | C12: All clauses + Annex A | D12: External (KPMG) | E12: Planned | F12: 30/09/2026 | K12: Full internal readiness assessment against 38 ISO 42001 clauses/Annex A items ahead of certification.
A14: Section 2: Management Reviews of the AIMS (ISO 42001 Clause 9.3)
A15: Review ID | B15: Review Title | C15: Date | D15: Chair | E15: Status | F15: Inputs Covered | G15: Key Decisions | H15: Actions Raised | I15: Effectiveness Confirmed | J15: Minutes Ref | K15: Next Review | L15: Linked Evidence
A16: MR-2025-Q3 | B16: AIMS Quarterly Management Review Q3 2025 | C16: 15/10/2025 | D16: Andrew Pollard (CDO) | E16: Closed | F16: Risk status, KPI/KRI, incidents, audit findings, resource, opportunities | G16: Approved AIMS scope; approved AI policy v1; noted resource gap | H16: 3 (CA-001, CA-002, CA-003) | I16: Yes - reviewed at MR-2025-Q4 | J16: EVD-027-MR-Q3 | K16: 15/01/2026 | L16: EVD-027
A17: MR-2025-Q4 | B17: AIMS Quarterly Management Review Q4 2025 | C17: 15/01/2026 | D17: Andrew Pollard (CDO) | E17: Closed | F17: Risk status, KPI/KRI, incidents, corrective actions, roadmap, vendor posture | G17: Approved ISO 42001 readiness programme; approved hiring plan; confirmed CA-001 effective | H17: 4 (CA-004, CA-005, CA-006, CA-007) | I17: Yes - reviewed at MR-2026-Q1 | J17: EVD-027-MR-Q4 | K17: 15/04/2026 | L17: EVD-027
A18: MR-2026-Q1 | B18: AIMS Quarterly Management Review Q1 2026 | C18: 15/04/2026 | D18: Andrew Pollard (CDO) | E18: Closed | F18: All 9.3 inputs: changes, performance, audits, NCs, KPIs, risks, opportunities, resources, continual improvement | G18: Approved closure plan for major NCs; noted vendor exit plan progress; approved training campaign escalation | H18: 5 (CA-009, CA-010, CA-011, CA-012, CA-014) | I18: Partial - PIR effectiveness pending | J18: EVD-027-MR-Q1-26 | K18: 15/07/2026 | L18: EVD-027
A19: MR-2026-Q2 | B19: AIMS Quarterly Management Review Q2 2026 | C19: 15/07/2026 | D19: Andrew Pollard (CDO) | E19: Scheduled | F19: All 9.3 inputs; effectiveness review of all closed PIRs; CA-009 to CA-014 progress review | K19: 15/10/2026 | L19: EVD-027
A21: Section 3: Corrective Actions Register (ISO 42001 Clause 10.1, 10.2)
A22: CA ID | B22: Corrective Action | C22: Source | D22: Root Cause | E22: Owner | F22: Target Date | G22: Status | H22: Days to Target | I22: Effectiveness Review | J22: Linked Audit/Incident | K22: Linked Control | L22: Priority
A23: CA-001 | B23: Add seasonality features to FNOL training set; tighten drift thresholds | C23: INC-001 / PIR-001 | D23: Seasonal claim composition not in training data | E23: Mohammed Iqbal | F23: 30/06/2026 | G23: Closed | H23: =IF(G23="Closed","",IFERROR(DATEVALUE(F23)-TODAY(),"")) | I23: Confirmed effective at MR-2025-Q4 | J23: AUDIT-001, INC-001 | K23: CTL-005 | L23: Medium
A24: CA-002 | B24: Complete ABBYY privacy review after sub-processor change | C24: AUDIT-003 / Vendor review | D24: Vendor sub-processor change triggered review | E24: Sarah Mitchell | F24: 30/06/2026 | G24: In Progress | H24: =IF(G24="Closed","",IFERROR(DATEVALUE(F24)-TODAY(),"")) -> -37 | I24: Due at MR-2026-Q2 | J24: AUDIT-003 | K24: CTL-011 | L24: Medium
A25: CA-003 | B25: Strengthen pre-issue guardrail for outlier features (pricing) | C25: INC-002 / PIR-002 | D25: Outlier feature interaction not handled | E25: Helen Carter | F25: 31/03/2026 | G25: Closed | H25: =IF(G25="Closed","",IFERROR(DATEVALUE(F25)-TODAY(),"")) | I25: Confirmed effective at MR-2025-Q4 | J25: INC-002 | K25: CTL-014 | L25: Medium
A26: CA-004 | B26: Sensitivity-label review cycle; Purview policy refresh | C26: INC-004 / PIR-004 | D26: SharePoint label inheritance gap | E26: Karen Holloway | F26: 30/09/2026 | G26: In Progress | H26: =IF(G26="Closed","",IFERROR(DATEVALUE(F26)-TODAY(),"")) -> 55 | I26: Due at MR-2026-Q2 | J26: INC-004 | K26: CTL-006 | L26: Medium
A27: CA-005 | B27: Vendor SLA exceptions; resilience plan updated for tabletop | C27: INC-005 / PIR-005 | D27: Vendor outage exposed DR gap | E27: James Whitfield | F27: 30/09/2026 | G27: In Progress | H27: =IF(G27="Closed","",IFERROR(DATEVALUE(F27)-TODAY(),"")) -> 55 | I27: Due at MR-2026-Q3 | J27: INC-005 | K27: CTL-005 | L27: Low
A28: CA-006 | B28: Confirm template update SLAs with ABBYY vendor | C28: INC-006 / PIR-006 | D28: New template not in training corpus | E28: Mohammed Iqbal | F28: 30/06/2026 | G28: Closed | H28: =IF(G28="Closed","",IFERROR(DATEVALUE(F28)-TODAY(),"")) | I28: Confirmed effective at MR-2026-Q1 | J28: INC-006 | K28: CTL-004 | L28: Low
A29: CA-007 | B29: PAM bundles re-baselined; quarterly review added | C29: INC-007 / PIR-007 | D29: Misconfigured PAM bundle | E29: Karen Holloway | F29: 31/03/2026 | G29: Closed | H29: =IF(G29="Closed","",IFERROR(DATEVALUE(F29)-TODAY(),"")) | I29: Confirmed effective at MR-2026-Q1 | J29: AUDIT-004, INC-007 | K29: CTL-013 | L29: Medium
A30: CA-008 | B30: Hallucination filter re-tune; vendor change-window QA alignment | C30: INC-008 / PIR-008 | D30: Filter regression after vendor model update | E30: Olivia Bennett | F30: 30/06/2026 | G30: Closed | H30: =IF(G30="Closed","",IFERROR(DATEVALUE(F30)-TODAY(),"")) | I30: Due at MR-2026-Q2 | J30: INC-008 | K30: CTL-010 | L30: High
A31: CA-009 | B31: Strengthen 9.3 management review input checklist | C31: AUDIT-001 (Major NC) | D31: MR input checklist incomplete vs Clause 9.3 requirements | E31: Andrew Pollard | F31: 30/06/2026 | G31: In Progress | H31: =IF(G31="Closed","",IFERROR(DATEVALUE(F31)-TODAY(),"")) -> -37 | I31: Due at MR-2026-Q2 | J31: AUDIT-001 | K31: Clause 9.3 | L31: High
A32: CA-010 | B32: Customer-facing AI impact assessments refresh | C32: AUDIT-002 (Major NC) | D32: Impact assessments not refreshed after vendor sub-processor changes | E32: Rebecca Lloyd | F32: 30/09/2026 | G32: In Progress | H32: =IF(G32="Closed","",IFERROR(DATEVALUE(F32)-TODAY(),"")) -> 55 | I32: Due at MR-2026-Q3 | J32: AUDIT-002 | K32: CTL-003, A.6.2.5 | L32: High
A33: CA-011 | B33: Tier-1 vendor exit plans (VEN-001, VEN-006) | C33: AUDIT-003 (Major NC) | D33: Exit plans incomplete for material vendors | E33: Sarah Mitchell | F33: 30/09/2026 | G33: In Progress | H33: =IF(G33="Closed","",IFERROR(DATEVALUE(F33)-TODAY(),"")) -> 55 | I33: Due at MR-2026-Q3 | J33: AUDIT-003 | K33: CTL-011, A.7.5 | L33: High
A34: CA-012 | B34: Accelerate Tier-1 vendor DD currency to 100% | C34: MR-2026-Q1 | D34: One Tier-1 vendor in renewal; DD expired | E34: Sarah Mitchell | F34: 30/06/2026 | G34: In Progress | H34: =IF(G34="Closed","",IFERROR(DATEVALUE(F34)-TODAY(),"")) -> -37 | I34: Due at MR-2026-Q2 | J34: MR-2026-Q1 | K34: CTL-011 | L34: Medium
... A36: CA-014 | B36: Lift training completion to 95% (AI awareness module) | C36: AUDIT-001 / MR-2026-Q1 | D36: Training at 86% vs 95% target; Clauses 7.2-7.3 gap | E36: Daniel O'Reilly | F36: 30/09/2026 | G36: In Progress | H36: =IF(G36="Closed","",IFERROR(DATEVALUE(F36)-TODAY(),"")) -> 55 | I36: Due at MR-2026-Q3 | J36: AUDIT-001 | K36: CTL-016, A.7.6 | L36: High
A38: Section 4: Post-Incident Review (PIR) Effectiveness Tracker
A39: PIR ID | B39: Incident | C39: Category | D39: Severity | E39: Corrective Action Taken | F39: Effectiveness Criteria | G39: Review Date | H39: Effectiveness Status | I39: Residual Gap | J39: Reviewer | K39: Linked CA | L39: Next Review
A40: PIR-001 | B40: INC-001 - Claims FNOL drift | C40: Model Drift | D40: Sev 2 | E40: Retraining with refreshed data; revised drift threshold; cadence increased | F40: No recurrence of drift on same model within 90 days; seasonal features validated | G40: 15/04/2026 | H40: Effective | I40: None | J40: Mohammed Iqbal | K40: CA-001 | L40: N/A
A41: PIR-002 | B41: INC-002 - UW pricing outlier | C41: Output Quality | D41: Sev 3 | E41: Added guardrail rule; updated pricing committee escalation | F41: No recurrence of uncontrolled outlier quote within 90 days | G41: 15/04/2026 | H41: Effective | I41: None | J41: Helen Carter | K41: CA-003 | L41: N/A
A42: PIR-003 | B42: INC-003 - Voice agent inaccurate suggestion | C42: Output Quality | D42: Sev 2 | E42: Index refresh automation; content owner cadence updated; sample QA increase | F42: No recurrence of stale-content surfacing; index freshness SLA met | G42: 15/04/2026 | H42: Effective | I42: None | J42: Olivia Bennett | L42: N/A
A43: PIR-004 | B43: INC-004 - M365 Copilot label leak | C43: Data Leakage | D43: Sev 3 | E43: Label review cycle introduced; Purview policy refresh | F43: No recurrence of label inheritance gap; quarterly label audit clean | G43: 15/07/2026 | H43: Pending | I43: Label inheritance on legacy sites | J43: Karen Holloway | K43: CA-004 | L43: MR-2026-Q2
A44: PIR-005 | B44: INC-005 - Tractable vendor outage | C44: Vendor Outage | D44: Sev 2 | E44: Vendor SLA exceptions; resilience plan updated; tabletop scheduled | F44: Tabletop exercise completed; fallback invoked within RTO | G44: 15/07/2026 | H44: Pending | I44: Tabletop not yet completed | J44: James Whitfield | K44: CA-005 | L44: MR-2026-Q2
A45: PIR-006 | B45: INC-006 - ABBYY extraction error | C45: Output Quality | D45: Sev 3 | E45: Vendor template update; QA sample increase | F45: Template SLA met; no recurrence on same format | G45: 15/04/2026 | H45: Effective | I45: None | J45: Mohammed Iqbal | K45: CA-006 | L45: N/A
A46: PIR-007 | B46: INC-007 - PAM privilege escalation | C46: Access Violation | D46: Sev 2 | E46: PAM bundles re-baselined; quarterly review added | F46: No privilege over-assignment in subsequent quarters; automated test passing | G46: 15/04/2026 | H46: Effective | I46: None | J46: Karen Holloway | K46: CA-007 | L46: N/A
A47: PIR-008 | B47: INC-008 - Policy smart search hallucination | C47: Output Quality | D47: Sev 3 | E47: Filter re-tuned; vendor change-window controls strengthened | F47: No recurrence post vendor updates; change-window QA alignment confirmed | G47: 15/07/2026 | H47: Pending | I47: Vendor change-window alignment ongoing | J47: Olivia Bennett | K47: CA-008 | L47: MR-2026-Q2
A49: Section 5: Continual Improvement Register (ISO 42001 Clause 10.2)
A50: CI ID | B50: Improvement Opportunity | C50: Source | D50: Category | E50: Owner | F50: Target Date | G50: Status | H50: Expected Benefit | I50: Linked Roadmap | J50: Priority | K50: Review Forum | L50: Notes
A51: CI-001 | B51: Automate KRI data collection from source systems to reduce manual effort | C51: MR-2025-Q4 | D51: Efficiency | E51: Karen Holloway | F51: 31/12/2026 | G51: In Progress | H51: Reduce monthly KRI reporting effort by 60%; improve data currency | I51: RDM-010 | J51: Medium | K51: AIGF | L51: Tied to Sentinel migration
A52: CI-002 | B52: Implement automated evidence currency alerting (email 30 days before expiry) | C52: MR-2026-Q1 | D52: Assurance | E52: Sarah Mitchell | F52: 30/09/2026 | G52: In Progress | H52: Prevent evidence staleness; reduce audit prep effort | I52: RDM-007 | J52: Medium | K52: AIGF | L52: Part of ISO 42001 readiness
A53: CI-003 | B53: Extend bias monitoring to all Tier-2 customer-facing use cases | C53: MR-2026-Q1 | D53: Risk Reduction | E53: Olivia Bennett | F53: 31/03/2027 | G53: Planned | H53: Expand fairness assurance coverage from 11 to 16 use cases | I53: RDM-001 | J53: Medium | K53: AIGF | L53: Consumer Duty alignment
A54: CI-004 | B54: Develop quantitative scenario-range risk modelling capability | C54: MR-2026-Q1 | D54: Risk Maturity | E54: Geoffrey Sanders | F54: 30/06/2027 | G54: Not Started | H54: Move from point-estimate to range-based exposure; inform risk appetite reset | I54: RDM-012 | J54: High | K54: Risk Committee | L54: Board decision DEC-Q1-04
A55: CI-005 | B55: Establish AI Security operating model v2 with clear RACI refresh | C55: MR-2026-Q1 | D55: Governance | E55: Sarah Mitchell | F55: 31/03/2027 | G55: Not Started | H55: Clear accountability; efficient decision rights; reduced escalation friction | I55: RDM-011 | J55: Medium | K55: ExCo | L55: Depends on FTE hiring
A56: CI-006 | B56: Introduce automated drift detection for Tier-2 models | C56: PIR-001 lessons | D56: Detection | E56: Mohammed Iqbal | F56: 31/12/2026 | G56: In Progress | H56: Extend drift coverage from Tier-1 (100%) to Tier-2 (target 80%) | I56: RDM-006 | J56: Medium | K56: AIGF | L56: Reduces KRI-001 future risk
A57: CI-007 | B57: Implement vendor change-window notification integration with QA calendar | C57: PIR-008 lessons | D57: Process | E57: Olivia Bennett | F57: 30/09/2026 | G57: In Progress | H57: Prevent filter regression by aligning vendor updates with QA windows | I57: RDM-001 | J57: High | K57: AIGF | L57: Directly addresses INC-008 root cause
A58: CI-008 | B58: Develop board-level AI risk appetite statement with quantified thresholds | C58: Board feedback | D58: Governance | E58: Geoffrey Sanders | F58: 30/09/2026 | G58: In Progress | H58: Formal risk appetite enables clearer escalation and de-escalation criteria | I58: RDM-012 | J58: High | K58: Risk Committee / Board | L58: Feeds DEC-Q1-04
A60: Section 6: Summary Metrics
A61: Total Audits | C61: Audits Closed | E61: Open CAs | G61: Overdue CAs | I61: PIRs Effective | K61: PIRs Pending
A62: =COUNTA(A7:A12) -> 6 | C62: =COUNTIF(E7:E12,"Closed") -> 4 | E62: =COUNTIF(G23:G36,"In Progress") -> 9 | G62: =COUNTIF(H23:H36,"<0") -> 4 | I62: =COUNTIF(H40:H47,"Effective") -> 5 | K62: =COUNTIF(H40:H47,"Pending") -> 3
A63: Scheduled + completed | C63: Findings closed out | E63: Active remediation | G63: Past target close date | I63: Controls confirmed working | K63: Awaiting effectiveness review
A65: End of Management Review and Internal Audit Tracker | ISO 42001 Clauses 9.2, 9.3, 10.1, 10.2 | Owner: AI Security Manager & Internal Audit | Classification: Internal - Restricted

Sheet Dashboard
A1: AI Security Manager Executive Dashboard V2 - Mid-Sized UK Insurer
A2: Formula-driven control tower for AI governance, risk, security, services, incidents, audit readiness, evidence, vendor assurance, roadmap and budget. Owner AI Security Manager. As at 02/05/2026.
A3: Open TOM Index for navigation | B3: Open ID Glossary
A5: 1. Headline Posture
A6: Active AI Use Cases | D6: Tier 1 Critical Use Cases | G6: ISO 42001 Audit Readiness | J6: Maturity Score Pct of Target
A7: =COUNTIF('AI Use Case Register'!R5:R26,"Approved") -> 20 | D7: =COUNTIF('AI Use Case Register'!Q5:Q26,"Tier 1") -> 11 | G7: =AVERAGE('[1]ISO 42001 Audit Readiness Matri'!K5:K42)/3 -> #REF! | J7: =SUM('Maturity Assessment'!D5:D13)/SUM('Maturity Assessment'!F5:F13) -> 0.76315789
A8: Approved use cases in production | D8: Tier 1 critical AI use cases | G8: Average readiness vs max 3 across 38 clauses + Annex A | J8: Composite of 9 maturity domains vs target
A9: High or Critical Residual Risks | D9: KRI Breaches Red | G9: Open Incidents | J9: Quantified Residual Exposure
A10: =COUNTIF('Risk Quantification'!K5:K17,">=15") -> 0 | D10: =COUNTIF('KRI Tracking'!J5:J13,"Red") -> 0 | G10: =COUNTIF('Incident Analysis'!M5:M12,"Open")+COUNTIF('Incident Analysis'!M5:M12,"Under Review") -> 0 | J10: =SUM('Risk Quantification'!L5:L17) -> 53.7
A11: Residual score 15 or higher (max 25) | D11: KRIs above red threshold | G11: Open or under review (rolling 90d) | J11: Total residual exposure across 13 risks
A13: 2. ISO/IEC 42001 Audit Readiness
A14: Clauses Audit Ready | D14: Clauses Major NC Risk | G14: Evidence Items Stale | J14: Evidence Items Due Soon
A15: =COUNTIF('[1]ISO 42001 Audit Readiness Matri'!K5:K42,3) -> #VALUE! | D15: =COUNTIF('[1]ISO 42001 Audit Readiness Matri'!L5:L42,"Major*") -> #VALUE! | G15: =COUNTIF('[2]Evidence Register'!O5:O34,"Stale") -> #VALUE! | J15: =COUNTIF('[2]Evidence Register'!O5:O34,"Due Soon") -> #VALUE!
A16: Score of 3 (Audit Ready) out of 38 items | D16: Items where absence is potential major nonconformity | G16: Evidence past next-review date | J16: Evidence due in next 30 days
A17: Controls Implemented | D17: Controls Partial | G17: Controls with Open Gap | J17: Controls Lacking Evidence
A18: =COUNTIF('Compliance Mapping'!K5:K20,"Implemented") -> 12 | D18: =COUNTIF('Compliance Mapping'!K5:K20,"Partially Implemented") -> 4 | G18: =SUMPRODUCT(('Compliance Mapping'!P5:P20<>"No material gaps")*(LEN('Compliance Mapping'!P5:P20)>0)) -> 6 | J18: =COUNTBLANK('Compliance Mapping'!L5:L20) -> 0
A19: Out of 16 controls in scope | D19: Controls with open implementation gaps | G19: Controls with documented residual gap | J19: Controls with no linked evidence ID
A21: 3. Service Delivery, Incidents and Vendor Assurance
A22: Open Service Requests | D22: SLA Met Rate | G22: Tier 1 Vendor DD Currency | J22: Vendor Reviews Overdue
A23: =COUNTIF('Service Request Log'!H5:H28,"Open")+COUNTIF('Service Request Log'!H5:H28,"In Progress") -> 6 | D23: =COUNTIF('Service Request Log'!L5:L28,"Yes")/(COUNTIF('Service Request Log'!L5:L28,"Yes")+COUNTIF('Service Request Log'!L5:L28,"No")) -> 0.88888889 | G23: =COUNTIF('Third-Party Risk Services'!G5:G20,"Complete")/COUNTA('Third-Party Risk Services'!G5:G20) -> 0.9375 | J23: =SUMPRODUCT(('Third-Party Risk Services'!J5:J20<TODAY())*1) -> 0
A24: Open or in flight requests | D24: Pct of closed requests within SLA | G24: Pct of vendors with current due diligence | J24: Vendors with contract renewal date in past
A25: Sev 1 or 2 Incidents (90d) | D25: Avg Days to Close Request | G25: KRI Amber | J25: Evidence Currency Pct
A26: =COUNTIF('Incident Analysis'!D5:D12,"Sev 1")+COUNTIF('Incident Analysis'!D5:D12,"Sev 2") -> 4 | D26: =AVERAGEIF('Service Request Log'!H5:H28,"Closed",'Service Request Log'!K5:K28) -> 13.5 | G26: =COUNTIF('KRI Tracking'!J5:J13,"Amber") -> 2 | J26: =COUNTIF('[2]Evidence Register'!O5:O34,"Current")/COUNTA('[2]Evidence Register'!O5:O34) -> #VALUE!
A27: Sev 1 and Sev 2 in rolling 90 days | D27: Mean ageing of closed requests (days) | G27: KRIs in amber zone | J27: Evidence items current vs total
A29: 4. Roadmap, Budget and People
A30: Roadmap Avg Pct Complete | D30: Total FY 26 27 Budget | G30: Budget Variance | J30: FTE Gap Vacancies
A31: =AVERAGE('Implementation Roadmap'!I5:I16) -> 0.375 | D31: ='Financial Analysis'!E34 -> 6159.3 | G31: ='Financial Analysis'!H34 -> -58 | J31: =SUM('Resource Planning'!D5:D16)-SUM('Resource Planning'!C5:C16) -> 5
A32: Weighted across 12 roadmap items | D32: Run plus Change plus Contingency | G32: Negative equals favourable underspend | J32: Open vacancies vs target
A33: Roadmap Items On Track | D33: Roadmap Items At Risk | G33: Open Corrective Actions | J33: Overdue Corrective Actions
A34: =COUNTIF('Implementation Roadmap'!H5:H16,"On Track")+COUNTIF('Implementation Roadmap'!H5:H16,"In Progress") -> 10 | D34: =COUNTIF('Implementation Roadmap'!H5:H16,"Delayed")+COUNTIF('Implementation Roadmap'!H5:H16,"Not Started") -> 2 | G34: =COUNTIF('[3]Management Review and Internal '!G24:G37,"Open")+COUNTIF('[3]Management Review and Internal '!G24:G37,"In Progress") -> #VALUE! | J34: =SUMPRODUCT(('[3]Management Review and Internal '!G24:G37<>"Closed")*('[3]Management Review and Internal '!F24:F37<TODAY())*1) -> #REF!
A35: On Track or In Progress workstreams | D35: Delayed or Not Started workstreams | G35: Open or In Progress corrective actions | J35: Open actions past target date
A37: 5. Top 5 Residual Risks (by Quantified Exposure)
A38: Risk ID | C38: Risk Title | F38: Residual Score | G38: Exposure | H38: Treatment | J38: Owner
A39: RSK-011 | C39: Regulatory breach (Consumer Duty / fairness / FCA) | F39: ='Risk Quantification'!K15 -> 10 | G39: ='Risk Quantification'!L15 -> 7.5 | H39: ='Risk Quantification'!M15 -> Mitigate | J39: Rebecca Lloyd
A40: RSK-001 | C40: Model performance drift causing pricing/UW losses | F40: ='Risk Quantification'!K5 -> 8 | G40: ='Risk Quantification'!L5 -> 6.5 | H40: ='Risk Quantification'!M5 -> Mitigate | J40: Mohammed Iqbal
A41: RSK-010 | C41: Cloud misconfiguration exposing AI workloads | F41: ='Risk Quantification'!K14 -> 10 | G41: ='Risk Quantification'!L14 -> 6 | H41: ='Risk Quantification'!M14 -> Mitigate | J41: Karen Holloway
A42: RSK-004 | C42: Pricing or fairness bias against protected groups | F42: ='Risk Quantification'!K8 -> 8 | G42: ='Risk Quantification'!L8 -> 5.5 | H42: ='Risk Quantification'!M8 -> Mitigate | J42: Helen Carter
A43: RSK-005 | C43: LLM hallucination delivered to customer | F43: ='Risk Quantification'!K9 -> 8 | G43: ='Risk Quantification'!L9 -> 4.8 | H43: ='Risk Quantification'!M9 -> Mitigate | J43: Olivia Bennett
A45: 6. Top 10 Remediation Actions (overdue first, then due soon)
A46: Action ID | C46: Action | G46: Owner | H46: Target Date | J46: Days to Target | K46: Status
A47: CA-010 | C47: Complete impact assessments for customer-facing AI use cases | G47: Rebecca Lloyd | H47: ='[3]Management Review and Internal '!F33 -> #REF! | J47: ='[3]Management Review and Internal '!H33 -> #REF! | K47: ='[3]Management Review and Internal '!G33 -> #REF!
A48: CA-011 | C48: Documented exit plans for remaining Tier-1 AI vendors (VEN-001, VEN-006) | G48: Sarah Mitchell | H48: ='[3]Management Review and Internal '!F34 -> #REF! | J48: ='[3]Management Review and Internal '!H34 -> #REF! | K48: ='[3]Management Review and Internal '!G34 -> #REF!
A49: CA-009 | C49: Strengthen 9.3 management review input checklist | G49: Andrew Pollard | H49: ='[3]Management Review and Internal '!F32 -> #REF! | J49: ='[3]Management Review and Internal '!H32 -> #REF! | K49: ='[3]Management Review and Internal '!G32 -> #REF!
A50: CA-012 | C50: Accelerate Tier-1 vendor DD currency to 100 percent | G50: Sarah Mitchell | H50: ='[3]Management Review and Internal '!F35 -> #REF! | J50: ='[3]Management Review and Internal '!H35 -> #REF! | K50: ='[3]Management Review and Internal '!G35 -> #REF!
A51: CA-014 | C51: Push training campaign to lift completion to 95 percent | G51: Daniel O'Reilly | H51: ='[3]Management Review and Internal '!F37 -> #REF! | J51: ='[3]Management Review and Internal '!H37 -> #REF! | K51: ='[3]Management Review and Internal '!G37 -> #REF!
A52: CA-013 | C52: Targeted training to top-3 BUs with elevated DLP exceptions | G52: Karen Holloway | H52: ='[3]Management Review and Internal '!F36 -> #REF! | J52: ='[3]Management Review and Internal '!H36 -> #REF! | K52: ='[3]Management Review and Internal '!G36 -> #REF!
A53: CA-001 | C53: Add seasonality features to FNOL training set; tighten drift thresholds | G53: Mohammed Iqbal | H53: ='[3]Management Review and Internal '!F24 -> #REF! | J53: ='[3]Management Review and Internal '!H24 -> #REF! | K53: ='[3]Management Review and Internal '!G24 -> #REF!
A54: CA-008 | C54: Hallucination filter re-tune; vendor change-window QA alignment | G54: Olivia Bennett | H54: ='[3]Management Review and Internal '!F31 -> #REF! | J54: ='[3]Management Review and Internal '!H31 -> #REF! | K54: ='[3]Management Review and Internal '!G31 -> #REF!
A55: CA-004 | C55: Sensitivity-label review cycle; Purview policy refresh | G55: Karen Holloway | H55: ='[3]Management Review and Internal '!F27 -> #REF! | J55: ='[3]Management Review and Internal '!H27 -> #REF! | K55: ='[3]Management Review and Internal '!G27 -> #REF!
A56: CA-005 | C56: Vendor SLA exceptions; resilience plan updated for tabletop scenario | G56: James Whitfield | H56: ='[3]Management Review and Internal '!F28 -> #REF! | J56: ='[3]Management Review and Internal '!H28 -> #REF! | K56: ='[3]Management Review and Internal '!G28 -> #REF!
A58: 7. Maturity by Domain (1 Initial to 5 Optimised)
A59: Domain | G59: Current | H59: Target | I59: Gap | J59: Owner
A60: Governance (MAT-01) | G60: ='Maturity Assessment'!D5 -> 4 | H60: ='Maturity Assessment'!F5 -> 5 | I60: ='Maturity Assessment'!H5 -> 1 | J60: Andrew Pollard
A61: Risk Management (MAT-02) | G61: ='Maturity Assessment'!D6 -> 3 | H61: ='Maturity Assessment'!F6 -> 4 | I61: ='Maturity Assessment'!H6 -> 1 | J61: Geoffrey Sanders
A62: Security Controls (MAT-03) | G62: ='Maturity Assessment'!D7 -> 4 | H62: ='Maturity Assessment'!F7 -> 5 | I62: ='Maturity Assessment'!H7 -> 1 | J62: Karen Holloway
A63: Privacy and Data Handling (MAT-04) | G63: ='Maturity Assessment'!D8 -> 3 | H63: ='Maturity Assessment'!F8 -> 4 | I63: ='Maturity Assessment'!H8 -> 1 | J63: Rebecca Lloyd
A64: Monitoring and Assurance (MAT-05) | G64: ='Maturity Assessment'!D9 -> 3 | H64: ='Maturity Assessment'!F9 -> 4 | I64: ='Maturity Assessment'!H9 -> 1 | J64: Mohammed Iqbal
A65: Third-Party Oversight (MAT-06) | G65: ='Maturity Assessment'!D10 -> 3 | H65: ='Maturity Assessment'!F10 -> 4 | I65: ='Maturity Assessment'!H10 -> 1 | J65: Sarah Mitchell
A66: Lifecycle Management (MAT-07) | G66: ='Maturity Assessment'!D11 -> 3 | H66: ='Maturity Assessment'!F11 -> 4 | I66: ='Maturity Assessment'!H11 -> 1 | J66: Daniel O'Reilly
A67: Resilience and Continuity (MAT-08) | G67: ='Maturity Assessment'!D12 -> 3 | H67: ='Maturity Assessment'!F12 -> 4 | I67: ='Maturity Assessment'!H12 -> 1 | J67: Yvonne Mathieson
A68: Evidence and Documentation (MAT-09) | G68: ='Maturity Assessment'!D13 -> 3 | H68: ='Maturity Assessment'!F13 -> 4 | I68: ='Maturity Assessment'!H13 -> 1 | J68: Sarah Mitchell
A70: 8. Management Commentary (Q1 2026)
A71: ISO/IEC 42001 readiness is on a credible glide-path with 3 of 38 clauses Audit Ready (score 3) and 24 Ready with minor gaps (score 2). The function is on track for an internal readiness review by Q4 2026 (RDM-007). Leadership focus this quarter is on closing four major-risk areas before audit - customer-facing impact assessments (CA-010), Tier-1 vendor exit plans (CA-011), AIMS management review input checklist (CA-009), and AI awareness training completion (CA-014). The risk register stands at 53.7m total residual exposure, with regulatory breach (RSK-011 7.5m) and cloud misconfiguration (RSK-010 6.0m) the dominant exposures. KRI posture is Green-Amber - two amber breaches (DLP exceptions, cloud config drift) under remediation; no red breaches. Q1 budget is favourable through vacancy underspend; Phase 1 of the roadmap is at 50 percent complete.
A73: 9. Quick Navigation
A74: Use Cases | B74: Risks | C74: KRIs | D74: KPIs | E74: Compliance V2 | F74: Evidence | G74: ISO 42001 Matrix | H74: Mgmt Review | I74: Roadmap | J74: Vendors | K74: Finance | L74: TOM Index
A77: 10. Top 5 Board Risks (Residual Score and Exposure)
A78: Risk ID | C78: Risk Title | G78: Residual Score | H78: Exposure | I78: Treatment | K78: Owner
A79: RSK-011 | C79: Regulatory breach (Consumer Duty / fairness / FCA) | G79: ='Risk Quantification'!K15 -> 10 | H79: ='Risk Quantification'!L15 -> 7.5 | I79: ='Risk Quantification'!M15 -> Mitigate | K79: Rebecca Lloyd
A80: RSK-001 | C80: Model performance drift causing pricing/UW losses | G80: ='Risk Quantification'!K5 -> 8 | H80: ='Risk Quantification'!L5 -> 6.5 | I80: ='Risk Quantification'!M5 -> Mitigate | K80: Mohammed Iqbal
A81: RSK-010 | C81: Cloud misconfiguration exposing AI workloads | G81: ='Risk Quantification'!K14 -> 10 | H81: ='Risk Quantification'!L14 -> 6 | I81: ='Risk Quantification'!M14 -> Mitigate | K81: Karen Holloway
A82: RSK-004 | C82: Pricing or fairness bias against protected groups | G82: ='Risk Quantification'!K8 -> 8 | H82: ='Risk Quantification'!L8 -> 5.5 | I82: ='Risk Quantification'!M8 -> Mitigate | K82: Helen Carter
A83: RSK-005 | C83: LLM hallucination delivered to customer | G83: ='Risk Quantification'!K9 -> 8 | H83: ='Risk Quantification'!L9 -> 4.8 | I83: ='Risk Quantification'!M9 -> Mitigate | K83: Olivia Bennett
A85: 11. Critical AI Use Cases Requiring Attention
A86: Use Case ID | C86: Use Case | G86: Tier | H86: Approval Status | J86: Reason for Attention
A87: AUC-007 | C87: MI / Reporting Assistant - Finance | G87: Tier 2 | H87: Conditionally Approved | J87: Conditional approval extension; output validation strengthening required
A88: AUC-016 | C88: HR CV Screening Pilot | G88: Tier 2 | H88: Conditionally Approved | J88: Quarterly bias review required; pilot scope under review
A89: AUC-004 | C89: Customer Service Copilot - Voice Agent Assist | G89: Tier 1 | H89: Approved | J89: Hallucination filter retune live (PIR-003 closed); ongoing sample QA
A90: AUC-013 | C90: Smart Search - Policy Wordings (Customer Portal) | G90: Tier 2 | H90: Approved | J90: INC-008 closed; vendor change-window controls being aligned
A91: AUC-011 | C91: Vulnerable Customer Detection - Service Calls | G91: Tier 1 | H91: Approved | J91: Consumer Duty quarterly review live; specialist routing performance trending
A93: 12. Open High-Severity Incidents (rolling 90 days)
A94: ="There are "&(COUNTIF('Incident Analysis'!D5:D12,"Sev 1")+COUNTIF('Incident Analysis'!D5:D12,"Sev 2"))&" Sev 1 or Sev 2 incidents in the rolling 90-day window. "&(COUNTIF('Incident Analysis'!M5:M12,"Open")+COUNTIF('Incident Analysis'!M5:M12,"Under Review"))&" currently open or under review. All eight closed PIRs subject to effectiveness review at MR-2026-Q2." -> There are 4 Sev 1 or Sev 2 incidents in the rolling 90-day window. 0 currently open or under review. All eight closed PIRs subject to effectiveness review at MR-2026-Q2.
A96: 13. Overdue Remediation Actions
A97: Action ID | C97: Action | G97: Owner | H97: Target Date | J97: Days to Target | K97: Status
A98: CA-009 | C98: Strengthen 9.3 management review input checklist | G98: Andrew Pollard | H98: ='[3]Management Review and Internal '!F32 -> #REF! | J98: ='[3]Management Review and Internal '!H32 -> #REF! | K98: ='[3]Management Review and Internal '!G32 -> #REF!
A99: CA-010 | C99: Customer-facing AI impact assessments refresh | G99: Rebecca Lloyd | H99: ='[3]Management Review and Internal '!F33 -> #REF! | J99: ='[3]Management Review and Internal '!H33 -> #REF! | K99: ='[3]Management Review and Internal '!G33 -> #REF!
A100: CA-011 | C100: Tier-1 vendor exit plans (VEN-001, VEN-006) | G100: Sarah Mitchell | H100: ='[3]Management Review and Internal '!F34 -> #REF! | J100: ='[3]Management Review and Internal '!H34 -> #REF! | K100: ='[3]Management Review and Internal '!G34 -> #REF!
A101: CA-012 | C101: Accelerate Tier-1 vendor DD currency to 100 percent | G101: Sarah Mitchell | H101: ='[3]Management Review and Internal '!F35 -> #REF! | J101: ='[3]Management Review and Internal '!H35 -> #REF! | K101: ='[3]Management Review and Internal '!G35 -> #REF!
A102: CA-014 | C102: Lift training completion to 95 percent | G102: Daniel O'Reilly | H102: ='[3]Management Review and Internal '!F37 -> #REF! | J102: ='[3]Management Review and Internal '!H37 -> #REF! | K102: ='[3]Management Review and Internal '!G37 -> #REF!
A104: 14. Third-Party AI Risk Hotspots
A105: Vendor ID | C105: Supplier | G105: Residual | H105: Action Required | J105: Owner
A106: VEN-001 | C106: Microsoft Azure OpenAI / M365 Copilot | G106: Amber | H106: Quarterly subprocessor review; refresh DPIA after RDM-002 | J106: Sarah Mitchell
A107: VEN-003 | C107: ABBYY (Document AI) | G107: Amber | H107: Complete privacy review by 30/06/2026 (CA-002) | J107: Sarah Mitchell
A108: VEN-007 | C108: Tractable (Computer Vision) | G108: Amber | H108: Complete security review refresh (CA-005) | J108: Sarah Mitchell
A109: VEN-013 | C109: Persistent Systems (MLOps Augmentation) | G109: Amber | H109: Refresh AI-specific contract clauses; finalise renewal (CA-008) | J109: Sarah Mitchell
A110: VEN-015 | C110: Splunk (Transitional SIEM) | G110: Amber | H110: Complete migration to Sentinel by Q4 2026 (RDM-010) | J110: Karen Holloway
A112: 15. Tier-1 AI Use Case Control Coverage
A113: Tier-1 Use Cases (count) | D113: With Monitoring (CTL-005) | G113: With HITL (CTL-008) | J113: With Independent Bias Test (CTL-014)
A114: =COUNTIF('AI Use Case Register'!Q5:Q26,"Tier 1") -> 11 | D114: =SUMPRODUCT(('AI Use Case Register'!Q5:Q26="Tier 1")*ISNUMBER(SEARCH("CTL-005",'AI Use Case Register'!U5:U26))) -> 4 | G114: =SUMPRODUCT(('AI Use Case Register'!Q5:Q26="Tier 1")*ISNUMBER(SEARCH("CTL-008",'AI Use Case Register'!U5:U26))) -> 7 | J114: =SUMPRODUCT(('AI Use Case Register'!Q5:Q26="Tier 1")*ISNUMBER(SEARCH("CTL-014",'AI Use Case Register'!U5:U26))) -> 4
A115: Critical AI use cases in scope | D115: Tier-1 with production monitoring | G115: Tier-1 with HITL gate | J115: Tier-1 with independent bias test
A117: 16. Maturity by Domain (Board View)
...

Sheet Executive Report
A1: Executive Report V2 - AI Security and Governance Posture
A2: Quarterly leadership view of AI security, governance, risk, audit readiness, evidence and roadmap. Owner AI Security Manager. Reporting Period Q1 2026. Audience Board, ExCo, Risk Committee, Audit Committee.
A3: Back to Dashboard
B5: 1. Executive Summary
B6: The AI Security function is on a credible glide-path toward ISO/IEC 42001 internal readiness review by Q4 2026 and certification readiness assessment in Q1 2027 (RDM-007). 22 AI use cases are in production, of which 11 are Tier 1 and customer-impacting. The composite maturity score is 3.22 of 5.00 against a target of 4.22 (76 percent of target). Across 38 ISO/IEC 42001 clauses and Annex A controls, 3 items are Audit Ready (score 3) and 24 are Ready with minor gaps (score 2); average readiness is 1.95 (65 percent of max). Twelve items carry potential major nonconformity risk if absent and are the focus of remediation. There are no Red KRI breaches; two KRIs are Amber under remediation. Quantified residual exposure is 53.7m, dominated by RSK-011 Regulatory breach (7.5m) and RSK-010 Cloud misconfiguration (6.0m).
B8: 2. ISO/IEC 42001 Audit Readiness Posture
B9: ISO/IEC 42001 readiness is the function's primary focus. The AIMS scope, AI policy, and governance framework are documented and approved (EVD-023, EVD-024, EVD-027). Risk management (Clause 6.1), operational controls (Clause 8.1) and performance evaluation (Clause 9.1) are operating with strong evidence. Three areas carry the largest residual gap and are the most likely sources of nonconformity at audit if not closed - (a) AI system impact assessments under Clause 6.1.4 and Annex A.6.2.5 where customer-facing assessments require refresh after vendor sub-processor changes (CA-010); (b) third-party AI substitutability under Clause 8.1 and Annex A.7.5 where Tier-1 vendor exit plans are incomplete for VEN-001 and VEN-006 (CA-011); and (c) competence and awareness under Clauses 7.2-7.3 and Annex A.7.6 where training completion is 86 percent against a 95 percent target (CA-014). The function does not claim certification will be achieved - certification ultimately depends on assessor judgement and the actual implementation observed. Internal readiness review (AUDIT-006) is scheduled for September 2026.
B11: 3. Strategic Posture
B12: The AI estate continues to expand within Risk Appetite. Internal models (underwriting, claims triage, fraud, pricing) remain robust with strong assurance and monitoring coverage at 92 percent for Tier 1 models. Customer-facing AI (voice agent assist, vulnerable customer detection, smart search) has matured with output guardrails, sample QA, complaint linkage, and refreshed hallucination filter post INC-008. Generative AI productivity tooling is embedded with Microsoft Purview controls; legacy SharePoint label inheritance is the residual gap (CA-004). The Splunk to Sentinel migration (RDM-010) is 60 percent complete and on track to retire dual-running cost in Q4 2026.
B14: 4. Top 5 Material Risks (by Quantified Residual Exposure)
B15: Risk ID | C15: Risk | D15: Residual Score | E15: Exposure | F15: Treatment | G15: Owner
B16: RSK-011 | C16: Regulatory breach (Consumer Duty, fairness, FCA) | D16: ='Risk Quantification'!K15 -> 10 | E16: ='Risk Quantification'!L15 -> 7.5 | F16: Mitigate | G16: Rebecca Lloyd
B17: RSK-001 | C17: Model performance drift causing pricing/UW losses | D17: ='Risk Quantification'!K5 -> 8 | E17: ='Risk Quantification'!L5 -> 6.5 | F17: Mitigate | G17: Mohammed Iqbal
B18: RSK-010 | C18: Cloud misconfiguration exposing AI workloads | D18: ='Risk Quantification'!K14 -> 10 | E18: ='Risk Quantification'!L14 -> 6 | F18: Mitigate | G18: Karen Holloway
B19: RSK-004 | C19: Pricing or fairness bias against protected groups | D19: ='Risk Quantification'!K8 -> 8 | E19: ='Risk Quantification'!L8 -> 5.5 | F19: Mitigate | G19: Helen Carter
B20: RSK-005 | C20: LLM hallucination delivered to customer | D20: ='Risk Quantification'!K9 -> 8 | E20: ='Risk Quantification'!L9 -> 4.8 | F20: Mitigate | G20: Olivia Bennett
B22: 5. Likely Audit Test Focus and Interview Owners (Top 10 by Audit Sensitivity)
B23: Clause / Annex A | C23: Test Focus | D23: Interview Owner | E23: Readiness Score | F23: Status | G23: Linked Evidence
B24: Clause 4.3 - Scope of AIMS | C24: Auditor will request AIMS scope statement and trace it to actual AI estate | D24: AI Security Manager | E24: 3 | F24: Audit Ready | G24: EVD-023
B25: Clause 5.2 - AI Policy | C25: Auditor will check policy approval, version control, and that staff can articulate it | D25: AI Security Manager / CDO | E25: 3 | F25: Audit Ready | G25: EVD-024
B26: Clause 6.1.2 - AI risk assessment | C26: Auditor will sample risk records and re-perform on selected use case | D26: CRO / AI Security Manager | E26: 2 | F26: Ready (minor gaps) | G26: EVD-008
B27: Clause 6.1.4 / A.6.2.5 - AI system impact assessment | C27: Auditor will sample 2-3 material use cases and request full impact assessment | D27: AI Security Manager / DPO | E27: 2 | F27: Ready (minor gaps) | G27: EVD-004,EVD-008
B28: Clause 7.3 / A.7.6 - Awareness and training | C28: Auditor will interview random colleagues to test awareness | D28: AI Security Manager / Comms | E28: 1 | F28: Partial - Major NC risk | G28: EVD-029
B29: Clause 8.1 / A.7.5 - Vendor exit | C29: Auditor will check exit-plan completeness for material vendors | D29: Sarah Mitchell | E29: 1 | F29: Partial - Major NC risk | G29: EVD-030
B30: Clause 9.1 / A.6.2.7 - Fairness and bias | C30: Auditor will sample fairness test records for AUC-010 and AUC-014 | D30: Helen Carter / Olivia Bennett | E30: 2 | F30: Ready (minor gaps) | G30: EVD-010,EVD-014,EVD-019
B31: Clause 9.2 - Internal audit | C31: Auditor will request full internal audit programme and review findings closure | D31: CAE / Liam Carmichael | E31: 2 | F31: Ready (minor gaps) | G31: EVD-026
B32: Clause 9.3 - Management review | C32: Auditor will check that all 9.3 inputs are evidenced (changes, performance, audits, risks, opportunities) | D32: AIGF Chair / AI Security Manager | E32: 2 | F32: Ready (minor gaps) | G32: EVD-027
B33: Clause 10.2 - Corrective action | C33: Auditor will sample incidents and trace through corrective action and effectiveness | D33: AI Security Manager / IR | E33: 2 | F33: Ready (minor gaps) | G33: EVD-013,EVD-028
B35: 6. Recent Incidents and Themes
B36: Eight incidents have been recorded and closed in the rolling 90-day window. No customer detriment was confirmed. Dominant themes are Output Quality (4 incidents - INC-002, INC-003, INC-006, INC-008), Model Drift (1 incident - INC-001) and Vendor Outage (1 incident - INC-005). Each incident has a closed PIR with lessons fed into controls and roadmap items. Notable improvements include the hallucination filter retune (CTL-010), tighter alignment of vendor change windows with QA windows (CTL-007), and PAM re-baseline post INC-007. All eight PIRs are subject to effectiveness review at the next quarterly Management Review of AIMS (MR-2026-Q2).
B38: 7. Top 10 Priority Remediation Actions (overdue first; ISO 42001-impacting)
B39: Action ID | C39: Action | D39: Owner | E39: Target Date | F39: Status | G39: Notes
B40: CA-010 | C40: Complete impact assessments for all customer-facing AI use cases (refresh post-vendor sub-processor changes) | D40: Rebecca Lloyd | E40: ='Management Review and Internal '!F32 -> 30/09/2026 | F40: ='Management Review and Internal '!G32 -> In Progress | G40: Closes Clause 6.1.4 / A.6.2.5 gap
B41: CA-011 | C41: Documented exit plans for remaining Tier-1 AI vendors (VEN-001, VEN-006) | D41: Sarah Mitchell | E41: ='Management Review and Internal '!F33 -> 30/09/2026 | F41: ='Management Review and Internal '!G33 -> In Progress | G41: Closes Clause 8.1 / A.7.5 gap; PRA Op Resilience aligned
B42: CA-009 | C42: Strengthen 9.3 management review input checklist | D42: Andrew Pollard | E42: ='Management Review and Internal '!F31 -> 30/06/2026 | F42: ='Management Review and Internal '!G31 -> In Progress | G42: Closes Clause 9.3 management review gap
B43: CA-014 | C43: Push training campaign to lift completion to 95 percent | D43: Daniel O'Reilly | E43: ='Management Review and Internal '!F36 -> 30/09/2026 | F43: ='Management Review and Internal '!G36 -> In Progress | G43: Closes Clauses 7.2-7.3 / A.7.6 gap
B44: CA-012 | C44: Accelerate Tier-1 vendor DD currency to 100 percent | D44: Sarah Mitchell | E44: ='Management Review and Internal '!F34 -> 30/06/2026 | F44: ='Management Review and Internal '!G34 -> In Progress | G44: Closes A.7.3 vendor DD gap
B45: CA-013 | C45: Targeted training to top-3 BUs with elevated DLP exceptions | D45: Karen Holloway | E45: ='Management Review and Internal '!F35 -> 30/06/2026 | F45: ='Management Review and Internal '!G35 -> In Progress | G45: Reduces KRI-007 DLP exception trend
B46: CA-001 | C46: Add seasonality features to FNOL training set; tighten drift thresholds | D46: Mohammed Iqbal | E46: ='Management Review and Internal '!F23 -> 30/06/2026 | F46: ='Management Review and Internal '!G23 -> Closed | G46: Closes PIR-001 lessons learned
B47: CA-008 | C47: Hallucination filter re-tune; vendor change-window QA alignment | D47: Olivia Bennett | E47: ='Management Review and Internal '!F30 -> 30/06/2026 | F47: ='Management Review and Internal '!G30 -> Closed | G47: Closes PIR-008 lessons learned
B48: CA-004 | C48: Sensitivity-label review cycle; Purview policy refresh | D48: Karen Holloway | E48: ='Management Review and Internal '!F26 -> 30/09/2026 | F48: ='Management Review and Internal '!G26 -> In Progress | G48: Closes legacy SharePoint label gap
B49: CA-005 | C49: Vendor SLA exceptions; resilience plan updated for tabletop scenario | D49: James Whitfield | E49: ='Management Review and Internal '!F27 -> 30/09/2026 | F49: ='Management Review and Internal '!G27 -> In Progress | G49: Strengthens BCP for vendor outage
B51: 8. Investment Priorities (FY 2026/27)
B52: Investment | C52: Category | D52: Annual Cost | E52: Outcome | F52: Linked Roadmap | G52: Owner
B53: ISO 42001 readiness programme | C53: Programme - Change | D53: ='Financial Analysis'!E24 -> 240 | E53: Internal readiness review Q4 2026; certification readiness Q1 2027 | F53: RDM-007 | G53: Sarah Mitchell
B54: AI security tooling enhancements | C54: Programme - Change | D54: ='Financial Analysis'!E25 -> 180 | E54: Closes RSK-008 evidence gap; supports A.6.2.9 logging | F54: RDM-002 | G54: Karen Holloway
B55: Splunk to Sentinel migration | C55: Programme - Change | D55: ='Financial Analysis'!E26 -> 160 | E55: Retires dual-run; AI-aware detections; supports A.6.2.9 | F55: RDM-010 | G55: Karen Holloway
B56: Sensitivity-label remediation | C56: Programme - Change | D56: ='Financial Analysis'!E27 -> 120 | E56: Closes CTL-006 gap; supports A.7.4 | F56: RDM-002 | G56: Karen Holloway
B57: Tier-2 model monitoring uplift | C57: Programme - Change | D57: ='Financial Analysis'!E28 -> 140 | E57: Lifts MAT-05 to Managed; supports A.6.2.8 | F57: RDM-007 | G57: Mohammed Iqbal
B58: Customer-facing AI guardrail uplift | C58: Programme - Change | D58: ='Financial Analysis'!E29 -> 100 | E58: Reduces RSK-005 exposure; supports A.6.2.11 | F58: RDM-001 | G58: Olivia Bennett
B59: Vendor exit planning | C59: Programme - Change | D59: ='Financial Analysis'!E30 -> 80 | E59: Closes A.7.5 gap; supports PRA Op Resilience | F59: RDM-005 | G59: Sarah Mitchell
B60: Training and awareness | C60: Programme - Change | D60: ='Financial Analysis'!E31 -> 60 | E60: Lifts CTL-016 to Implemented; closes A.7.6 gap | F60: Cross-cutting | G60: Daniel O'Reilly
B61: Total Change Investment | C61: Subtotal | D61: ='Financial Analysis'!E32 -> 1080 | E61: Phase 1 + Phase 2 delivery | F61: All RDM | G61: AI Security Manager
B63: 9. Key Leadership Decisions Required
B64: Decision | C64: Forum | D64: Recommendation | E64: Decision Date | F64: Owner
B65: Approve ISO 42001 internal readiness review pack and certification path | C65: ExCo / Risk Committee | D65: Approve subject to AUDIT-006 outcome | E65: 46418 | F65: Sarah Mitchell
B66: Approve closure plan for 4 major-NC-risk areas | C66: AI Governance Forum | D66: Approve - CA-010, CA-011, CA-009, CA-014 | E66: 46203 | F66: Sarah Mitchell
B67: Approve Salesforce Einstein-feature posture | C67: AI Governance Forum | D67: Maintain restricted posture pending vendor AI feature review | E67: 46203 | F67: Olivia Bennett
B68: Approve Tier-1 vendor exit plans (VEN-001, VEN-006) | C68: Third-Party Oversight Forum | D68: Approve documented substitutability assessments | E68: 46295 | F68: Sarah Mitchell
B69: Approve net hire of 5 FTE to close resource gap | C69: ExCo | D69: Approve in line with FY26/27 plan | E69: 46203 | F69: Sarah Mitchell
B70: Reset risk appetite for residual AI risk
B72: 10. Forward Look (Next 12 Months)
B73: Over the next 12 months, the function will deliver Phase 1 (Foundation) and progress Phase 2 (Embed) of the roadmap. ISO 42001 internal readiness review (RDM-007) is the centrepiece, supported by the lifecycle framework v2 (RDM-008) and SOC modernisation (RDM-010). Customer-facing AI guardrails (RDM-001), GenAI productivity controls (RDM-002), and pricing fairness (RDM-003) will continue maturing. Material risk reduction is targeted across regulatory exposure (RSK-011), customer-facing model risks (RSK-005, RSK-007, RSK-012) and cloud security (RSK-010). The first AIMS internal audit cycle (AUDIT-002 to AUDIT-006) will close out by year-end and feed into Q4 management review of AIMS. Phase 3 workstreams - operating model uplift (RDM-011) and resilience modelling (RDM-012) - begin in H2 to lay foundations for FY 2027/28.
B75: 11. Sign-off and Distribution
B76: Role | C76: Name | D76: Action | E76: Date | F76: Distribution
B77: AI Security Manager | C77: Sarah Mitchell | D77: Prepared | E77: 46144 | F77: AI Governance Forum, ExCo, Risk Committee, Audit Committee
B78: CISO | C78: Karen Holloway | D78: Reviewed | E78: 46147 | F78: As above
B79: CRO | C79: Geoffrey Sanders | D79: Reviewed | E79: 46150 | F79: As above
B80: CDO (AIGF Chair) | C80: Andrew Pollard | D80: Approved | E80: 46154 | F80: Quarterly board cycle
A81: End of Executive Report | Owner: AI Security Manager | Distribution: Board, ExCo, Risk Committee, Audit Committee | Classification: Board Confidential

Sheet TOM & Strategy
A1: TOM and Strategy V3 - AI Security and Governance Target Operating Model
A2: Target operating model for AI security and governance in a mid-sized UK insurer. Owner AI Security Manager, ratified by AI Governance Forum. Reviewed annually. Inspired by ISO IEC 42001, NIST AI RMF, FCA Consumer Duty and PRA Operational Resilience.
A3: Back to Dashboard | B3: Open ID Glossary
B5: 0. Vision and Strategic Pillars
B6: Vision | D6: To enable Secure, Trustworthy and Ethical AI across the insurer through proactive risk management, embedded controls and standardised compliance, in line with ISO IEC 42001 and FCA Consumer Duty.
B8: Strategic Pillars (4)
B9: Pillar ID | C9: Pillar | D9: Outcome | E9: Linked Strategic Objective | F9: Linked Capability | G9: Lead Owner | H9: Primary Forum
B10: PIL-01 | C10: Governance and Compliance | D10: Embed an ISO IEC 42001 aligned AIMS with traceable evidence and audit-ready posture | E10: SO-01 | F10: CAP-01, CAP-09 | G10: AI Security Manager | H10: AI Governance Forum
B11: PIL-02 | C11: Data Security and Privacy | D11: Protect training data, prompts, outputs and customer data from leakage and unauthorised access | E11: SO-02 | F11: CAP-04, CAP-03 | G11: CISO and DPO | H11: Data Protection Forum
B12: PIL-03 | C12: Model Integrity and Fairness | D12: Prevent drift, bias, hallucination and tampering across material AI models | E12: SO-03 | F12: CAP-02, CAP-05 | G12: Mohammed Iqbal | H12: Model Risk Committee
B13: PIL-04 | C13: Threat Detection and Resilience | D13: Detect adversarial activity, vendor outage and AI-specific threats; recover within tested fallback | E13: SO-04, SO-05 | F13: CAP-03, CAP-08 | G13: CISO | H13: Tech Risk and Op Resilience
B15: 1. Strategic Objectives
B16: Objective ID | C16: Strategic Objective | D16: Outcome | E16: Owner | F16: Target Horizon | G16: Linked Roadmap | H16: Linked Pillar
B17: SO-01 | C17: Embed ISO IEC 42001 aligned AI Management System | D17: Internal readiness review Q4 2026; certification readiness assessment Q1 2027 | E17: AI Security Manager | F17: FY 2026/27 | G17: RDM-007 | H17: PIL-01
B18: SO-02 | C18: Strengthen customer-facing AI guardrails and Consumer Duty alignment | D18: Demonstrable customer outcomes monitored and improved; complaint linkage active | E18: Olivia Bennett | F18: FY 2026/27 | G18: RDM-001 | H18: PIL-02
B19: SO-03 | C19: Mature monitoring coverage across all production AI | D19: 98 percent Tier-1 and 85 percent Tier-2 model coverage with drift, performance and bias monitoring | E19: Mohammed Iqbal | F19: FY 2026/27 | G19: RDM-007 | H19: PIL-03
B20: SO-04 | C20: Reduce concentration risk on material AI vendors | D20: Documented exit plans for all Tier-1 AI vendors and refreshed contractual clauses | E20: Sarah Mitchell | F20: FY 2027/28 | G20: RDM-005 | H20: PIL-04
B21: SO-05 | C21: Modernise SOC and SIEM with AI-aware detections | D21: Splunk retired; Sentinel plus Copilot for Security covering Azure subs | E21: Karen Holloway | F21: FY 2026/27 | G21: RDM-010 | H21: PIL-04
B22: SO-06 | C22: Lift AI awareness and competence across the workforce | D22: 95 percent completion across colleagues with AI access | E22: Daniel O'Reilly | F22: FY 2026/27 | G22: RDM-009 | H22: PIL-01
B23: SO-07 | C23: Quantify and refresh AI risk exposure with scenario depth | D23: Quarterly residual risk update with quantified ranges informing risk appetite | E23: Geoffrey Sanders | F23: FY 2027/28 | G23: RDM-012 | H23: PIL-03
B25: 2. Design Principles
B26: Principle ID | C26: Principle | D26: Description | E26: Implication for Operating Model | F26: Linked Controls | G26: Linked Policies | H26: Owner
B27: DP-01 | C27: Risk-based and proportionate | D27: Effort and oversight scale with materiality and customer impact | E27: Tiering of use cases drives forum routing and assurance depth | F27: CTL-001, CTL-014 | G27: POL-001, POL-002 | H27: AI Security Manager
B28: DP-02 | C28: Human-in-the-Loop by default | D28: Material decisions retain human accountability | E28: HITL is a control before approval; documented exceptions only | F28: CTL-008 | G28: POL-002 | H28: AI Security Manager
B29: DP-03 | C29: Privacy by Design and data minimisation | D29: Limit personal and restricted data exposure to AI; embedded at design | E29: Purpose limitation, sensitivity labelling and DPIA gate AI deployment | F29: CTL-006, CTL-013 | G29: POL-008 | H29: DPO
B30: DP-04 | C30: Secure by Design | D30: Threat modelling and architecture review at intake | E30: Architecture review embedded in SVC-001 intake | F30: CTL-001, CTL-013 | G30: POL-005 | H30: CISO
B31: DP-05 | C31: Continuous monitoring | D31: Drift, performance and bias monitoring across deployed AI | E31: Monitoring is a service (SVC-010) with cross-model coverage | F31: CTL-005 | G31: POL-004 | H31: Mohammed Iqbal
B32: DP-06 | C32: Three Lines of Defence | D32: Clear separation between operate, oversee and assure | E32: Owner / AISec / IA model with defined RACI | F32: All controls | G32: POL-002, POL-007 | H32: CRO
B33: DP-07 | C33: Vendor accountability | D33: Third-party AI providers held to same controls as internal AI | E33: DD, ongoing monitoring, exit and substitutability evidenced | F33: CTL-009, CTL-011 | G33: POL-009 | H33: Sarah Mitchell
B34: DP-08 | C34: Evidence-driven assurance and Transparency | D34: Audit-ready evidence library; explainability for stakeholders and auditors | E34: GRC tooling underpins control testing; XAI for material models | F34: All controls | G34: POL-007 | H34: AI Security Manager
B36: 3. Capability Layer Model
B37: Layer | C37: Capability ID | D37: Capability Area | E37: Service Domain | F37: Owning Function | G37: Linked Services | H37: Linked Maturity Domain
B38: Strategy and Policy | C38: CAP-01 | D38: AI Governance and Policy | E38: Governance | F38: AI Governance Office | G38: SVC-001 | H38: MAT-01
B39: Governance and Risk | C39: CAP-02 | D39: AI Risk Management | E39: Risk | F39: Risk Function | G39: SVC-002, SVC-004, SVC-010 | H39: MAT-02
B40: Governance and Risk | C40: CAP-06 | D40: Third-Party Oversight | E40: Third-Party | F40: Procurement and TPRM | G40: SVC-015 | H40: MAT-06
B41: Governance and Risk | C41: CAP-07 | D41: AI Lifecycle Management | E41: Operations | F41: AI Governance Office | G41: SVC-001, SVC-002, SVC-003 | H41: MAT-07
B42: Engineering and Privacy | C42: CAP-03 | D42: AI Security Engineering | E42: Security Engineering | F42: CISO | G42: SVC-014 | H42: MAT-03
B43: Engineering and Privacy | C43: CAP-04 | D43: Privacy and Data Handling | E43: Compliance | F43: DPO | G43: SVC-009 | H43: MAT-04
B44: Operations and Assurance | C44: CAP-05 | D44: Monitoring and Assurance | E44: Monitoring | F44: Data and Analytics | G44: SVC-010 | H44: MAT-05
B45: Operations and Assurance | C45: CAP-08 | D45: Operational Resilience | E45: Incident Response | F45: COO | G45: SVC-014 | H45: MAT-08
B46: Operations and Assurance | C46: CAP-09 | D46: Evidence and Documentation | E46: Assurance | F46: AI Security Manager | G46: SVC-002, SVC-006, SVC-015 | H46: MAT-09
B48: 4. AI Lifecycle Oversight Model (5 Stages)
B49: Stage | C49: Stage Description | D49: Key Activities | E49: Gating Decision and Owner | F49: Linked Controls | G49: Linked Service | H49: Linked Forum
B50: 1. Discovery | C50: Use case identification, materiality screen and data feasibility | D50: Intake form, problem statement, data classification, customer impact flag | E50: Triage decision - Daniel O'Reilly | F50: CTL-001 | G50: SVC-001 | H50: AI Governance Forum
B51: 2. Assessment | C51: Risk, privacy, fairness, security and impact assessment | D51: DPIA, security review, fairness review, model risk classification | E51: Use case approval - AI Governance Forum | F51: CTL-001, CTL-003, CTL-008, CTL-014 | G51: SVC-002, SVC-004 | H51: AIGF and Model Risk Committee
B52: 3. Development | C52: Secure build, data minimisation, fairness testing, validation | D52: Secure coding, sandboxing, sensitivity labelling, validation packs | E52: Pre-deployment sign-off - Mohammed Iqbal and Karen Holloway | F52: CTL-005, CTL-006, CTL-012 | G52: SVC-002, SVC-006 | H52: Model Risk Committee
B53: 4. Deployment | C53: Controlled deployment with guardrails, change control and rollback | D53: Output filters, change windows, HITL gates, change records | E53: Go-live decision - Service Owner | F53: CTL-007, CTL-008, CTL-010 | G53: SVC-003, SVC-005 | H53: AI Governance Forum
B54: 5. Monitoring | C54: Continuous performance, drift, bias, prompt and incident monitoring | D54: Drift alerts, sample QA, complaints linkage, periodic review | E54: Quarterly review - Mohammed Iqbal | F54: CTL-005, CTL-008, CTL-013, CTL-014 | G54: SVC-010 | H54: MRC and AIGF
B56: 5. Metrics Framework (KRI / KPI / KCI)
B57: Metric Type | C57: Definition | D57: Example | E57: Sheet | F57: Cadence | G57: Threshold Logic | H57: Primary Forum
B58: KRI - Key Risk Indicator | C58: Forward-looking indicator that a risk threshold may be breached | D58: KRI-001 Models with material drift; KRI-007 DLP exceptions on GenAI | E58: KRI Tracking | F58: Monthly | G58: Threshold Amber/Red with trend; escalation flag formula | H58: AIGF and Risk Committee
B59: KPI - Key Performance Indicator | C59: Backward-looking indicator of operational performance vs target | D59: KPI-002 Material models with current assurance; KPI-007 Tier-1 vendor DD currency | E59: KPI Tracking | F59: Monthly | G59: Actual vs Target via IF formula | H59: AI Governance Forum
B60: KCI - Key Control Indicator | C60: Indicator of control operating effectiveness over a period | D60: KCI-01 percent of material models passing fairness test; KCI-02 percent of customer-facing AI with output filter regression test pass | E60: KPI Tracking (KCI block) and Compliance Mapping | F60: Quarterly | G60: Pass percentage vs target with trend | H60: Model Risk Committee
B61: Maturity Score | C61: Composite maturity score 1-5 across 9 domains vs target 4.22 | D61: MAT-01 to MAT-09 current vs target with gap | E61: Maturity Assessment | F61: Half-yearly | G61: Average current divided by target | H61: AI Governance Forum
B62: Audit Readiness | C62: Readiness against ISO IEC 42001 clauses and Annex A controls | D62: Readiness score 0-3 across 38 items | E62: ISO 42001 Audit Readiness Matrix | F62: Quarterly | G62: Score 3 = Audit Ready; 2 = minor gaps; 1 = partial; 0 = not ready | H62: AIGF and Audit Committee
B64: 6. Supporting Technology Architecture
B65: Architecture Layer | C65: Capability | D65: Tooling | E65: Purpose | F65: Linked Use Cases | G65: Owner | H65: Linked Capability
B66: Secure Sandboxes | C66: Isolated experimentation environment | D66: Databricks workspaces, Azure Sandbox subscriptions | E66: Allow data scientists to experiment on synthetic or controlled data | F66: AUC-009 and dev environments | G66: Karen Holloway | H66: CAP-03
B67: AI Gateway and Output Filters | C67: Policy enforcement and guardrails on AI outputs | D67: Azure OpenAI content filters, internal hallucination filter, prompt logging | E67: Enforce output guardrails (PII redaction, hallucination, toxic content) on customer-facing AI | F67: AUC-004, AUC-008, AUC-013, AUC-017 | G67: Olivia Bennett | H67: CAP-03
B68: Model and Drift Scanners | C68: Continuous model and data drift scanning | D68: Databricks model registry, MLOps drift monitor | E68: Detect drift, performance degradation and bias on deployed models | F68: AUC-001, AUC-002, AUC-009, AUC-010, AUC-019 | G68: Mohammed Iqbal | H68: CAP-05
B69: Adversarial Testing and Red Teaming | C69: Structured adversarial testing of AI systems | D69: Internal red-team harness, hallucination regression battery, prompt-injection test set | E69: Test customer-facing GenAI for prompt injection, hallucination, leakage | F69: AUC-004, AUC-008, AUC-013, AUC-017 | G69: Karen Holloway and Olivia Bennett | H69: CAP-03
B70: Privacy Enhancing Technologies | C70: Data minimisation and privacy at the inference layer | D70: Microsoft Purview sensitivity labels, DLP, redaction | E70: Prevent restricted or personal data leaving the perimeter via GenAI | F70: AUC-006, AUC-007, AUC-008 | G70: Karen Holloway and DPO | H70: CAP-04
B71: XAI and Explainability | C71: Explainability and traceability of AI outputs | D71: Internal model explainability dashboards, audit logs | E71: Provide auditor and stakeholder access to model rationale; supports A.6.2.9 logging | F71: AUC-001, AUC-003, AUC-010, AUC-014, AUC-019 | G71: Mohammed Iqbal | H71: CAP-05
B72: SIEM and SOC | C72: Security monitoring and SOC analytics for AI workloads | D72: Microsoft Sentinel plus Copilot for Security; Splunk transitional | E72: AI-aware threat detection and SOC playbooks | F72: AUC-009, AUC-017, AUC-021 | G72: Karen Holloway | H72: CAP-03
B73: GRC and Evidence | C73: Centralised evidence library and DPIA tooling | D73: OneTrust GRC plus DPIA plus Evidence Register | E73: Audit-ready evidence pack and DPIA workflow | F73: Cross-cutting | G73: Sarah Mitchell | H73: CAP-09
B75: 7. Talent and Capability Model
B76: Role Type | C76: Linked RES ID | D76: Specialist Skill | E76: Capability Coverage | F76: Sourcing Model | G76: Critical Skills Gap | H76: Owner
B77: AI Security Architect | C77: RES-001, RES-003 | D77: Cloud security, MLOps security, prompt injection defence | E77: PIL-02, PIL-04 | F77: Internal FTE | G77: Prompt-injection detection content authoring | H77: Karen Holloway
B78: Data Privacy Engineer | C78: RES-006 | D78: DPIA, GDPR/UK DPA, ISO 27701, sensitivity labelling | E78: PIL-02 | F78: Internal FTE | G78: Stable | H78: DPO
B79: ML Risk Analyst | C79: RES-002 | D79: Risk quantification, model risk, fairness review, regulatory mapping | E79: PIL-03 | F79: Internal FTE | G79: NIST AI RMF practitioner, UK Consumer Duty practical experience | H79: Geoffrey Sanders
B80: AI Ethics and Compliance Specialist | C80: RES-007, RES-008 | D80: Compliance mapping, fairness testing, hallucination QA | E80: PIL-03, PIL-01 | F80: Internal FTE | G80: Bias and fairness testing depth | H80: Helen Carter, Olivia Bennett
B82: 8. Ownership Model - Three Lines of Defence
B83: Line | C83: Function | D83: Role in AI Estate | E83: Key Activities | F83: Forums | G83: Reports To | H83: Owner
B84: 1st Line | C84: Business / Tech / AI Operations | D84: Build, run and operate AI use cases | E84: Use case ownership, model build, monitoring response, evidence generation | F84: AI Governance Forum | G84: ExCo | H84: Business owners
B85: 2nd Line | C85: AI Security and Risk | D85: Independent oversight, policy and challenge | E85: Policy, risk, control design, assurance reporting | F85: AIGF, MRC, TRC, Risk Committee | G85: CRO | H85: AI Security Manager
B86: 3rd Line | C86: Internal Audit | D86: Independent assurance | E86: Audit plan, walkthroughs, control testing, findings | F86: Audit Committee | G86: Audit Committee | H86: CAE

Sheet TOM Index
A1: TOM Index - Workbook Navigation and Cross-Reference
A2: Index of capabilities, processes, owners and linked controls/metrics with hyperlinks to every sheet in the workbook. Use this sheet as the central navigation hub.
A3: Back to Dashboard | B3: Open ID Glossary
A4: Workbook Section | B4: Sheet | C4: Capability/Purpose | D4: Owner | E4: Linked Control Family | F4: Key KPI/KRI | G4: Open Sheet
A5: Executive Overview | B5: Dashboard | C5: Formula-driven executive view of posture across governance, risk, security, services, incidents and roadmap | D5: AI Security Manager | E5: All | F5: KPI/KRI rollups | G5: Open Dashboard
A6: Executive Overview | B6: Executive Report | C6: Narrative view of strategic posture, material risks, priorities and leadership decisions | D6: AI Security Manager | E6: All | F6: Maturity score | G6: Open
A7: Strategy and Vision | B7: TOM and Strategy | C7: Target operating model strategic objectives design principles capabilities and ownership model | D7: AI Security Manager | E7: All | F7: Maturity targets | G7: Open
A8: Strategy and Vision | B8: TOM Index | C8: This sheet - workbook navigation and cross-reference index | D8: AI Security Manager | E8: All | F8: Coverage | G8: Open
A9: AI Estate | B9: AI Use Case Register | C9: Anchor sheet - inventory of 22 AI use cases linked to risks, controls, services, vendors, KPIs, KRIs, incidents and roadmap | D9: AI Governance Office | E9: CTL-001,CTL-014 | F9: KPI-001 | G9: Open
A10: Governance | B10: Governance Framework | C10: 9 oversight committees with mandates cadence and reporting | D10: Company Secretariat / Risk | E10: All | F10: N/A | G10: Open
A11: Governance | B11: RACI Matrix | C11: 18 lifecycle activities mapped against 9 organisational roles | D11: AI Security Manager | E11: All | F11: N/A | G11: Open
A12: Service Delivery | B12: Service Catalog Master | C12: 15 AI security and governance services | D12: AI Security Manager | E12: CTL-001..CTL-016 | F12: KPI-001..KPI-011 | G12: Open
A13: Service Delivery | B13: SLA-SLO Definitions | C13: Response, resolution and quality targets across services | D13: AI Security Manager | E13: All | F13: KPI-001,KPI-003,KPI-009 | G13: Open
A14: Service Delivery | B14: Service Request Log | C14: 24 historic and in-flight requests with ageing and SLA-met formulas | D14: AI Security Manager | E14: All | F14: KPI-001 | G14: Open
A15: Risk Management | B15: KRI Tracking | C15: 9 KRIs with breach formulas and trends | D15: AI Security Manager | E15: CTL-005,CTL-013,CTL-014 | F15: KRI-001..KRI-009 | G15: Open
... A31: Reference Data | B31: Reference Data | C31: Centralised dropdown lists and validation vocabulary | D31: AI Governance Office | E31: N/A | F31: N/A | G31: Open

Sheet AI Use Case Register
A1: AI Use Case Register - Core Inventory of AI Capabilities
A2: Anchor sheet of the workbook. Each use case links to services, vendors, risks, controls, KPIs, KRIs, incidents, roadmap items and evidence. Owner AI Governance Office. Cadence quarterly review.
A3: Back to Dashboard | B3: Open ID Glossary
A4: Use Case ID | B4: Use Case Name | C4: Business Unit | D4: Description | E4: Objective | F4: AI Type | G4: Model Service Type | H4: Deployment | I4: Vendor ID | J4: Service ID | K4: Business Owner | L4: Technical Owner | M4: Risk Owner | N4: Data Classification | O4: Personal Data | P4: Customer Impact | Q4: Criticality Tier | R4: Approval Status | S4: Assurance Status | T4: Linked Risk IDs | U4: Linked Control IDs | V4: Linked KPI IDs | W4: Linked KRI IDs | X4: Linked Incident IDs | Y4: Linked Roadmap IDs | Z4: Governance Forum | AA4: Evidence Ref | AB4: Last Review | AC4: Next Review | AD4: Notes | AE4: Review Currency
A5: AUC-001 | B5: Underwriting Decision Support - Commercial Property | C5: Underwriting | D5: GBM model assists underwriters with risk scoring on commercial property submissions; advisory only, underwriter retains decision. | E5: Improve technical pricing accuracy and reduce time-to-quote | F5: Traditional ML | G5: Internal model on Databricks | H5: IaaS | J5: SVC-002 | K5: Sarah Mitchell | L5: Daniel O'Reilly | M5: Priya Shah | N5: Confidential | O5: No | P5: Yes | Q5: Tier 1 | R5: Approved | S5: Complete | T5: RSK-001,RSK-004 | U5: CTL-001,CTL-005,CTL-012 | V5: KPI-002,KPI-007 | W5: KRI-001,KRI-003 | X5: INC-002 | Y5: RDM-003,RDM-007 | Z5: AI Governance Forum | AA5: EVD-001 | AB5: 12/03/2026 | AC5: 12/06/2026 | AD5: Reviewed Q1 2026; minor drift remediation underway | AE5: =IF(AC5<TODAY(),"Overdue",IF(AC5<TODAY()+30,"Due Soon","Current")) -> Current
A6: AUC-002 | B6: Claims Triage - Motor FNOL | C6: Claims | D6: Classifies inbound FNOL into fast-track, complex and fraud-suspect channels; SLA-driven routing with human override. | E6: Cut average triage time and route complex claims earlier | F6: Traditional ML | G6: Internal | H6: IaaS | J6: SVC-003 | K6: James Whitfield | L6: Daniel O'Reilly | M6: Priya Shah | N6: Confidential | O6: Yes | P6: Yes | Q6: Tier 1 | R6: Approved | S6: Complete | T6: RSK-002,RSK-007 | U6: CTL-002,CTL-005,CTL-008 | V6: KPI-003,KPI-009 | W6: KRI-002,KRI-005 | X6: INC-001,INC-005 | Y6: RDM-004 | Z6: Model Risk Committee | AA6: EVD-002 | AB6: 22/02/2026 | AC6: 22/05/2026 | AD6: Champion-challenger active | AE6: =IF(AC6<TODAY(),"Overdue",IF(AC6<TODAY()+30,"Due Soon","Current")) -> Current
A7: AUC-003 | B7: Fraud Detection - Motor Claims | C7: Claims | D7: Anomaly detection scoring claims for organised and opportunistic fraud likelihood; outputs feed SIU queue. | E7: Increase recovery and reduce leakage | F7: Anomaly Detection | G7: Internal plus 3rd-party signals | H7: Hybrid | I7: VEN-002 | J7: SVC-004 | K7: Helen Carter | L7: Mohammed Iqbal | M7: Priya Shah | N7: Restricted | O7: Yes | P7: Yes | Q7: Tier 1 | R7: Approved | S7: Complete | T7: RSK-003,RSK-007,RSK-011 | U7: CTL-002,CTL-008,CTL-014 | V7: KPI-004 | W7: KRI-006 | Y7: RDM-005 | Z7: Model Risk Committee | AA7: EVD-003 | AB7: 05/01/2026 | AC7: 05/04/2026 | AD7: False-positive review scheduled | AE7: =IF(AC7<TODAY(),"Overdue",IF(AC7<TODAY()+30,"Due Soon","Current")) -> Current
A8: AUC-004 | B8: Customer Service Copilot - Voice Agent Assist | C8: Customer Operations | D8: LLM assistant providing real-time suggested responses to contact-centre agents on policy and claims queries; agent always confirms before relaying. | E8: Reduce AHT and improve first-contact resolution | F8: Generative AI (LLM) | G8: Vendor LLM (Azure OpenAI) | H8: SaaS | I8: VEN-001 | J8: SVC-005 | K8: Olivia Bennett | L8: Daniel O'Reilly | M8: Priya Shah | N8: Confidential | O8: Yes | P8: Yes | Q8: Tier 1 | R8: Approved | S8: In Progress | T8: RSK-005,RSK-008,RSK-012 | U8: CTL-003,CTL-006,CTL-010,CTL-015 | V8: KPI-005,KPI-010 | W8: KRI-004,KRI-007 | X8: INC-003,INC-008 | Y8: RDM-001,RDM-002 | Z8: AI Governance Forum | AA8: EVD-004 | AB8: 18/03/2026 | AC8: 18/06/2026 | AD8: DPIA approved; output filtering active | AE8: =IF(AC8<TODAY(),"Overdue",IF(AC8<TODAY()+30,"Due Soon","Current")) -> Current
A9: AUC-005 | B9: Document Intelligence - Claims Evidence Extraction | C9: Claims | D9: OCR plus NLP extracts data from claims documents (invoices, medical reports) and pre-populates claim system fields. | E9: Reduce manual keying and cycle time | F9: NLP | G9: Vendor plus Internal | H9: Hybrid | I9: VEN-003 | J9: SVC-006 | K9: James Whitfield | L9: Mohammed Iqbal | M9: Priya Shah | N9: Confidential | O9: Yes | P9: No | Q9: Tier 2 | R9: Approved | S9: Complete | T9: RSK-006,RSK-009 | U9: CTL-004,CTL-007 | V9: KPI-008 | W9: KRI-008 | X9: INC-006 | Y9: RDM-006 | Z9: AI Governance Forum | AA9: EVD-005 | AB9: 28/01/2026 | AC9: 28/04/2026 | AD9: Drift monitoring weekly | AE9: =IF(AC9<TODAY(),"Overdue",IF(AC9<TODAY()+30,"Due Soon","Current")) -> Current
A10: AUC-006 | B10: Internal GenAI Productivity Assistant - M365 Copilot | C10: IT and Cloud | D10: Microsoft 365 Copilot deployed to ~600 colleagues; restricted by sensitivity labels and Purview DLP. | E10: Improve colleague productivity | F10: Generative AI (LLM) | G10: Vendor LLM | H10: SaaS | I10: VEN-001 | J10: SVC-007 | K10: Karen Holloway | L10: Daniel O'Reilly | M10: Priya Shah | N10: Internal | O10: Yes | P10: No | Q10: Tier 2 | R10: Approved | S10: In Progress | T10: RSK-005,RSK-008,RSK-010 | U10: CTL-006,CTL-010,CTL-013,CTL-016 | V10: KPI-011 | W10: KRI-007,KRI-009 | X10: INC-004 | Y10: RDM-002 | Z10: AI Governance Forum | AA10: EVD-006 | AB10: 14/04/2026 | AC10: 14/07/2026 | AD10: Sensitivity-label enforcement reviewed Apr-26 | AE10: =IF(AC10<TODAY(),"Overdue",IF(AC10<TODAY()+30,"Due Soon","Current")) -> Current
A11: AUC-007 | B11: MI / Reporting Assistant - Finance | C11: Finance | D11: Internal text-to-SQL assistant on a curated finance semantic layer; outputs reviewed before circulation. | E11: Faster MI cycle and free analyst time | F11: Generative AI (LLM) | G11: Internal plus vendor | H11: Hybrid | I11: VEN-001 | J11: SVC-008 | K11: Andrew Pollard | L11: Mohammed Iqbal | M11: Priya Shah | N11: Confidential | O11: No | P11: No | Q11: Tier 2 | R11: Conditionally Approved | S11: In Progress | T11: RSK-008,RSK-013 | U11: CTL-006,CTL-013 | V11: KPI-011 | W11: KRI-009 | Y11: RDM-008 | Z11: AI Governance Forum | AA11: EVD-007 | AB11: 01/03/2026 | AC11: 01/06/2026 | AD11: Conditional on enhanced output validation | AE11: =IF(AC11<TODAY(),"Overdue",IF(AC11<TODAY()+30,"Due Soon","Current")) -> Current
A12: AUC-008 | B12: Knowledge Retrieval Assistant - Compliance | C12: Legal and Compliance | D12: RAG assistant indexed over policy library and FCA Handbook; restricted to Compliance Advisory team. | E12: Faster policy lookup and consistency | F12: Generative AI (LLM) | G12: Internal RAG | H12: SaaS | I12: VEN-001 | J12: SVC-009 | K12: Rebecca Lloyd | L12: Mohammed Iqbal | M12: Priya Shah | N12: Internal | O12: No | P12: No | Q12: Tier 3 | R12: Approved | S12: Complete | T12: RSK-008 | U12: CTL-006,CTL-013,CTL-016 | V12: KPI-011 | W12: KRI-009 | Y12: RDM-009 | Z12: AI Governance Forum | AA12: EVD-008 | AB12: 11/02/2026 | AC12: 11/08/2026 | AD12: Audit log review monthly | AE12: =IF(AC12<TODAY(),"Overdue",IF(AC12<TODAY()+30,"Due Soon","Current")) -> Current
A13: AUC-009 | B13: Model Monitoring and Drift Detection Service | C13: Data and Analytics | D13: Internal MLOps service providing drift, performance and bias monitoring; raises alerts via SIEM. | E13: Continuous assurance over deployed AI | F13: Traditional ML | G13: Internal MLOps | H13: IaaS | J13: SVC-010 | K13: Mohammed Iqbal | L13: Mohammed Iqbal | M13: Priya Shah | N13: Internal | O13: No | P13: No | Q13: Tier 1 | R13: Approved | S13: Complete | T13: RSK-001,RSK-002,RSK-006 | U13: CTL-005,CTL-008,CTL-014 | V13: KPI-002,KPI-003,KPI-004 | W13: KRI-001,KRI-002,KRI-008 | X13: INC-001 | Y13: RDM-007 | Z13: Model Risk Committee | AA13: EVD-009 | AB13: 30/03/2026 | AC13: 30/06/2026 | AD13: Coverage 92 percent of in-scope models | AE13: =IF(AC13<TODAY(),"Overdue",IF(AC13<TODAY()+30,"Due Soon","Current")) -> Current
A14: AUC-010 | B14: Pricing Optimisation - Personal Lines Motor | C14: Actuarial | D14: GLM/GBM hybrid pricing engine; subject to actuarial sign-off and pricing fairness review. | E14: Maintain combined ratio and competitive position | F14: Traditional ML | G14: Internal | H14: IaaS | J14: SVC-002 | K14: Helen Carter | L14: Mohammed Iqbal | M14: Priya Shah | N14: Confidential | O14: Yes | P14: Yes | Q14: Tier 1 | R14: Approved | S14: Complete | T14: RSK-001,RSK-004,RSK-011 | U14: CTL-001,CTL-005,CTL-012,CTL-014 | V14: KPI-002 | W14: KRI-001,KRI-003 | X14: INC-002 | Y14: RDM-003 | Z14: Model Risk Committee | AA14: EVD-010 | AB14: 09/03/2026 | AC14: 09/06/2026 | AD14: Pricing fairness review Mar-26 | AE14: =IF(AC14<TODAY(),"Overdue",IF(AC14<TODAY()+30,"Due Soon","Current")) -> Current
A15: AUC-011 | B15: Vulnerable Customer Detection - Service Calls | C15: Customer Operations | D15: NLP flags vulnerability indicators in contact-centre transcripts; routed to specialist team for human handling. | E15: Improve outcomes for vulnerable customers (Consumer Duty) | F15: NLP | G15: Vendor plus Internal | H15: Hybrid | I15: VEN-004 | J15: SVC-005 | K15: Olivia Bennett | L15: Mohammed Iqbal | M15: Priya Shah | N15: Restricted | O15: Yes | P15: Yes | Q15: Tier 1 | R15: Approved | S15: Complete | T15: RSK-005,RSK-007,RSK-012 | U15: CTL-003,CTL-008,CTL-015 | V15: KPI-005,KPI-010 | W15: KRI-004,KRI-005 | Y15: RDM-004 | Z15: AI Governance Forum | AA15: EVD-011 | AB15: 24/02/2026 | AC15: 24/05/2026 | AD15: Consumer Duty quarterly review | AE15: =IF(AC15<TODAY(),"Overdue",IF(AC15<TODAY()+30,"Due Soon","Current")) -> Current
A16: AUC-012 | B16: Email Triage - Broker Operations | C16: Distribution | D16: Classifies inbound broker emails (quote, endorsement, claim, admin) and auto-routes. | E16: Reduce broker turnaround | F16: NLP | G16: Internal | H16: IaaS | J16: SVC-011 | K16: Christopher Doyle | L16: Mohammed Iqbal | M16: Priya Shah | N16: Internal | O16: No | P16: No | Q16: Tier 3 | R16: Approved | S16: Complete | T16: RSK-006 | U16: CTL-004,CTL-007 | V16: KPI-008 | W16: KRI-008 | Y16: RDM-006 | Z16: AI Governance Forum | AA16: EVD-012 | AB16: 19/01/2026 | AC16: 19/07/2026 | AD16: Stable since Q4 2025 | AE16: =IF(AC16<TODAY(),"Overdue",IF(AC16<TODAY()+30,"Due Soon","Current")) -> Current
A17: AUC-013 | B17: Smart Search - Policy Wordings (Customer Portal) | C17: Customer Operations | D17: Vector search over policy-wording PDFs surfaced via portal; constrained to policy-document corpus only. | E17: Reduce 'unable to find policy info' contacts | F17: Generative AI (LLM) | G17: Vendor LLM | H17: SaaS | I17: VEN-001 | J17: SVC-009 | K17: Olivia Bennett | L17: Daniel O'Reilly | M17: Priya Shah | N17: Public | O17: No | P17: Yes | Q17: Tier 2 | R17: Approved | S17: In Progress | T17: RSK-005,RSK-008 | U17: CTL-006,CTL-010,CTL-013 | V17: KPI-010 | W17: KRI-007 | X17: INC-008 | Y17: RDM-001 | Z17: AI Governance Forum | AA17: EVD-013 | AB17: 03/04/2026 | AC17: 03/07/2026 | AD17: Hallucination filter tuned Apr-26 | AE17: =IF(AC17<TODAY(),"Overdue",IF(AC17<TODAY()+30,"Due Soon","Current")) -> Current
A18: AUC-014 | B18: Sanctions and PEP Screening - Augmented Match | C18: Legal and Compliance | D18: ML overlay on sanctions screening reduces false positives; final decision by Compliance Officer. | E18: Reduce false-positive rate while maintaining regulatory robustness | F18: Traditional ML | G18: Vendor | H18: SaaS | I18: VEN-005 | J18: SVC-012 | K18: Rebecca Lloyd | L18: Mohammed Iqbal | M18: Priya Shah | N18: Restricted | O18: Yes | P18: No | Q18: Tier 1 | R18: Approved | S18: Complete | T18: RSK-003,RSK-011,RSK-013 | U18: CTL-002,CTL-008,CTL-014 | V18: KPI-004 | W18: KRI-006 | Y18: RDM-005 | Z18: Model Risk Committee | AA18: EVD-014 | AB18: 26/02/2026 | AC18: 26/05/2026 | AD18: Annual independent validation Jul-26 | AE18: =IF(AC18<TODAY(),"Overdue",IF(AC18<TODAY()+30,"Due Soon","Current")) -> Current
A19: AUC-015 | B19: Customer Churn Propensity - Renewal Retention | C19: Distribution | D19: Scores renewal book for likely churn; informs marketing offers within fairness guardrails. | E19: Lift renewal retention 1-2 pts | F19: Traditional ML | G19: Internal | H19: IaaS | J19: SVC-013 | K19: Christopher Doyle | L19: Mohammed Iqbal | M19: Priya Shah | N19: Confidential | O19: Yes | P19: No | Q19: Tier 2 | R19: Approved | S19: Complete | T19: RSK-004,RSK-011 | U19: CTL-001,CTL-005 | V19: KPI-002 | W19: KRI-003 | Y19: RDM-003 | Z19: Model Risk Committee | AA19: EVD-015 | AB19: 16/03/2026 | AC19: 16/06/2026 | AD19: Bias review Q2 2026 | AE19: =IF(AC19<TODAY(),"Overdue",IF(AC19<TODAY()+30,"Due Soon","Current")) -> Current
A20: AUC-016 | B20: HR CV Screening Pilot | C20: HR | D20: Pilot LLM-assisted CV summarisation only; humans make all selection decisions; no candidate scoring. | E20: Improve recruiter productivity | F20: Generative AI (LLM) | G20: Vendor LLM | H20: SaaS | I20: VEN-001 | J20: SVC-007 | K20: Naomi Edwards | L20: Daniel O'Reilly | M20: Priya Shah | N20: Confidential | O20: Yes | P20: No | Q20: Tier 2 | R20: Conditionally Approved | S20: In Progress | T20: RSK-005,RSK-011,RSK-012 | U20: CTL-003,CTL-006,CTL-015 | V20: KPI-011 | W20: KRI-007 | Y20: RDM-009 | Z20: AI Governance Forum | AA20: EVD-016 | AB20: 07/04/2026 | AC20: 07/07/2026 | AD20: Quarterly bias review required | AE20: =IF(AC20<TODAY(),"Overdue",IF(AC20<TODAY()+30,"Due Soon","Current")) -> Current
A21: AUC-017 | B21: Cyber Threat Triage - SOC Copilot | C21: IT and Cloud | D21: LLM-assisted triage of SIEM alerts; analysts review and decide on every action. | E21: Reduce mean-time-to-triage | F21: Generative AI (LLM) | G21: Vendor | H21: SaaS | I21: VEN-006 | J21: SVC-014 | K21: Karen Holloway | L21: Mohammed Iqbal | M21: Priya Shah | N21: Restricted | O21: No | P21: No | Q21: Tier 1 | R21: Approved | S21: Complete | T21: RSK-008,RSK-010 | U21: CTL-006,CTL-010,CTL-013 | V21: KPI-006 | W21: KRI-009 | X21: INC-007 | Y21: RDM-010 | Z21: Technology Risk Committee | AA21: EVD-017 | AB21: 02/03/2026 | AC21: 02/06/2026 | AD21: SOC effectiveness reviewed | AE21: =IF(AC21<TODAY(),"Overdue",IF(AC21<TODAY()+30,"Due Soon","Current")) -> Current
A22: AUC-018 | B22: Reserving Analytics Assistant | C22: Actuarial | D22: ML-based reserve indication tool used as directional input; not a chain-ladder replacement. | E22: Faster reserve diagnostics | F22: Traditional ML | G22: Internal | H22: IaaS | J22: SVC-008 | K22: Andrew Pollard | L22: Mohammed Iqbal | M22: Priya Shah | N22: Confidential | O22: No | P22: No | Q22: Tier 2 | R22: Approved | S22: Complete | T22: RSK-001,RSK-004 | U22: CTL-001,CTL-005 | V22: KPI-002 | W22: KRI-001 | Y22: RDM-008 | Z22: Model Risk Committee | AA22: EVD-018 | AB22: 21/03/2026 | AC22: 21/06/2026 | AD22: Independent actuarial sign-off | AE22: =IF(AC22<TODAY(),"Overdue",IF(AC22<TODAY()+30,"Due Soon","Current")) -> Current
A23: AUC-019 | B23: Image-Based Damage Estimation - Motor | C23: Claims | D23: CV estimates motor damage severity from photos; engineer validates before payment. | E23: Reduce engineer dispatch and improve cycle time | F23: Computer Vision | G23: Vendor | H23: SaaS | I23: VEN-007 | J23: SVC-006 | K23: James Whitfield | L23: Mohammed Iqbal | M23: Priya Shah | N23: Confidential | O23: Yes | P23: Yes | Q23: Tier 1 | R23: Approved | S23: Complete | T23: RSK-002,RSK-006,RSK-009 | U23: CTL-002,CTL-004,CTL-008 | V23: KPI-003,KPI-008 | W23: KRI-002,KRI-008 | X23: INC-005 | Y23: RDM-004 | Z23: Model Risk Committee | AA23: EVD-019 | AB23: 10/02/2026 | AC23: 10/05/2026 | AD23: Engineer override rate trended monthly | AE23: =IF(AC23<TODAY(),"Overdue",IF(AC23<TODAY()+30,"Due Soon","Current")) -> Current
A24: AUC-020 | B24: Complaints Categorisation and Root Cause Themes | C24: Legal and Compliance | D24: NLP categorises complaints and clusters root cause themes for Consumer Duty MI. | E24: Quicker theme detection and reporting | F24: NLP | G24: Internal | H24: IaaS | J24: SVC-009 | K24: Rebecca Lloyd | L24: Mohammed Iqbal | M24: Priya Shah | N24: Restricted | O24: Yes | P24: Yes | Q24: Tier 1 | R24: Approved | S24: Complete | T24: RSK-005,RSK-007,RSK-012 | U24: CTL-003,CTL-008,CTL-015 | V24: KPI-005,KPI-010 | W24: KRI-004 | Y24: RDM-001 | Z24: AI Governance Forum | AA24: EVD-020 | AB24: 27/03/2026 | AC24: 27/06/2026 | AD24: Aligned with Consumer Duty MI | AE24: =IF(AC24<TODAY(),"Overdue",IF(AC24<TODAY()+30,"Due Soon","Current")) -> Current
A25: AUC-021 | B25: Cloud Cost Anomaly Detection | C25: IT and Cloud | D25: Detects abnormal cloud spend patterns across Azure subscriptions; alerts FinOps. | E25: Avoid run-rate surprises | F25: Anomaly Detection | G25: Internal | H25: IaaS | J25: SVC-014 | K25: Karen Holloway | L25: Mohammed Iqbal | M25: Priya Shah | N25: Internal | O25: No | P25: No | Q25: Tier 3 | R25: Approved | S25: Complete | T25: RSK-010,RSK-013 | U25: CTL-005,CTL-016 | V25: KPI-006 | W25: KRI-009 | Y25: RDM-010 | Z25: Technology Risk Committee | AA25: EVD-021 | AB25: 08/04/2026 | AC25: 08/10/2026 | AD25: Stable; low alert volume | AE25: =IF(AC25<TODAY(),"Overdue",IF(AC25<TODAY()+30,"Due Soon","Current")) -> Current
A26: AUC-022 | B26: Internal Audit Analytics - Continuous Auditing | C26: Internal Audit | D26: Internal audit analytics over GL, claims and procurement to flag anomalies for follow-up. | E26: Risk-based, evidence-driven audit coverage | F26: Anomaly Detection | G26: Internal | H26: IaaS | J26: SVC-008 | K26: Liam Carmichael | L26: Mohammed Iqbal | M26: Priya Shah | N26: Confidential | O26: No | P26: No | Q26: Tier 2 | R26: Approved | S26: Complete | T26: RSK-013 | U26: CTL-005,CTL-014 | V26: KPI-006 | W26: KRI-008 | Y26: RDM-008 | Z26: Audit Committee | AA26: EVD-022 | AB26: 13/03/2026 | AC26: 13/09/2026 | AD26: Reviewed annually with CAE | AE26: =IF(AC26<TODAY(),"Overdue",IF(AC26<TODAY()+30,"Due Soon","Current")) -> Current

Sheet Governance Framework
A1: Governance Framework - AI Governance Committees and Forums
A2: Decision-making and oversight forums for AI security and governance. Owner Company Secretariat and Risk.
A3: Back to Dashboard | B3: Open ID Glossary
A4: Committee ID | B4: Committee Name | C4: Purpose | D4: Mandate | E4: Chair | F4: Membership | G4: Cadence | H4: Escalation Route | I4: Reporting Outputs | J4: Key Decisions Held | K4: Linked Policies
A5: COM-001 | B5: AI Governance Forum | C5: Operational governance of AI use cases | D5: Approve, conditionally approve or reject AI use cases below ExCo threshold; oversee assurance status; review incidents. | E5: Chief Data Officer (Andrew Pollard) | F5: CISO, CDO, Head of Risk, Head of Compliance, Head of Data Science, AI Security Manager, DPO, business sponsors | G5: Monthly | H5: Risk Committee then ExCo | I5: Monthly forum pack; minutes; decisions log | J5: Use case approvals, conditional approvals, model retirements | K5: POL-001,POL-002,POL-003
A6: COM-002 | B6: Model Risk Committee | C6: Independent challenge of model risk for material AI/ML | D6: Apply MRM standard (POL-004) to validate and monitor material models. | E6: CRO (Geoffrey Sanders) | F6: CRO, CFO, Head of Actuarial, CDO, AI Security Manager, MRM Lead | G6: Monthly | H6: Risk Committee | I6: MRM dashboard; validation reports | J6: Model approvals, validation outcomes, risk acceptances | K6: POL-004,POL-002
A7: COM-003 | B7: Technology Risk Committee | C7: IT, cloud and security risk oversight | D7: Oversee technology risk across estate including AI workloads. | E7: CIO (Stephen Mackenzie) | F7: CIO, CISO, Head of IT, Head of Cloud, AI Security Manager, Risk rep | G7: Monthly | H7: Risk Committee | I7: Tech risk pack; KRI dashboard | J7: Risk acceptances, exceptions, programme decisions | K7: POL-005,POL-006
A8: COM-004 | B8: ExCo | C8: Executive committee | D8: Oversight of strategic risks and material decisions including AI. | E8: CEO (Margaret Whittaker) | F8: CEO, CRO, CFO, CIO, CDO, COO, GC | G8: Weekly | H8: Board | I8: ExCo papers; minutes | J8: Strategic AI investment, escalations | K8: POL-001
A9: COM-005 | B9: Risk Committee (Board) | C9: Board-level risk oversight | D9: Assurance over enterprise risk including AI. | E9: NED Risk Chair (Patricia Donnelly) | F9: NEDs, CEO, CRO | G9: Quarterly | H9: Board | I9: Board risk pack | J9: Risk appetite, material risk decisions | K9: POL-001,POL-002
A10: COM-006 | B10: Audit Committee (Board) | C10: Board-level audit oversight | D10: Internal/external audit oversight including AI assurance. | E10: NED Audit Chair (Robert Henshaw) | F10: NEDs, CFO, CAE | G10: Quarterly | H10: Board | I10: Board audit pack | J10: Audit findings, remediation acceptance | K10: POL-007
A11: COM-007 | B11: Data Protection Forum | C11: Privacy and data protection oversight | D11: Operational forum for privacy obligations across business lines. | E11: DPO (Rebecca Lloyd) | F11: DPO, Privacy Champions, AI Security Manager, IS, Legal | G11: Monthly | H11: Risk Committee | I11: DP forum pack; DPIA log | J11: DPIA outcomes, breach notifications | K11: POL-008,POL-003
A12: COM-008 | B12: Third-Party Oversight Forum | C12: Third-party risk oversight | D12: Onboarding, ongoing oversight and exit planning for material third parties. | E12: Procurement Director (Nigel Ashton) | F12: Procurement, IS, Risk, Legal, AI Security Manager, business owners | G12: Monthly | H12: Risk Committee | I12: TPRM pack; vendor heatmap | J12: Vendor approvals, exits, contractual changes | K12: POL-009
A13: COM-009 | B13: Operational Resilience Committee | C13: Operational resilience and continuity oversight | D13: Important Business Service mapping, severe but plausible scenarios, exercise programme. | E13: COO (Yvonne Mathieson) | F13: COO, CIO, CISO, Head of BCP, Risk, AI Security Manager | G13: Monthly | H13: Risk Committee | I13: OR pack; exercise reports | J13: IBS designations, exercise outcomes | K13: POL-010

Sheet RACI Matrix
A1: RACI Matrix - AI Security and Governance Activities
A2: Activity-level responsibilities across the AI lifecycle. R = Responsible, A = Accountable, C = Consulted, I = Informed. Owner AI Security Manager. Cadence reviewed annually.
A3: Back to Dashboard
A4: Activity ID | B4: Activity | C4: Business Owner | D4: AI Security Manager | E4: CISO | F4: CRO / Risk | G4: DPO / Compliance | H4: Data Science / MLOps | I4: Internal Audit | J4: Procurement / TPRM | K4: Tech / Cloud Ops | L4: Linked Policies
A5: ACT-RACI-01 | B5: AI Use Case Onboarding and Intake Triage | C5: A | D5: R | E5: C | F5: C | G5: C | H5: C | I5: I | J5: I | K5: I | L5: POL-001,POL-003
A6: ACT-RACI-02 | B6: Model and Vendor Due Diligence Review | C6: C | D6: R | E6: C | F6: A | G6: C | H6: C | I6: I | J6: R | K6: I | L6: POL-004,POL-009
A7: ACT-RACI-03 | B7: AI Risk Assessment and Quantification | C7: C | D7: R | E7: C | F7: A | G7: C | H7: C | I7: I | J7: C | K7: I | L7: POL-002
A8: ACT-RACI-04 | B8: DPIA and Privacy Review | C8: C | D8: C | E8: I | F8: I | G8: A,R | H8: C | I8: I | J8: C | K8: I | L8: POL-008,POL-003
A9: ACT-RACI-05 | B9: Security Assessment and Threat Modelling | C9: I | D9: R | E9: A | F9: C | G9: C | H9: C | I9: I | J9: C | K9: C | L9: POL-005,POL-006
A10: ACT-RACI-06 | B10: Use Case Approval Decision (AI Governance Forum) | C10: C | D10: R | E10: C | F10: C | G10: C | H10: C | I10: I | J10: I | K10: I | L10: POL-001
A11: ACT-RACI-07 | B11: Pre-Deployment Review and Sign-off | C11: A | D11: R | E11: C | F11: C | G11: C | H11: R | I11: I | J11: I | K11: C | L11: POL-002,POL-004
A12: ACT-RACI-08 | B12: Production Monitoring (drift, bias, performance) | C12: I | D12: A | E12: I | F12: I | G12: I | H12: R | I12: I | J12: I | K12: C | L12: POL-004,POL-006
A13: ACT-RACI-09 | B13: Incident Detection, Triage and Response | C13: C | D13: A | E13: R | F13: C | G13: C | H13: R | I13: I | J13: C | K13: R | L13: POL-005,POL-006
A14: ACT-RACI-10 | B14: Access Provisioning and Periodic Recertification | C14: A | D14: C | E14: R | F14: I | G14: I | H14: I | I14: I | J14: I | K14: R | L14: POL-005
A15: ACT-RACI-11 | B15: Audit Evidence Collection and Control Testing | C15: I | D15: R | E15: C | F15: C | G15: C | H15: C | I15: A | J15: I | K15: C | L15: POL-007
... A22: ACT-RACI-18 | B22: Use Case Periodic Review (Quarterly) | C22: A | D22: R | E22: I | F22: C | G22: C | H22: C | I22: I | J22: I | K22: I | L22: POL-001,POL-004

Sheet Service Catalog Master
A1: Service Catalog Master - AI Security and Governance Services
A2: Catalogue of services delivered by the AI Security function. Owner AI Security Manager. Cadence half-yearly review.
A3: Back to Dashboard | B3: Open ID Glossary
A4: Service ID | B4: Service Name | C4: Service Category | D4: Description | E4: Intake Route | F4: Service Owner | G4: Customer Group | H4: Linked Use Cases | I4: Linked Controls | J4: Linked KPIs | K4: Service Outputs | L4: Dependency Notes | M4: Assurance Relevance
A5: SVC-001 | B5: AI Use Case Intake and Triage | C5: Governance | D5: Single intake point for new AI use cases; initial materiality, data, regulatory and security screening. | E5: ServiceNow intake form | F5: Daniel O'Reilly | G5: Business sponsors | H5: AUC-001 to AUC-022 (all) | I5: CTL-001,CTL-003 | J5: KPI-001 | K5: Intake decision pack; routing to forums | L5: ServiceNow form; AI inventory | M5: High
A6: SVC-002 | B6: Underwriting and Pricing Model Assurance | C6: Assurance | D6: Independent challenge of pricing and UW models including fairness, performance, governance. | E6: AI Governance Forum | F6: Mohammed Iqbal | G6: Underwriting, Actuarial | H6: AUC-001,AUC-010,AUC-015,AUC-018 | I6: CTL-001,CTL-005,CTL-012,CTL-014 | J6: KPI-002 | K6: Model assurance reports; sign-off papers | L6: MLOps platform; model registry | M6: High
A7: SVC-003 | B7: Claims AI Service Operations | C7: Operations | D7: Operational service for claims-facing AI: monitoring, change, incident, drift response. | E7: AI Governance Forum | F7: Mohammed Iqbal | G7: Claims | H7: AUC-002,AUC-019 | I7: CTL-002,CTL-005,CTL-008 | J7: KPI-003,KPI-009 | K7: Monitoring reports; change records | L7: MLOps; SIEM; ServiceNow | M7: High
A8: SVC-004 | B8: Fraud Analytics Model Oversight | C8: Assurance | D8: Oversight of fraud detection models including fairness, false-positive monitoring, SIU feedback. | E8: Model Risk Committee | F8: Helen Carter | G8: SIU, Claims | H8: AUC-003,AUC-014 | I8: CTL-002,CTL-008,CTL-014 | J8: KPI-004 | K8: Performance and FPR reports; SIU feedback log | L8: Fraud platform; SIU case mgmt | M8: High
A9: SVC-005 | B9: Customer-Facing AI Risk Service | C9: Operations | D9: Operational service for customer-facing AI tools: real-time guardrails, output review, complaint linkage. | E9: AI Governance Forum | F9: Olivia Bennett | G9: Customer Operations | H9: AUC-004,AUC-011 | I9: CTL-003,CTL-006,CTL-008,CTL-010,CTL-015 | J9: KPI-005,KPI-010 | K9: Guardrail logs; sample reviews; complaint links | L9: Vendor LLM; CCaaS; complaints system | M9: High
A10: SVC-006 | B10: Document AI Quality Assurance | C10: Assurance | D10: QA over document AI extractions; sample review and downstream impact monitoring. | E10: ServiceNow | F10: Mohammed Iqbal | G10: Claims, Operations | H10: AUC-005,AUC-019 | I10: CTL-004,CTL-007 | J10: KPI-008 | K10: QA sample report; reject-rate trend | L10: DMS; OCR/NLP platform | M10: Medium
A11: SVC-007 | B11: GenAI Productivity Tooling Service | C11: Operations | D11: Service for internal GenAI productivity tools: licensing, usage controls, sensitivity-label enforcement. | E11: ServiceNow | F11: Karen Holloway | G11: All staff | H11: AUC-006,AUC-016 | I11: CTL-006,CTL-010,CTL-013,CTL-016 | J11: KPI-011 | K11: Usage MI; DLP exception log | L11: Microsoft Purview; M365 | M11: Medium
A12: SVC-008 | B12: Internal Analytics and MI Assistant Service | C12: Operations | D12: Service for internal analytics assistants including MI/reporting and reserving analytics. | E12: ServiceNow | F12: Andrew Pollard | G12: Finance, Actuarial, IA | H12: AUC-007,AUC-018,AUC-022 | I12: CTL-006,CTL-013 | J12: KPI-011 | K12: Curated semantic layer; output validation log | L12: Data platform; semantic layer | M12: Medium
A13: SVC-009 | B13: Compliance and Knowledge Assistant Service | C13: Operations | D13: Service supporting compliance/knowledge assistants and policy-wording search. | E13: ServiceNow | F13: Rebecca Lloyd | G13: Compliance, Customers | H13: AUC-008,AUC-013,AUC-020 | I13: CTL-006,CTL-010,CTL-013,CTL-015,CTL-016 | J13: KPI-005,KPI-010 | K13: RAG corpus controls; output sample reviews | L13: Vector DB; policy library | M13: High
A14: SVC-010 | B14: Model Monitoring and Drift Service | C14: Monitoring | D14: Cross-model monitoring service for drift, performance, bias and incidents. | E14: AI Governance Forum | F14: Mohammed Iqbal | G14: All AI owners | H14: AUC-009 | I14: CTL-005,CTL-008,CTL-014 | J14: KPI-002,KPI-003,KPI-004 | K14: Drift dashboards; alert tickets | L14: MLOps; SIEM | M14: High
A15: SVC-011 | B15: Broker AI Channel Operations | C15: Operations | D15: Operational service for distribution-channel AI. | E15: ServiceNow | F15: Christopher Doyle | G15: Distribution | H15: AUC-012,AUC-015 | I15: CTL-004,CTL-007 | J15: KPI-008 | K15: Routing accuracy MI | L15: Email gateway; CRM | M15: Medium
... A19: SVC-015 | B19: Third-Party AI Assurance Service | C19: Third-Party | D19: Due diligence and ongoing assurance over third-party AI providers. | E19: Procurement intake | F19: Sarah Mitchell | G19: Procurement, Risk | H19: AUC-004,AUC-005,AUC-006,AUC-008,AUC-013,AUC-017,AUC-019 | I19: CTL-009,CTL-011,CTL-014 | J19: KPI-007 | K19: Vendor DD packs; ongoing monitoring | L19: GRC; procurement system | M19: High

Sheet SLA-SLO Definitions
A1: SLA-SLO Definitions - Service Level Agreements and Objectives
A2: Service-level commitments for AI security and governance services. Owner AI Security Manager. Reviewed semi-annually.
A3: Back to Dashboard
A4: Service ID | B4: Service Name | C4: SLA Response Target | D4: SLA Resolution Target | E4: SLO Quality Measure | F4: Measurement Source | G4: Breach Rule | H4: Exclusions | I4: Severity Treatment | J4: Reporting Cadence
A5: SVC-001 | B5: AI Use Case Intake and Triage | C5: Within 2 working days | D5: Decision pack within 10 working days | E5: >=95% of intakes triaged on time | F5: ServiceNow report | G5: Two consecutive months below 90% | H5: Use cases requiring DPIA extension | I5: Sev 1: same day; Sev 2: next working day | J5: Monthly
A6: SVC-002 | B6: Underwriting and Pricing Model Assurance | C6: Within 5 working days | D6: Assurance pack within 20 working days | E6: >=98% pricing models with current assurance | F6: Model registry MI | G6: >2 models without current assurance | H6: Model retirements in flight | I6: Critical: emergency MRC review | J6: Monthly
A7: SVC-003 | B7: Claims AI Service Operations | C7: Within 4 hours (Sev 1) | D7: Within 8 working hours (Sev 1) | E7: >=99.5% in-month uptime; <=2 Sev1 incidents/month | F7: SIEM and ServiceNow | G7: Single Sev 1 outage > 8 hours | H7: Planned maintenance windows | I7: Sev 1: page on-call; Sev 2: ticket within 1h | J7: Weekly
A8: SVC-004 | B8: Fraud Analytics Model Oversight | C8: Within 5 working days | D8: Within 15 working days | E8: False-positive rate within agreed band | F8: Fraud platform MI | G8: FPR > target +20% for 2 months | H8: Threshold change windows | I8: Sev 2 ticket if FPR breached | J8: Monthly
A9: SVC-005 | B9: Customer-Facing AI Risk Service | C9: Within 2 hours (live customer impact) | D9: Within 4 hours (live customer impact) | E9: >=99% guardrail availability | F9: Vendor MI plus internal logs | G9: Single guardrail outage > 1 hour in production | H9: Vendor maintenance windows | I9: Sev 1: page on-call; complaint linkage required | J9: Weekly
A10: SVC-006 | B10: Document AI Quality Assurance | C10: Within 5 working days | D10: Within 15 working days | E10: >=98% QA sample reviews on time | F10: ServiceNow plus QA tracker | G10: Two consecutive months <95% | H10: Vendor outages | I10: Sev 3 ticket if QA backlog > 10 days | J10: Monthly
A11: SVC-007 | B11: GenAI Productivity Tooling Service | C11: Within 1 working day | D11: Within 5 working days | E11: >=95% DLP exception decisions on time | F11: Microsoft Purview MI | G11: Pending exceptions > 7 days | H11: Major vendor incidents | I11: Sev 2: ticket within 4h | J11: Monthly
A12: SVC-008 | B12: Internal Analytics and MI Assistant Service | C12: Within 3 working days | D12: Within 10 working days | E12: >=95% queries with output validation | F12: Internal logs | G12: Output validation rate < 90% for any month | H12: Restricted analyst groups | I12: Sev 3 ticket if validation gap | J12: Monthly
A13: SVC-009 | B13: Compliance and Knowledge Assistant Service | C13: Within 3 working days | D13: Within 10 working days | E13: >=98% sample reviews completed monthly | F13: Internal logs | G13: Sample review backlog > 5 | H13: Audit log gaps notified | I13: Sev 2 ticket if backlog grows | J13: Monthly
A14: SVC-010 | B14: Model Monitoring and Drift Service | C14: Within 1 hour (alert acknowledgement) | D14: Within 8 hours (drift triage) | E14: >=98% in-scope models monitored | F14: MLOps platform | G14: Coverage < 95% in any month | H14: Models in retirement | I14: Sev 1: page MLOps on-call | J14: Weekly
A15: SVC-011 | B15: Broker AI Channel Operations | C15: Within 4 working hours | D15: Within 1 working day | E15: >=98% routing accuracy | F15: CRM and email gateway logs | G15: Routing accuracy < 95% for any week | H15: Vendor outages | I15: Sev 3 ticket if accuracy slips | J15: Weekly
... A19: SVC-015 | B19: Third-Party AI Assurance Service | C19: Within 5 working days | D19: Within 30 working days for full DD pack | E19: >=95% Tier-1 vendors with current DD | F19: GRC tracker | G19: Tier-1 vendor with overdue DD | H19: Cross-cutting/exit-only vendors | I19: Critical: TPRM forum escalation | J19: Monthly

Sheet Service Request Log
A1: Service Request Log - AI Security Service Demand
A2: Historic and in-flight requests against the AI Security service catalog. Owner AI Security Manager. Live ServiceNow extract refreshed weekly.
A3: Back to Dashboard
A4: Request ID | B4: Date Raised | C4: Service ID | D4: Request Category | E4: Requestor BU | F4: Priority | G4: Owner | H4: Status | I4: Target Date | J4: Completion Date | K4: Ageing (days) | L4: SLA Met | M4: Linked Use Case ID | N4: Comments | P4: Service Request Summary
A5: REQ-2026-001 | B5: 46027 | C5: SVC-001 | D5: New Use Case Intake | E5: Customer Operations | F5: High | G5: Daniel O'Reilly | H5: Closed | I5: 46037 | J5: 46036 | K5: =IF(J5="",TODAY()-B5,J5-B5) -> 9 | L5: =IF(J5="","Open",IF(J5<=I5,"Yes","No")) -> Yes | M5: AUC-013 | N5: Smart Search portal go-live decision pack | P5: Total Requests | Q5: =COUNTA(A5:A28) -> 24
A6: REQ-2026-002 | B6: 46029 | C6: SVC-015 | D6: Vendor Assessment | E6: IT and Cloud | F6: High | G6: Sarah Mitchell | H6: Closed | I6: 46059 | J6: 46057 | K6: =IF(J6="",TODAY()-B6,J6-B6) -> 28 | L6: =IF(J6="","Open",IF(J6<=I6,"Yes","No")) -> Yes | M6: AUC-017 | N6: Sentinel Copilot for Security DD | P6: Open | Q6: =COUNTIF(H5:H28,"Open") -> 2
A7: REQ-2026-003 | B7: 46034 | C7: SVC-005 | D7: DPIA | E7: Customer Operations | F7: Critical | G7: Rebecca Lloyd | H7: Closed | I7: 46065 | J7: 46062 | K7: =IF(J7="",TODAY()-B7,J7-B7) -> 28 | L7: =IF(J7="","Open",IF(J7<=I7,"Yes","No")) -> Yes | M7: AUC-004 | N7: DPIA refresh for voice agent assist | P7: In Progress | Q7: =COUNTIF(H5:H28,"In Progress") -> 4
A8: REQ-2026-004 | B8: 46037 | C8: SVC-007 | D8: Policy Exception | E8: Finance | F8: Medium | G8: Karen Holloway | H8: Closed | I8: 46051 | J8: 46049 | K8: =IF(J8="",TODAY()-B8,J8-B8) -> 12 | L8: =IF(J8="","Open",IF(J8<=I8,"Yes","No")) -> Yes | M8: AUC-007 | N8: Temporary DLP exception for Finance pilot | P8: Closed | Q8: =COUNTIF(H5:H28,"Closed") -> 18
A9: REQ-2026-005 | B9: 46042 | C9: SVC-014 | D9: Security Review | E9: IT and Cloud | F9: High | G9: Karen Holloway | H9: Closed | I9: 46056 | J9: 46055 | K9: =IF(J9="",TODAY()-B9,J9-B9) -> 13 | L9: =IF(J9="","Open",IF(J9<=I9,"Yes","No")) -> Yes | M9: AUC-009 | N9: MLOps environment hardening review | P9: SLA Met | Q9: =COUNTIF(L5:L28,"Yes") -> 16
A10: REQ-2026-006 | B10: 46046 | C10: SVC-001 | D10: New Use Case Intake | E10: HR | F10: Medium | G10: Daniel O'Reilly | H10: Closed | I10: 46063 | J10: 46060 | K10: =IF(J10="",TODAY()-B10,J10-B10) -> 14 | L10: =IF(J10="","Open",IF(J10<=I10,"Yes","No")) -> Yes | M10: AUC-016 | N10: HR CV summarisation pilot intake | P10: SLA Missed | Q10: =COUNTIF(L5:L28,"No") -> 2
A11: REQ-2026-007 | B11: 46055 | C11: SVC-010 | D11: Incident Triage | E11: Claims | F11: Critical | G11: Mohammed Iqbal | H11: Closed | I11: 46056 | J11: 46056 | K11: =IF(J11="",TODAY()-B11,J11-B11) -> 1 | L11: =IF(J11="","Open",IF(J11<=I11,"Yes","No")) -> Yes | M11: AUC-002 | N11: FNOL drift alert - INC-001 | P11: Critical/High | Q11: =COUNTIF(F5:F28,"Critical")+COUNTIF(F5:F28,"High") -> 11
A12: REQ-2026-008 | B12: 46059 | C12: SVC-009 | D12: New Use Case Intake | E12: Legal and Compliance | F12: Medium | G12: Daniel O'Reilly | H12: Closed | I12: 46073 | J12: 46071 | K12: =IF(J12="",TODAY()-B12,J12-B12) -> 12 | L12: =IF(J12="","Open",IF(J12<=I12,"Yes","No")) -> Yes | M12: AUC-008 | N12: Compliance RAG knowledge assistant | P12: Avg Ageing (closed) | Q12: =AVERAGEIF(H5:H28,"Closed",K5:K28) -> 13.5
A13: REQ-2026-009 | B13: 46063 | C13: SVC-002 | D13: Audit Evidence | E13: Internal Audit | F13: Medium | G13: Mohammed Iqbal | H13: Closed | I13: 46077 | J13: 46076 | K13: =IF(J13="",TODAY()-B13,J13-B13) -> 13 | L13: =IF(J13="","Open",IF(J13<=I13,"Yes","No")) -> Yes | M13: AUC-001 | N13: UW model assurance pack for IA walkthrough
A14: REQ-2026-010 | B14: 46065 | C14: SVC-005 | D14: Incident Triage | E14: Customer Operations | F14: High | G14: Olivia Bennett | H14: Closed | I14: 46066 | J14: 46066 | K14: =IF(J14="",TODAY()-B14,J14-B14) -> 1 | L14: =IF(J14="","Open",IF(J14<=I14,"Yes","No")) -> Yes | M14: AUC-004 | N14: Voice agent INC-003 follow-up
A15: REQ-2026-011 | B15: 46071 | C15: SVC-015 | D15: Vendor Assessment | E15: Claims | F15: High | G15: Sarah Mitchell | H15: In Progress | I15: 46162 | K15: =IF(J15="",TODAY()-B15,J15-B15) -> 169 | L15: =IF(J15="","Open",IF(J15<=I15,"Yes","No")) -> Open | M15: AUC-005 | N15: ABBYY privacy review refresh - ACT-002
A16: REQ-2026-012 | B16: 46075 | C16: SVC-014 | D16: Access Provisioning | E16: Data and Analytics | F16: Medium | G16: Karen Holloway | H16: Closed | I16: 46089 | J16: 46087 | K16: =IF(J16="",TODAY()-B16,J16-B16) -> 12 | L16: =IF(J16="","Open",IF(J16<=I16,"Yes","No")) -> Yes | M16: AUC-009 | N16: PAM grants for MLOps engineers
A17: REQ-2026-013 | B17: 46080 | C17: SVC-001 | D17: New Use Case Intake | E17: Distribution | F17: Medium | G17: Daniel O'Reilly | H17: Closed | I17: 46094 | J17: 46092 | K17: =IF(J17="",TODAY()-B17,J17-B17) -> 12 | L17: =IF(J17="","Open",IF(J17<=I17,"Yes","No")) -> Yes | M17: AUC-015 | N17: Churn propensity refresh intake
A18: REQ-2026-014 | B18: 46083 | C18: SVC-005 | D18: Training Request | E18: Customer Operations | F18: Low | G18: Olivia Bennett | H18: Closed | I18: 46114 | J18: 46109 | K18: =IF(J18="",TODAY()-B18,J18-B18) -> 26 | L18: =IF(J18="","Open",IF(J18<=I18,"Yes","No")) -> Yes | M18: AUC-004 | N18: Floor walk for new agents on copilot guardrails
A19: REQ-2026-015 | B19: 46090 | C19: SVC-002 | D19: Model Change | E19: Underwriting | F19: High | G19: Mohammed Iqbal | H19: Closed | I19: 46104 | J19: 46105 | K19: =IF(J19="",TODAY()-B19,J19-B19) -> 15 | L19: =IF(J19="","Open",IF(J19<=I19,"Yes","No")) -> No | M19: AUC-001 | N19: GBM challenger swap; SLA missed by 1 day
A20: REQ-2026-016 | B20: 46096 | C20: SVC-010 | D20: Incident Triage | E20: Customer Operations | F20: High | G20: Mohammed Iqbal | H20: Closed | I20: 46097 | J20: 46098 | K20: =IF(J20="",TODAY()-B20,J20-B20) -> 2 | L20: =IF(J20="","Open",IF(J20<=I20,"Yes","No")) -> No | M20: AUC-013 | N20: Hallucination filter alert INC-008
A21: REQ-2026-017 | B21: 46101 | C21: SVC-007 | D21: Policy Exception | E21: HR | F21: Medium | G21: Karen Holloway | H21: In Progress | I21: 46162 | K21: =IF(J21="",TODAY()-B21,J21-B21) -> 139 | L21: =IF(J21="","Open",IF(J21<=I21,"Yes","No")) -> Open | M21: AUC-016 | N21: Awaiting bias review sign-off
A22: REQ-2026-018 | B22: 46108 | C22: SVC-004 | D22: Audit Evidence | E22: Internal Audit | F22: Medium | G22: Helen Carter | H22: Closed | I22: 46122 | J22: 46120 | K22: =IF(J22="",TODAY()-B22,J22-B22) -> 12 | L22: =IF(J22="","Open",IF(J22<=I22,"Yes","No")) -> Yes | M22: AUC-003 | N22: Fraud model walkthrough pack
A23: REQ-2026-019 | B23: 46114 | C23: SVC-008 | D23: New Use Case Intake | E23: Finance | F23: Medium | G23: Daniel O'Reilly | H23: Closed | I23: 46128 | J23: 46127 | K23: =IF(J23="",TODAY()-B23,J23-B23) -> 13 | L23: =IF(J23="","Open",IF(J23<=I23,"Yes","No")) -> Yes | M23: AUC-007 | N23: Conditional approval extended to month-end MI
A24: REQ-2026-020 | B24: 46120 | C24: SVC-014 | D24: Security Review | E24: IT and Cloud | F24: High | G24: Karen Holloway | H24: In Progress | I24: 46151 | K24: =IF(J24="",TODAY()-B24,J24-B24) -> 120 | L24: =IF(J24="","Open",IF(J24<=I24,"Yes","No")) -> Open | M24: AUC-021 | N24: Cloud cost anomaly platform review
A25: REQ-2026-021 | B25: 46124 | C25: SVC-006 | D25: Audit Evidence | E25: Claims | F25: Low | G25: Mohammed Iqbal | H25: Closed | I25: 46145 | J25: 46144 | K25: =IF(J25="",TODAY()-B25,J25-B25) -> 20 | L25: =IF(J25="","Open",IF(J25<=I25,"Yes","No")) -> Yes | M25: AUC-005 | N25: Drift QA evidence for ISO 42001 readiness
A26: REQ-2026-022 | B26: 46130 | C26: SVC-015 | D26: Vendor Assessment | E26: Claims | F26: High | G26: Sarah Mitchell | H26: Open | I26: 46160 | K26: =IF(J26="",TODAY()-B26,J26-B26) -> 110 | L26: =IF(J26="","Open",IF(J26<=I26,"Yes","No")) -> Open | M26: AUC-019 | N26: Tractable security review refresh - ACT-005
A27: REQ-2026-023 | B27: 46135 | C27: SVC-009 | D27: DPIA | E27: Legal and Compliance | F27: Medium | G27: Rebecca Lloyd | H27: In Progress | I27: 46149 | K27: =IF(J27="",TODAY()-B27,J27-B27) -> 105 | L27: =IF(J27="","Open",IF(J27<=I27,"Yes","No")) -> Open | M27: AUC-008 | N27: Compliance RAG corpus expansion DPIA
A28: REQ-2026-024 | B28: 46141 | C28: SVC-001 | D28: New Use Case Intake | E28: Actuarial | F28: Medium | G28: Daniel O'Reilly | H28: Open | I28: 46162 | K28: =IF(J28="",TODAY()-B28,J28-B28) -> 99 | L28: =IF(J28="","Open",IF(J28<=I28,"Yes","No")) -> Open | M28: AUC-018 | N28: Reserving assistant scope extension

Sheet KRI Tracking
A1: KRI Tracking - Key Risk Indicators for AI Security and Governance
A2: Threshold-based KRIs reported monthly to AI Governance Forum and Risk Committee. Owner AI Security Manager.
A3: Back to Dashboard | B3: Open ID Glossary
A4: KRI ID | B4: KRI Name | C4: Linked Risk ID | D4: Linked Use Case/Vendor | E4: Threshold (Amber) | F4: Threshold (Red) | G4: Current Value | H4: Target Value | I4: Trend | J4: Breach Status | K4: Owner | L4: Action / Escalation | M4: Last Review | N4: Escalation Flag | O4: KRI Summary
A5: KRI-001 | B5: Models with material drift in last 30 days | C5: RSK-001 | D5: AUC-001,AUC-009,AUC-010,AUC-018 | E5: 2 | F5: 4 | G5: 1 | I5: Improving | J5: =IF(G5>=F5,"Red",IF(G5>=E5,"Amber","Green")) -> Green | K5: Mohammed Iqbal | L5: One model under remediation; champion-challenger live; review at AIGF May-26 | M5: 02/05/2026 | N5: =IF(J5="Red","Escalate to AIGF",IF(OR(J5="Amber",I5="Deteriorating"),"Monitor at next AIGF","BAU")) -> BAU | O5: Total KRIs | P5: =COUNTA(A5:A13) -> 9
A6: KRI-002 | B6: Tier-1 models without current monitoring coverage | C6: RSK-002 | D6: AUC-002,AUC-019 | E6: 1 | F6: 2 | I6: Stable | J6: =IF(G6>=F6,"Red",IF(G6>=E6,"Amber","Green")) -> Green | K6: Mohammed Iqbal | L6: Coverage 100% across Tier-1; maintain BAU | M6: 02/05/2026 | N6: =IF(J6="Red","Escalate to AIGF",IF(OR(J6="Amber",I6="Deteriorating"),"Monitor at next AIGF","BAU")) -> BAU | O6: Red Breaches | P6: =COUNTIF(J5:J13,"Red") -> 0
A7: KRI-003 | B7: Pricing fairness review breaches outstanding | C7: RSK-001 | D7: AUC-001,AUC-010,AUC-015,AUC-018 | E7: 1 | F7: 3 | I7: Stable | J7: =IF(G7>=F7,"Red",IF(G7>=E7,"Amber","Green")) -> Green | K7: Helen Carter | L7: Q1 review clean; Q2 review scheduled Jun-26 | M7: 02/05/2026 | N7: =IF(J7="Red","Escalate to AIGF",IF(OR(J7="Amber",I7="Deteriorating"),"Monitor at next AIGF","BAU")) -> BAU | O7: Amber | P7: =COUNTIF(J5:J13,"Amber") -> 2
A8: KRI-004 | B8: Customer-facing AI complaints linked to AI behaviour (rolling 90d) | C8: RSK-005 | D8: AUC-004,AUC-011,AUC-020 | E8: 5 | F8: 10 | G8: 3 | H8: <=2 | I8: Improving | J8: =IF(G8>=F8,"Red",IF(G8>=E8,"Amber","Green")) -> Green | K8: Olivia Bennett | L8: Output filter retuned; complaint root-cause review live | M8: 02/05/2026 | N8: =IF(J8="Red","Escalate to AIGF",IF(OR(J8="Amber",I8="Deteriorating"),"Monitor at next AIGF","BAU")) -> BAU | O8: Green | P8: =COUNTIF(J5:J13,"Green") -> 7
A9: KRI-005 | B9: Vulnerable customer cases handled outside specialist team | C9: RSK-012 | D9: AUC-002,AUC-011 | E9: 2 | F9: 5 | G9: 1 | I9: Stable | J9: =IF(G9>=F9,"Red",IF(G9>=E9,"Amber","Green")) -> Green | K9: Olivia Bennett | L9: One case under PIR; routing rule update in flight | M9: 02/05/2026 | N9: =IF(J9="Red","Escalate to AIGF",IF(OR(J9="Amber",I9="Deteriorating"),"Monitor at next AIGF","BAU")) -> BAU | O9: Improving Trend | P9: =COUNTIF(I5:I13,"Improving") -> 3
A10: KRI-006 | B10: Sanctions/fraud false-negative incidents (rolling 90d) | C10: RSK-003 | D10: AUC-003,AUC-014 | E10: 1 | F10: 2 | I10: Improving | J10: =IF(G10>=F10,"Red",IF(G10>=E10,"Amber","Green")) -> Green | K10: Helen Carter | L10: No detected FN; vendor signals improving | M10: 02/05/2026 | N10: =IF(J10="Red","Escalate to AIGF",IF(OR(J10="Amber",I10="Deteriorating"),"Monitor at next AIGF","BAU")) -> BAU | O10: Deteriorating Trend | P10: =COUNTIF(I5:I13,"Deteriorating") -> 1
A11: KRI-007 | B11: DLP exceptions raised on GenAI tools (per month) | C11: RSK-008 | D11: AUC-004,AUC-006,AUC-013,AUC-016 | E11: 10 | F11: 20 | G11: 14 | H11: <=8 | I11: Deteriorating | J11: =IF(G11>=F11,"Red",IF(G11>=E11,"Amber","Green")) -> Amber | K11: Karen Holloway | L11: Targeted training to top-3 BUs; Purview labels reviewed | M11: 02/05/2026 | N11: =IF(J11="Red","Escalate to AIGF",IF(OR(J11="Amber",I11="Deteriorating"),"Monitor at next AIGF","BAU")) -> Monitor at next AIGF
A12: KRI-008 | B12: Document AI extraction reject rate | C12: RSK-006 | D12: AUC-005,AUC-012,AUC-019,AUC-022 | E12: 4 | F12: 8 | G12: 3 | H12: <=3 | I12: Stable | J12: =IF(G12>=F12,"Red",IF(G12>=E12,"Amber","Green")) -> Green | K12: Mohammed Iqbal | L12: Within target; weekly QA continues | M12: 02/05/2026 | N12: =IF(J12="Red","Escalate to AIGF",IF(OR(J12="Amber",I12="Deteriorating"),"Monitor at next AIGF","BAU")) -> BAU
A13: KRI-009 | B13: Cloud configuration drift on AI workloads | C13: RSK-010 | D13: AUC-006,AUC-009,AUC-017,AUC-021 | E13: 2 | F13: 5 | G13: 2 | I13: Stable | J13: =IF(G13>=F13,"Red",IF(G13>=E13,"Amber","Green")) -> Amber | K13: Karen Holloway | L13: Two findings open; remediation due 31/05/2026 | M13: 02/05/2026 | N13: =IF(J13="Red","Escalate to AIGF",IF(OR(J13="Amber",I13="Deteriorating"),"Monitor at next AIGF","BAU")) -> Monitor at next AIGF

Sheet Risk Quantification
A1: Risk Quantification - AI and AI-Security Risk Register
A2: Quantified AI risk register. Likelihood and Impact on 1-5 scale (5 = highest). Residual scoring after current control environment. Owner CRO and AI Security Manager.
A3: Back to Dashboard | B3: Open ID Glossary
A4: Risk ID | B4: Risk Title | C4: Linked Use Case IDs | D4: Linked Vendor IDs | E4: Inherent Likelihood (1-5) | F4: Inherent Impact (1-5) | G4: Inherent Score | H4: Control Environment Summary | I4: Residual Likelihood (1-5) | J4: Residual Impact (1-5) | K4: Residual Score | L4: Quantified Exposure | M4: Risk Treatment | N4: Treatment Action ID | O4: Owner | Q4: Risk Summary (formula-driven)
A5: RSK-001 | B5: Model performance drift causing pricing/UW losses | C5: AUC-001,AUC-010,AUC-018 | E5: 4 | F5: 4 | G5: =E5*F5 -> 16 | H5: Drift monitoring (CTL-005), champion-challenger, model registry, quarterly model assurance. | I5: 2 | J5: 4 | K5: =I5*J5 -> 8 | L5: 6.5 | M5: Mitigate | N5: ACT-001 | O5: Mohammed Iqbal | Q5: Total Risks | R5: =COUNTA(A5:A17) -> 13
A6: RSK-002 | B6: Claims model misclassification harming customers | C6: AUC-002,AUC-019 | D6: VEN-007 | E6: 4 | F6: 4 | G6: =E6*F6 -> 16 | H6: Human override, monitoring, sample QA, complaints linkage. | I6: 2 | J6: 4 | K6: =I6*J6 -> 8 | L6: 4.2 | M6: Mitigate | N6: ACT-003 | O6: Mohammed Iqbal | Q6: High/Critical Inherent (>=15) | R6: =COUNTIF(G5:G17,">=15") -> 9
A7: RSK-003 | B7: Fraud model false negatives leading to leakage | C7: AUC-003,AUC-014 | D7: VEN-002,VEN-005 | E7: 4 | F7: 3 | G7: =E7*F7 -> 12 | H7: SIU feedback loop, threshold tuning, vendor signals. | I7: 3 | J7: 3 | K7: =I7*J7 -> 9 | L7: 3 | M7: Mitigate | N7: ACT-004 | O7: Helen Carter | Q7: High/Critical Residual (>=15) | R7: =COUNTIF(K5:K17,">=15") -> 0
A8: RSK-004 | B8: Pricing/fairness bias against protected groups | C8: AUC-001,AUC-010,AUC-015,AUC-018 | E8: 3 | F8: 5 | G8: =E8*F8 -> 15 | H8: Fairness reviews (CTL-014), Consumer Duty oversight, MI. | I8: 2 | J8: 4 | K8: =I8*J8 -> 8 | L8: 5.5 | M8: Mitigate | N8: ACT-006 | O8: Helen Carter | Q8: Total Quantified Exposure | R8: =SUM(L5:L17) -> 53.7
A9: RSK-005 | B9: LLM hallucination delivered to customer | C9: AUC-004,AUC-011,AUC-013,AUC-016,AUC-020 | D9: VEN-001 | E9: 4 | F9: 4 | G9: =E9*F9 -> 16 | H9: Output filters (CTL-010), human-in-the-loop, sample QA, restricted corpora. | I9: 2 | J9: 4 | K9: =I9*J9 -> 8 | L9: 4.8 | M9: Mitigate | N9: ACT-007 | O9: Olivia Bennett | Q9: Risks Mitigating | R9: =COUNTIF(M5:M17,"Mitigate") -> 13
A10: RSK-006 | B10: Model accuracy degradation in document AI | C10: AUC-005,AUC-019 | D10: VEN-003,VEN-007 | E10: 3 | F10: 3 | G10: =E10*F10 -> 9 | H10: Vendor SLAs, sample QA, drift alerts. | I10: 2 | J10: 3 | K10: =I10*J10 -> 6 | L10: 1.8 | M10: Mitigate | N10: ACT-002 | O10: Mohammed Iqbal | Q10: Risks Accepted | R10: =COUNTIF(M5:M17,"Accept") -> 0
A11: RSK-007 | B11: Customer detriment from biased customer-facing AI | C11: AUC-002,AUC-003,AUC-011,AUC-020 | E11: 3 | F11: 5 | G11: =E11*F11 -> 15 | H11: Consumer Duty governance, fairness reviews, complaints monitoring. | I11: 2 | J11: 4 | K11: =I11*J11 -> 8 | L11: 4 | M11: Mitigate | N11: ACT-006 | O11: Olivia Bennett | Q11: Avg Residual Score | R11: =AVERAGE(K5:K17) -> 8.0769231
A12: RSK-008 | B12: Sensitive data leakage via prompt to GenAI | C12: AUC-004,AUC-006,AUC-007,AUC-008,AUC-013,AUC-017 | D12: VEN-001,VEN-006 | E12: 4 | F12: 4 | G12: =E12*F12 -> 16 | H12: DLP/Purview (CTL-006,CTL-013), sensitivity labels, training (CTL-016). | I12: 2 | J12: 4 | K12: =I12*J12 -> 8 | L12: 3.5 | M12: Mitigate | N12: ACT-010 | O12: Karen Holloway | Q12: Reduction vs Inherent | R12: =1-(SUM(K5:K17)/SUM(G5:G17)) -> 0.42934783
A13: RSK-009 | B13: Document AI extraction error leading to wrong claim payment | C13: AUC-005,AUC-019 | D13: VEN-003,VEN-007 | E13: 3 | F13: 4 | G13: =E13*F13 -> 12 | H13: Engineer/handler review, sample QA, recovery process. | I13: 2 | J13: 4 | K13: =I13*J13 -> 8 | L13: 2.4 | M13: Mitigate | N13: ACT-002 | O13: James Whitfield
A14: RSK-010 | B14: Cloud misconfiguration exposing AI workloads | C14: AUC-006,AUC-009,AUC-017,AUC-021 | D14: VEN-006,VEN-008,VEN-009 | E14: 3 | F14: 5 | G14: =E14*F14 -> 15 | H14: CSPM, IaC, SOC monitoring, IAM controls. | I14: 2 | J14: 5 | K14: =I14*J14 -> 10 | L14: 6 | M14: Mitigate | N14: ACT-011 | O14: Karen Holloway
A15: RSK-011 | B15: Regulatory breach (Consumer Duty / fairness / FCA) | C15: AUC-001,AUC-003,AUC-010,AUC-014,AUC-015,AUC-016 | E15: 3 | F15: 5 | G15: =E15*F15 -> 15 | H15: Compliance oversight, fairness review, board reporting. | I15: 2 | J15: 5 | K15: =I15*J15 -> 10 | L15: 7.5 | M15: Mitigate | N15: ACT-012 | O15: Rebecca Lloyd
A16: RSK-012 | B16: Vulnerable customer outcomes worsened by AI | C16: AUC-004,AUC-011,AUC-016,AUC-020 | D16: VEN-004 | E16: 3 | F16: 5 | G16: =E16*F16 -> 15 | H16: Specialist routing, vulnerable customer policy, monitoring. | I16: 2 | J16: 4 | K16: =I16*J16 -> 8 | L16: 3 | M16: Mitigate | N16: ACT-013 | O16: Olivia Bennett
A17: RSK-013 | B17: Audit/regulatory finding due to evidence gaps | C17: AUC-007,AUC-014,AUC-022 | E17: 3 | F17: 4 | G17: =E17*F17 -> 12 | H17: Evidence library, control testing, ISO 42001 readiness. | I17: 2 | J17: 3 | K17: =I17*J17 -> 6 | L17: 1.5 | M17: Mitigate | N17: ACT-014 | O17: Sarah Mitchell

Sheet Third-Party Risk Services
A1: Third-Party Risk - AI Vendors and Service Providers
A2: AI-relevant suppliers and service providers. Owner Third-Party Risk Lead Sarah Mitchell. Cadence annual review; quarterly for Tier 1.
A3: Back to Dashboard | B3: Open ID Glossary
A4: Vendor ID | B4: Supplier Name | C4: Service Provided | D4: Linked Use Cases | E4: Hosting Model | F4: Data Classification Handled | G4: Due Diligence Status | H4: Security Review Status | I4: Privacy Review Status | J4: Contract Renewal Date | K4: Residual Risk | L4: Key Findings | M4: Action Required | N4: Exit Dependency | O4: Owner | P4: Days to Renewal | Q4: Vendor Summary
A5: VEN-001 | B5: Microsoft (Azure OpenAI / M365 Copilot) | C5: LLM platform and productivity copilots | D5: AUC-004,AUC-006,AUC-007,AUC-008,AUC-013,AUC-016 | E5: SaaS | F5: Confidential | G5: Complete | H5: Complete | I5: Complete | J5: 31/03/2027 | K5: Amber | L5: Strong contractual terms; data residency UK; ongoing review of subprocessor list. | M5: Quarterly subprocessor review; refresh DPIA after RDM-002 | N5: High - core platform | O5: Sarah Mitchell | Q5: Total Vendors | R5: =COUNTA(A5:A20) -> 16
A6: VEN-002 | B6: Featurespace | C6: Fraud analytics and adaptive behavioural analytics | D6: AUC-003 | E6: SaaS | F6: Restricted | G6: Complete | H6: Complete | I6: Complete | J6: 30/06/2026 | K6: Green | L6: Strong assurance; ISO 27001 plus SOC 2 Type II current. | M6: Renewal negotiation; review pricing tier | N6: Medium | O6: Sarah Mitchell | Q6: Tier 1 / High Criticality | R6: =COUNTIF(N5:N20,"High*") -> 8
A7: VEN-003 | B7: ABBYY | C7: Document intelligence (OCR/NLP) | D7: AUC-005 | E7: Hybrid | F7: Confidential | G7: Complete | H7: Complete | I7: In Progress | J7: 15/09/2026 | K7: Amber | L7: Privacy review pending refresh after vendor sub-processor change. | M7: Complete privacy review by 30/06/2026 (ACT-002) | N7: Medium | O7: Sarah Mitchell | Q7: Amber Residual | R7: =COUNTIF(K5:K20,"Amber") -> 6
A8: VEN-004 | B8: NICE Nexidia | C8: Speech analytics for vulnerable customer detection | D8: AUC-011 | E8: SaaS | F8: Restricted | G8: Complete | H8: Complete | I8: Complete | J8: 30/11/2026 | K8: Green | L8: All assurance current; audit-log review monthly. | M8: Maintain BAU monitoring | N8: Medium | O8: Sarah Mitchell | Q8: Green Residual | R8: =COUNTIF(K5:K20,"Green") -> 10
A9: VEN-005 | B9: LexisNexis Risk Solutions | C9: Sanctions and PEP screening | D9: AUC-014 | E9: SaaS | F9: Restricted | G9: Complete | H9: Complete | I9: Complete | J9: 28/02/2027 | K9: Green | L9: ISO 27001 verified; FCA-aligned controls. | M9: Annual recertification scheduled Feb-27 | N9: High - regulatory | O9: Sarah Mitchell | Q9: Red Residual | R9: =COUNTIF(K5:K20,"Red") -> 0
A10: VEN-006 | B10: Microsoft Sentinel + Copilot for Security | C10: SOC SIEM/SOAR with AI assist | D10: AUC-017 | E10: SaaS | F10: Restricted | G10: Complete | H10: Complete | I10: Complete | J10: 31/03/2027 | K10: Green | L10: Tightly integrated with M365 estate. | M10: Coverage expansion to Azure subscriptions (RDM-010) | N10: High | O10: Karen Holloway | Q10: DD/Sec/Privacy In Progress | R10: =COUNTIF(G5:G20,"In Progress")+COUNTIF(H5:H20,"In Progress")+COUNTIF(I5:I20,"In Progress") -> 4
A11: VEN-007 | B11: Tractable | C11: Computer-vision damage estimation | D11: AUC-019 | E11: SaaS | F11: Confidential | G11: Complete | H11: In Progress | I11: Complete | J11: 30/04/2026 | K11: Amber | L11: Security review refresh in progress; cycle-time benefits material. | M11: Complete security review (ACT-005) | N11: Medium | O11: Sarah Mitchell
A12: VEN-008 | B12: Snowflake | C12: Cloud data platform for AI workloads | D12: Cross-cutting | E12: SaaS | F12: Confidential | G12: Complete | H12: Complete | I12: Complete | J12: 30/09/2026 | K12: Green | L12: Strong key management; private connectivity in place. | M12: Annual review on track | N12: High | O12: Karen Holloway
A13: VEN-009 | B13: Databricks | C13: MLOps and ML feature platform | D13: AUC-001,AUC-002,AUC-009,AUC-010,AUC-018,AUC-022 | E13: PaaS | F13: Confidential | G13: Complete | H13: Complete | I13: Complete | J13: 31/12/2026 | K13: Green | L13: Core MLOps; UAP and SCIM integration in place. | M13: Continue tier-1 vendor monitoring | N13: High | O13: Karen Holloway
A14: VEN-010 | B14: OneTrust | C14: Privacy and DPIA tooling | D14: Cross-cutting | E14: SaaS | F14: Internal | G14: Complete | H14: Complete | I14: Complete | J14: 31/01/2027 | K14: Green | L14: Used to administer DPIAs and AI inventory metadata. | M14: BAU | N14: Medium | O14: Rebecca Lloyd
A15: VEN-011 | B15: ServiceNow | C15: ITSM intake / requests / changes | D15: Cross-cutting | E15: SaaS | F15: Internal | G15: Complete | H15: Complete | I15: Complete | J15: 30/06/2026 | K15: Green | L15: Underpins intake and request workflow. | M15: Maintain BAU; renewal in flight | N15: High | O15: Karen Holloway
A16: VEN-012 | B16: Hugging Face Enterprise | C16: Internal model repository | D16: AUC-009 | E16: SaaS | F16: Internal | G16: In Progress | H16: In Progress | I16: Not Required | J16: 31/07/2026 | K16: Amber | L16: Initial assessment underway; restricted use case. | M16: Complete DD by 30/06/2026 (ACT-009) | N16: Low | O16: Mohammed Iqbal
A17: VEN-013 | B17: Persistent Systems | C17: ML engineering augmentation partner | D17: AUC-009 | E17: Vendor Hosted | F17: Confidential | G17: Complete | H17: Complete | I17: Complete | J17: 30/06/2026 | K17: Amber | L17: Renewal in flight; SoW being refreshed for AI-specific clauses. | M17: Update contract clauses for AI; finalise renewal (ACT-008) | N17: Medium | O17: Sarah Mitchell
A18: VEN-014 | B18: Salesforce Service Cloud + Einstein | C18: CRM with AI features in customer ops | D18: AUC-004,AUC-011 | E18: SaaS | F18: Confidential | G18: Complete | H18: Complete | I18: Complete | J18: 31/05/2026 | K18: Green | L18: Einstein features disabled until AI feature review completes. | M18: Confirm Einstein-feature posture (RDM-001) | N18: High | O18: Olivia Bennett
A19: VEN-015 | B19: Splunk | C19: SIEM / log analytics (transitional) | D19: AUC-009,AUC-017 | E19: SaaS | F19: Restricted | G19: Complete | H19: Complete | I19: Complete | J19: 31/12/2026 | K19: Amber | L19: Migration to Sentinel underway; dual-running risk to be retired. | M19: Complete migration by Q4 2026 (RDM-010) | N19: High - transitional | O19: Karen Holloway
A20: VEN-016 | B20: KPMG (advisory) | C20: ISO 42001 readiness advisory | D20: Cross-cutting | E20: Vendor Hosted | F20: Internal | G20: Complete | H20: Not Required | I20: Not Required | J20: 30/09/2026 | K20: Green | L20: Advisory partner for the ISO 42001 readiness programme. | M20: Phase complete; transition to internal ownership | N20: Low | O20: Sarah Mitchell

Sheet Incident Analysis
A1: Incident Analysis - AI / AI-Security Incidents and Near Misses
A2: Incident register for AI-related events. Owner AI Security Manager and Incident Response. Cadence each incident has a PIR.
A3: Back to Dashboard | B3: Open ID Glossary
A4: Incident ID | B4: Date | C4: Category | D4: Severity | E4: Linked Use Case/Service/Vendor/Risk | F4: Summary | G4: Root Cause | H4: Impact | I4: Containment Action | J4: Remediation Action | K4: Owner | L4: Lessons Learned | M4: Closure Status | N4: PIR Reference | P4: Incident Summary (rolling 90d)
A5: INC-001 | B5: 46055 | C5: Model Drift | D5: Sev 2 | E5: AUC-002,SVC-003,RSK-002 | F5: Claims FNOL model showed elevated false-fast-track rate over 7-day window; flagged by drift monitor. | G5: Seasonal motor claim composition shift not captured in training data. | H5: Approx 60 claims mis-routed; later re-routed; no customer detriment confirmed. | I5: Champion-challenger fallback enabled within 4 hours. | J5: Retraining with refreshed data; revised drift threshold; drift monitor cadence increased. | K5: Mohammed Iqbal | L5: Add seasonality features to training set; tighten drift thresholds. | M5: Closed | N5: PIR-001 | P5: Total Incidents | Q5: =COUNTA(A5:A12) -> 8
A6: INC-002 | B6: 46062 | C6: Output Quality | D6: Sev 3 | E6: AUC-001,AUC-010,SVC-002,RSK-001 | F6: UW pricing engine produced an unusual quote on a high-value commercial property. | G6: Outlier feature interaction not handled by guardrail. | H6: One quote pulled before issue to customer; broker informed. | I6: Quote withdrawn within 1 hour. | J6: Added guardrail rule; updated pricing committee escalation criteria. | K6: Helen Carter | L6: Strengthen pre-issue checks for outlier features. | M6: Closed | N6: PIR-002 | P6: Sev 1 | Q6: =COUNTIF(D5:D12,"Sev 1") -> 0
A7: INC-003 | B7: 46065 | C7: Output Quality | D7: Sev 2 | E7: AUC-004,SVC-005,RSK-005,VEN-001 | F7: Voice agent assist surfaced an inaccurate suggestion citing an outdated FAQ. | G7: Source FAQ not refreshed in vector index. | H7: Agent caught error before customer relay; minor delay in handling. | I7: Suggestion suppression triggered; manual workaround used. | J7: Index refresh automation; updated content owner cadence; sample-QA increase. | K7: Olivia Bennett | L7: Strengthen content-freshness pipeline. | M7: Closed | N7: PIR-003 | P7: Sev 2 | Q7: =COUNTIF(D5:D12,"Sev 2") -> 4
A8: INC-004 | B8: 46073 | C8: Data Leakage | D8: Sev 3 | E8: AUC-006,SVC-007,RSK-008,VEN-001 | F8: Restricted-label content briefly accessible via M365 Copilot summary by an unintended audience. | G8: Sensitivity-label inheritance gap on a SharePoint site. | H8: Single low-impact instance; data was Internal not Confidential. | I8: Site labelling corrected within 2 hours; user notified. | J8: Sensitivity-label review cycle introduced; Purview policy refresh. | K8: Karen Holloway | L8: Tighten label inheritance for new sites. | M8: Closed | N8: PIR-004 | P8: Sev 3 | Q8: =COUNTIF(D5:D12,"Sev 3") -> 4
A9: INC-005 | B9: 46084 | C9: Vendor Outage | D9: Sev 2 | E9: AUC-002,AUC-019,SVC-003,VEN-007 | F9: Tractable damage estimation API degraded for 90 minutes during peak FNOL window. | G9: Vendor backend incident. | H9: Engineer dispatch process reverted to manual triage. | I9: Manual fallback per BCP. | J9: Vendor SLA exceptions claimed; resilience plan updated. | K9: James Whitfield | L9: Tabletop annual exercise to include this scenario. | M9: Closed | N9: PIR-005 | P9: Closed | Q9: =COUNTIF(M5:M12,"Closed") -> 8
A10: INC-006 | B10: 46095 | C10: Output Quality | D10: Sev 3 | E10: AUC-005,SVC-006,RSK-006,VEN-003 | F10: ABBYY extraction error on medical certificate format. | G10: New medical-form template not in training corpus. | H10: Three claims required manual re-keying; no customer detriment. | I10: Quarantine of affected template; manual handling. | J10: Vendor template update; QA sample increase. | K10: Mohammed Iqbal | L10: Confirm template update SLAs with vendor. | M10: Closed | N10: PIR-006 | P10: Open | Q10: =COUNTIF(M5:M12,"Open")+COUNTIF(M5:M12,"Under Review") -> 0
A11: INC-007 | B11: 46103 | C11: Access Violation | D11: Sev 2 | E11: AUC-017,SVC-014 | F11: Privileged role briefly granted in error to a SOC analyst beyond least-privilege baseline. | G11: Misconfigured PAM bundle. | H11: No data accessed inappropriately; logged and reviewed. | I11: Role removed within 30 minutes; access review scheduled. | J11: PAM bundles re-baselined; review every quarter. | K11: Karen Holloway | L11: Add automated re-baseline test. | M11: Closed | N11: PIR-007 | P11: Vendor-driven | Q11: =COUNTIF(C5:C12,"Vendor Outage") -> 1
A12: INC-008 | B12: 46114 | C12: Output Quality | D12: Sev 3 | E12: AUC-004,AUC-013,SVC-005,RSK-005,VEN-001 | F12: Hallucinated reference appeared in policy-wording smart search response. | G12: Filter regression after vendor model update. | H12: Surface only on internal QA sample; no customer impact. | I12: Hallucination filter rolled back to prior version. | J12: Filter re-tuned; vendor change-window controls strengthened. | K12: Olivia Bennett | L12: Vendor change windows must align with QA windows. | M12: Closed | N12: PIR-008 | P12: Output Quality | Q12: =COUNTIF(C5:C12,"Output Quality") -> 4

Sheet Compliance Mapping
A1: Compliance Mapping V2 - ISO/IEC 42001 Control Library with Audit Readiness Detail
A2: Workbook control library mapped to ISO/IEC 42001 (primary), ISO 27001, ISO 27701, ISO 31000, NIST AI RMF and FCA expectations. Each control specifies typical objective evidence expected, audit test focus, likely interview owner and potential nonconformity if absent. Owner AI Security Manager. Cadence quarterly.
A3: Back to Dashboard | B3: Open ID Glossary
A4: Control ID | B4: Control Statement | C4: ISO 42001 Clause | D4: Annex A Reference | E4: Other Framework Reference | F4: Control Objective Summary | G4: Linked Policy | H4: Owner | I4: Linked Use Cases | J4: Linked Services | K4: Implementation Status | L4: Evidence ID | M4: Review Frequency | N4: Audit Test Focus | O4: Likely Interview Owner | P4: Residual Gap | Q4: Potential Nonconformity if Absent | R4: Remediation Action ID | T4: Compliance Mapping V2 Summary
A5: CTL-001 | B5: AI use case intake, materiality assessment and approval gateway prior to development. | C5: Clause 6.1 + 8.1 | D5: A.6.2.2 | E5: NIST AI RMF Govern 1.1 | F5: Ensure every AI use case is risk-tiered and approved before resources are committed. | G5: POL-001 | H5: Daniel O'Reilly | I5: AUC-001,AUC-010,AUC-015,AUC-018 | J5: SVC-001,SVC-002,SVC-013 | K5: Implemented | L5: EVD-001 | M5: Quarterly | N5: Sample 3 use cases and trace from intake form through AIGF approval to deployment. | O5: AI Security Manager / AIGF Chair | P5: No material gaps | Q5: Major - missing intake gateway is a foundational nonconformity | T5: Total Controls | U5: =COUNTA(A5:A20) -> 16
A6: CTL-002 | B6: Independent challenge of material AI/ML models prior to deployment and at scheduled intervals. | C6: Clause 9.1 + 9.2 | D6: A.6.2.6 | E6: NIST AI RMF Measure 2.3; PRA SS1/23 | F6: Provide independent assurance over material model risk at deployment and on cadence. | G6: POL-004 | H6: Mohammed Iqbal | I6: AUC-002,AUC-003,AUC-014,AUC-019 | J6: SVC-003,SVC-004,SVC-012 | K6: Implemented | L6: EVD-002 | M6: Annual | N6: Request validation pack for AUC-014; trace to MRC minutes; check independent reviewer. | O6: Mohammed Iqbal / MRM Lead | P6: Independent validation backlog of one model | Q6: Major - inadequate independent challenge is high-impact 42001 finding | R6: ACT-004 | T6: Implemented | U6: =COUNTIF(K5:K20,"Implemented") -> 12
A7: CTL-003 | B7: Customer-facing AI subjected to fairness and Consumer Duty review prior to launch and at quarterly intervals. | C7: Clause 6.1.4 + 9.1 | D7: A.6.2.7 | E7: FCA Consumer Duty; NIST AI RMF Measure 2.11 | F7: Ensure customer outcomes are equitable and tested for bias before and after launch. | G7: POL-002 | H7: Olivia Bennett | I7: AUC-002,AUC-003,AUC-004,AUC-011,AUC-016,AUC-020 | J7: SVC-005,SVC-009 | K7: Implemented | L7: EVD-011 | M7: Quarterly | N7: Sample 2 customer journeys; trace through fairness review and complaints theme analysis. | O7: Olivia Bennett / DPO | P7: No material gaps | Q7: Major - bias gaps are high-priority 42001 audit focus | T7: Partially Implemented | U7: =COUNTIF(K5:K20,"Partially Implemented") -> 4
A8: CTL-004 | B8: Document AI extraction QA sampling and downstream impact monitoring. | C8: Clause 9.1 | D8: A.6.2.8 | E8: ISO 27001 A.5.34 | F8: Detect extraction error and downstream impact early through structured QA sampling. | G8: POL-006 | H8: Mohammed Iqbal | I8: AUC-005,AUC-012,AUC-019 | J8: SVC-006,SVC-011 | K8: Implemented | L8: EVD-005 | M8: Monthly | N8: Re-perform sample QA on a small selection; trace reject-rate trend. | O8: Mohammed Iqbal / Claims Ops | P8: No material gaps | Q8: Minor - typically observation | T8: Planned/Not Implemented | U8: =COUNTIF(K5:K20,"Planned")+COUNTIF(K5:K20,"Not Implemented") -> 0
A9: CTL-005 | B9: Production model monitoring (drift, performance, bias) and alerting via SIEM. | C9: Clause 9.1 | D9: A.6.2.8 | E9: NIST AI RMF Manage 4.1 | F9: Continuously monitor production AI for drift, degradation and bias with timely alerting. | G9: POL-004 | H9: Mohammed Iqbal | I9: AUC-001,AUC-002,AUC-005,AUC-009,AUC-010,AUC-018,AUC-019,AUC-021,AUC-022 | J9: SVC-002,SVC-003,SVC-010,SVC-014 | K9: Implemented | L9: EVD-009 | M9: Continuous | N9: Trace drift alert through to ServiceNow ticket and remediation; sample two weeks' alerts. | O9: Mohammed Iqbal (MLOps Lead) | P9: 8 percent Tier-2 model coverage gap | Q9: Major - Tier-1 monitoring gaps are high-impact 42001 finding | R9: ACT-001 | T9: ISO 42001 Clauses Mapped | U9: =SUMPRODUCT(--(LEN(C5:C20)>0)) -> 16
A10: CTL-006 | B10: GenAI usage controlled by sensitivity labels, DLP, prompt logging and corpus restrictions. | C10: Clause 7.4 + 8.1 | D10: A.7.4 | E10: ISO 27701 7.2.2; GDPR/UK DPA | F10: Prevent sensitive or restricted data leaving the perimeter via GenAI tools. | G10: POL-008 | H10: Karen Holloway | I10: AUC-004,AUC-006,AUC-007,AUC-008,AUC-013,AUC-016,AUC-017 | J10: SVC-005,SVC-007,SVC-008,SVC-009,SVC-014 | K10: Partially Implemented | L10: EVD-006 | M10: Monthly | N10: Test sensitivity-label inheritance on a sample of legacy SharePoint sites. | O10: Karen Holloway / DPO | P10: Label inheritance gap on legacy SharePoint sites | Q10: Major - data leakage path open to GenAI is high-impact 42001 finding | R10: ACT-010 | T10: Annex A Controls Mapped | U10: =SUMPRODUCT(--(LEN(D5:D20)>0)) -> 16
A11: CTL-007 | B11: Document AI vendor change windows controlled and aligned with QA windows. | C11: Clause 8.1 | D11: A.6.2.10 | E11: ISO 27001 A.5.23 | F11: Vendor model updates do not bypass change control and QA assurance. | G11: POL-009 | H11: Sarah Mitchell | I11: AUC-005,AUC-012 | J11: SVC-006,SVC-011 | K11: Implemented | L11: EVD-005 | M11: Per change | N11: Trace one vendor change through approval, QA window and post-change validation. | O11: Sarah Mitchell / Mohammed Iqbal | P11: No material gaps | Q11: Minor - observation if change-window control weak | T11: Major NC Risk if Absent | U11: =COUNTIF(Q5:Q20,"Major*") -> 14
A12: CTL-008 | B12: Human-in-the-loop required for customer-impacting decisions. | C12: Clause 6.1.4 | D12: A.6.2.5 | E12: NIST AI RMF Govern 5.1; FCA Consumer Duty | F12: Material customer-impacting decisions retain human accountability. | G12: POL-002 | H12: Olivia Bennett | I12: AUC-002,AUC-003,AUC-004,AUC-011,AUC-014,AUC-019,AUC-020 | J12: SVC-003,SVC-004,SVC-005,SVC-009,SVC-012 | K12: Implemented | L12: EVD-004 | M12: Quarterly | N12: Sample 30 customer-facing decisions; verify HITL evidence on each. | O12: Olivia Bennett / Customer Ops Lead | P12: No material gaps | Q12: Major - missing HITL on customer decisions is foundational 42001 finding | T12: Minor NC Risk if Absent | U12: =COUNTIF(Q5:Q20,"Minor*") -> 2
A13: CTL-009 | B13: Third-party AI vendors complete due diligence including security, privacy and AI assurance prior to onboarding. | C13: Clause 8.1 | D13: A.7.3 | E13: ISO 27001 A.5.19; FCA SYSC 8 | F13: Vendors meet equivalent control expectations to internal AI services. | G13: POL-009 | H13: Sarah Mitchell | I13: AUC-004,AUC-005,AUC-006,AUC-008,AUC-013,AUC-017,AUC-019 | J13: SVC-015 | K13: Partially Implemented | L13: EVD-030 | M13: Per onboarding | N13: Sample one Tier-1 vendor pack end-to-end; trace contract, security and privacy assurance. | O13: Sarah Mitchell / TPRM Lead | P13: One Tier-1 vendor DD overdue (94 percent currency vs 100 percent target) | Q13: Major - inadequate vendor DD on Tier-1 is high-impact 42001 finding | R13: ACT-008 | T13: Controls with Open Gap | U13: =SUMPRODUCT((LEN(P5:P20)>0)*(P5:P20<>"No material gaps")) -> 6
A14: CTL-010 | B14: GenAI output filters and guardrails (PII redaction, hallucination filter, toxic content). | C14: Clause 8.1 | D14: A.6.2.11 | E14: NIST AI RMF Measure 2.5 | F14: Output controls prevent customer-facing harm from GenAI errors. | G14: POL-008 | H14: Olivia Bennett | I14: AUC-004,AUC-006,AUC-008,AUC-013,AUC-017 | J14: SVC-005,SVC-007,SVC-009,SVC-014 | K14: Implemented | L14: EVD-013 | M14: Monthly | N14: Re-perform a canonical hallucination regression test set; sample QA outputs. | O14: Olivia Bennett / Customer-Facing AI Lead | P14: No material gaps | Q14: Major - missing guardrails on customer-facing GenAI is high-impact 42001 finding | T14: Controls Mapped to FCA | U14: =COUNTIF(E5:E20,"*FCA*") -> 6
A15: CTL-011 | B15: Vendor exit and substitutability assessed for material AI providers. | C15: Clause 8.1 | D15: A.7.5 | E15: FCA SYSC; PRA Operational Resilience | F15: Substitutability is documented and tested for material AI vendors. | G15: POL-009 | H15: Sarah Mitchell | I15: AUC-001 to AUC-022 (material) | J15: SVC-015 | K15: Partially Implemented | L15: EVD-030 | M15: Annual | N15: Request exit plan for VEN-001 and VEN-006 and trace substitutability evidence. | O15: Sarah Mitchell / Procurement Director | P15: Exit plans incomplete for VEN-001 and VEN-006 | Q15: Major - missing exit plans is high-impact 42001 and PRA finding | R15: ACT-008 | T15: Controls Mapped to NIST AI RMF | U15: =COUNTIF(E5:E20,"*NIST AI RMF*") -> 8
A16: CTL-012 | B16: Pricing and underwriting model fairness review prior to release and quarterly. | C16: Clause 6.1.4 + 9.1 | D16: A.6.2.7 | E16: FCA Consumer Duty; NIST AI RMF Measure 2.11 | F16: Pricing and UW models do not produce unfair outcomes for protected groups. | G16: POL-002 | H16: Helen Carter | I16: AUC-001,AUC-010,AUC-015,AUC-018 | J16: SVC-002,SVC-013 | K16: Implemented | L16: EVD-010 | M16: Quarterly | N16: Sample fairness test for AUC-010; trace through pricing committee. | O16: Helen Carter / Chief Actuary | P16: No material gaps | Q16: Major - bias on pricing models is high-impact 42001 and FCA finding | T16: Implementation % | U16: =COUNTIF(K5:K20,"Implemented")/COUNTA(A5:A20) -> 0.75
A17: CTL-013 | B17: Logging and audit trail for AI prompts, outputs and model decisions retained per data classification policy. | C17: Clause 9.1 | D17: A.6.2.9 | E17: ISO 27001 A.8.15; ISO 27701 7.2.6 | F17: AI activity is fully accountable through tamper-resistant logs. | G17: POL-006 | H17: Karen Holloway | I17: AUC-004,AUC-006,AUC-007,AUC-008,AUC-013,AUC-017 | J17: SVC-005,SVC-007,SVC-008,SVC-009,SVC-014 | K17: Implemented | L17: EVD-017 | M17: Monthly | N17: Sample logs from Sentinel; verify retention and immutability. | O17: Karen Holloway / SOC Lead | P17: No material gaps | Q17: Major - logging gaps on AI activity is high-impact 42001 finding
A18: CTL-014 | B18: Independent fairness and bias testing for material customer-impacting models. | C18: Clause 9.2 | D18: A.6.2.7 | E18: NIST AI RMF Measure 2.11 | F18: Independent fairness testing complements first-line fairness reviews. | G18: POL-002 | H18: Helen Carter | I18: AUC-001,AUC-003,AUC-010,AUC-014,AUC-022 | J18: SVC-002,SVC-004,SVC-010,SVC-012,SVC-015 | K18: Implemented | L18: EVD-014 | M18: Annual | N18: Request independent fairness pack for AUC-014; trace to MRC minutes. | O18: Helen Carter / Independent Validator | P18: No material gaps | Q18: Major - lack of independent challenge on bias is high-impact 42001 finding
A19: CTL-015 | B19: Vulnerable customer routing and human handling for sensitive customer journeys. | C19: Clause 6.1.4 | D19: A.6.2.5 | E19: FCA Consumer Duty; FCA Vulnerable Customers | F19: Vulnerable customers receive specialist human handling, not AI-only outcomes. | G19: POL-002 | H19: Olivia Bennett | I19: AUC-004,AUC-011,AUC-016,AUC-020 | J19: SVC-005,SVC-009 | K19: Implemented | L19: EVD-011 | M19: Quarterly | N19: Sample 20 calls flagged by NLP; verify specialist routing. | O19: Olivia Bennett / Vulnerable Customer Lead | P19: No material gaps | Q19: Major - missing vulnerable customer routing is high-impact FCA and 42001 finding
A20: CTL-016 | B20: AI awareness and training programme for all colleagues using or supporting AI tools. | C20: Clause 7.2 + 7.3 | D20: A.7.6 | E20: ISO 27001 A.6.3 | F20: Colleagues are competent and aware before using AI tools. | G20: POL-001 | H20: Daniel O'Reilly | I20: AUC-006,AUC-007,AUC-008,AUC-016,AUC-017,AUC-021 | J20: SVC-007,SVC-008,SVC-009,SVC-014 | K20: Partially Implemented | L20: EVD-029 | M20: Annual | N20: Sample colleague competence records and interview 5 colleagues to test awareness. | O20: Daniel O'Reilly / HR L&D | P20: Training completion 86 percent vs 95 percent target | Q20: Major - low awareness commonly leads to major 42001 nonconformity | R20: ACT-014

Sheet Cloud Security Services
A1: Cloud Security Services - Controls Supporting AI Workloads
A2: Cloud security control inventory protecting AI workloads. Owner CISO and Head of Cloud. Cadence reviewed quarterly.
A3: Back to Dashboard
A4: Control Area | B4: Control / Service Description | C4: Linked Control ID | D4: Linked Use Cases/Services | E4: Implementation Status | F4: Tooling | G4: Owner | H4: Coverage | I4: Last Test Date | J4: Evidence Ref | K4: Notes
A5: Architecture Assurance | B5: Solution architecture review and threat modelling for new AI workloads with security sign-off. | C5: CTL-001 | D5: AUC-001,AUC-009,AUC-017 | E5: Implemented | F5: Internal review process; Microsoft Threat Modeling Tool | G5: Karen Holloway | H5: 100% new AI workloads | I5: 2026-04-22 | J5: EVD-009 | K5: Embedded into intake gate (SVC-001)
A6: Environment Segregation | B6: Logical separation of Production, UAT, Development and Sandbox; isolated AI experimentation. | C6: CTL-005 | D6: AUC-001,AUC-002,AUC-005,AUC-009,AUC-010 | E6: Implemented | F6: Azure landing zones; Databricks workspaces | G6: Karen Holloway | H6: 100% | I6: 2026-03-15 | J6: EVD-009 | K6: Sandbox accounts use synthetic data only
A7: Encryption (in transit) | B7: TLS 1.2+ enforced; service-to-service encryption; private endpoints used where supported. | C7: CTL-006 | D7: All AI workloads | E7: Implemented | F7: Azure Front Door; private endpoints; certificate management | G7: Karen Holloway | H7: 100% | I7: 2026-04-02 | J7: EVD-009 | K7: Quarterly cert validity scan
A8: Encryption (at rest) | B8: AES-256 with customer-managed keys for all classified AI training/feature stores. | C8: CTL-006 | D8: AUC-001,AUC-002,AUC-005,AUC-009,AUC-010 | E8: Implemented | F8: Azure Key Vault; Snowflake CMK | G8: Karen Holloway | H8: 100% | I8: 2026-04-02 | J8: EVD-009 | K8: Key rotation 12 months
A9: Logging | B9: Centralised logging of platform, model and prompt activity into SIEM; retention aligned to classification. | C9: CTL-013 | D9: All AI workloads | E9: Implemented | F9: Microsoft Sentinel; Splunk (transitional) | G9: Karen Holloway | H9: 98% | I9: 2026-04-18 | J9: EVD-017 | K9: Splunk migration completes Q4 2026 (RDM-010)
A10: Monitoring (Posture) | B10: Cloud Security Posture Management with policy-as-code and automated drift detection. | C10: CTL-005,CTL-013 | D10: All AI workloads | E10: Implemented | F10: Microsoft Defender for Cloud; Azure Policy | G10: Karen Holloway | H10: 100% | I10: 2026-04-20 | J10: EVD-021 | K10: Two findings open (KRI-009)
